Workbook

Sheet Team Log ins 
A1: SHIPHERO LOG IN CREDENTIALS
A2: Agent Name | B2: Email Address | C2: PASSWORD
A3: Godwin Reasol | B3: teamdani1@proton.me | C3: B6!mY2#vQ9@tL
A4: Claudette Ibong | B4: teamdani2@proton.me | C4: Q8@cN4!zR7$kM
A5: CherryTubongbanua | B5: teamdani3@proton.me | C5: W5#pK9@xT3!vH
A6: Lyra Miclat | B6: teamdani4@proton.me | C6: J7!rM2$yL8@qZ
A7: Joemica Cariño | B7: teamdani5@proton.me | C7: C4@vP9#nX6!kR
A8: Candy Laid | B8: teamdani6@proton.me | C8: F8$zQ3!mT7@wL
A9: Sofhia Mae Santiago | B9: teamdani7@proton.me | C9: L2#xV6@rK9!pN
A10: Dan Mae David | B10: teamdani8@outlook.com | C10: S9!qH4$wM2@zP

Sheet Team Info
A1: Agent Name | B1: Email Address | C1: Contact Number | D1: Birthday | E1: Home Address | F1: Baranggay | G1: Municipality | H1: Province | I1: Zip Code | J1: Landmark
A2: Danielle Ann Mari Crizaldo | B2: daniellecrizaldo781@gmail.com | C2: 9082352381 | D2: 36790 | E2: 005 | F2: Marahan 1 | G2: Alfonso | H2: Cavite | I2: 4123 | J2: Droolymacaroni
A3: Dan Mae David | B3: dnlldvd19@gmail.com | C3: 639665294367 | D3: 34108
A4: Godwin Arellano | B4: ghodwinreasol@gmail.com | C4: 9811265923 | D4: 36816
A5: Candy Laid | B5: laidcandy1@gmail.com | C5: 9190726863 | D5: 31947
A6: Claudette Ibong | B6: blueibong@gmail.com | C6: 9776239411 | D6: 35924
A7: Sofhia Mae Santiago | B7: sofhiamae102099@gmail.com | C7: 9050312839 | D7: 36453
A8: Cherry Rose Tubongbanua | B8: cherryrose201606@gmail.com | C8: 9233005980 | D8: 36668
A9: Lyra Miclat | B9: lyranacu1996@gmail.com | C9: 9754168344 | D9: 35305
A10: Joemica Carino | B10: joemica20@gmail.com | C10: 9630166253 | D10: 34352

Sheet TEAM STATS
A1: 46054
A2: WEEK: February 2 - February 8
A3: Daily Productivity
A4: NAME OF AGENT | B4: Weekly Target | C4: Weekly Actual | D4: 46055 | E4: 46056 | F4: 46057 | G4: 46058 | H4: 46059 | I4: 46060 | J4: 46061 | K4: % Productivity | L4: Final Score
D5: Mon | E5: =text(E4,"ddd") -> Tue | F5: =text(F4,"ddd") -> Wed | G5: =text(G4,"ddd") -> Thu | H5: =text(H4,"ddd") -> Fri | I5: =text(I4,"ddd") -> Sat | J5: =text(J4,"ddd") -> Sun
A6: Danielle Mae David | B6: =30+30+15+20+5+25 -> 125 | C6: =SUM(D6:J6) -> 126 | D6: 33 | E6: 30 | F6: 16 | G6: 18 | H6: 5 | I6: OFF | J6: 24 | K6: =iferror(C6/B6,"-") -> 1.008 | L6: =(IF(K6="",(0),IF(K6>=1,(5),IF(K6>=0.9,(4),IF(K6>=0.8,(3),IF(K6>=0.69,(2),IF(K6<=0.69,(1)))))))) -> 5
A7: Godwin Arellano Reasol | B7: =30+30+25+25+30+20 -> 160 | C7: =SUM(D7:J7) -> 155 | D7: 31 | E7: 27 | F7: 24 | G7: 23 | H7: 32 | I7: OFF | J7: 18 | K7: =iferror(C7/B7,"-") -> 0.96875 | L7: =(IF(K7="",(0),IF(K7>=1,(5),IF(K7>=0.9,(4),IF(K7>=0.8,(3),IF(K7>=0.69,(2),IF(K7<=0.69,(1)))))))) -> 4
A8: Candy Laid | B8: =35+30+35+40+35 -> 175 | C8: =SUM(D8:J8) -> 180 | D8: 36 | E8: OFF | F8: 30 | G8: 42 | H8: 39 | I8: 33 | J8: OFF | K8: =iferror(C8/B8,"-") -> 1.0285714 | L8: =(IF(K8="",(0),IF(K8>=1,(5),IF(K8>=0.9,(4),IF(K8>=0.8,(3),IF(K8>=0.69,(2),IF(K8<=0.69,(1)))))))) -> 5
A9: Mary Claudette Ibong | B9: =35+35+25+25+30+10 -> 160 | C9: =SUM(D9:J9) -> 178 | D9: 42 | E9: 35 | F9: 26 | G9: 37 | H9: 30 | I9: 8 | J9: OFF | K9: =iferror(C9/B9,"-") -> 1.1125 | L9: =(IF(K9="",(0),IF(K9>=1,(5),IF(K9>=0.9,(4),IF(K9>=0.8,(3),IF(K9>=0.69,(2),IF(K9<=0.69,(1)))))))) -> 5
A10: Sofhia Mae Santiago | B10: =30+25+30 -> 85 | C10: =SUM(D10:J10) -> 85 | D10: 32 | E10: 26 | F10: 27 | G10: OFF | H10: OFF | I10: LWOP | J10: LWOP | K10: =iferror(C10/B10,"-") -> 1 | L10: =(IF(K10="",(0),IF(K10>=1,(5),IF(K10>=0.9,(4),IF(K10>=0.8,(3),IF(K10>=0.69,(2),IF(K10<=0.69,(1)))))))) -> 5
A11: Cherry Tubongbanua | B11: =30+30+25+25+40+25 -> 175 | C11: =SUM(D11:J11) -> 176 | D11: 29 | E11: 31 | F11: 20 | G11: 26 | H11: OFF | I11: 44 | J11: 26 | K11: =iferror(C11/B11,"-") -> 1.0057143 | L11: =(IF(K11="",(0),IF(K11>=1,(5),IF(K11>=0.9,(4),IF(K11>=0.8,(3),IF(K11>=0.69,(2),IF(K11<=0.69,(1)))))))) -> 5
A12: Faith Rivera | B12: =20*6 -> 120 | C12: =SUM(D12:J12) -> 119 | D12: 21 | E12: 20 | F12: 17 | G12: 19 | H12: 22 | I12: 20 | J12: OFF | K12: =iferror(C12/B12,"-") -> 0.99166667 | L12: =(IF(K12="",(0),IF(K12>=1,(5),IF(K12>=0.9,(4),IF(K12>=0.8,(3),IF(K12>=0.69,(2),IF(K12<=0.69,(1)))))))) -> 4
A14: Weekly Call Stats
A15: NAME OF AGENT | B15: Ringing Attempts | C15: Picked Up | D15: Not Picked Up | E15: Picked Up Rate | F15: AHT | G15: Picked Up Rate Score | H15: AHT Rate Score
A17: Danielle Mae David | B17: 130 | C17: 126 | D17: =B17-C17 -> 4 | E17: =IFERROR(C17/B17,"") -> 0.96923077 | F17: 0.0023611111 | G17: =IFERROR((IF(E17="",(0),IF(E17>=0.98,(5),IF(E17>=0.95,(4.5),IF(E17>=0.9,(4),IF(E17>=0.8,(3),IF(E17<=0.69,(1)))))))),"") -> 4.5 | H17: =ROUND( IF(F17="", 0, MAX(1, 5 - MAX(0, (F17 - TIME(0,4,0)) / TIME(0,1,0) * 0.5)) ), 2 ) -> 5
A18: Godwin Arellano Reasol | B18: 155 | C18: 154 | D18: =B18-C18 -> 1 | E18: =IFERROR(C18/B18,"") -> 0.99354839 | F18: 0.0039699074 | G18: =IFERROR((IF(E18="",(0),IF(E18>=0.98,(5),IF(E18>=0.95,(4.5),IF(E18>=0.9,(4),IF(E18>=0.8,(3),IF(E18<=0.69,(1)))))))),"") -> 5 | H18: =ROUND( IF(F18="", 0, MAX(1, 5 - MAX(0, (F18 - TIME(0,6,0)) / TIME(0,1,0) * 0.5)) ), 2 ) -> 5
A19: Candy Laid | B19: 178 | C19: 174 | D19: =B19-C19 -> 4 | E19: =IFERROR(C19/B19,"") -> 0.97752809 | F19: 0.0032175926 | G19: =IFERROR((IF(E19="",(0),IF(E19>=0.98,(5),IF(E19>=0.95,(4.5),IF(E19>=0.9,(4),IF(E19>=0.8,(3),IF(E19<=0.69,(1)))))))),"") -> 4.5 | H19: =ROUND( IF(F19="", 0, MAX(1, 5 - MAX(0, (F19 - TIME(0,4,0)) / TIME(0,1,0) * 0.5)) ), 2 ) -> 4.68
A20: Mary Claudette Ibong | B20: 183 | C20: 180 | D20: =B20-C20 -> 3 | E20: =IFERROR(C20/B20,"") -> 0.98360656 | F20: 0.0031944444 | G20: =IFERROR((IF(E20="",(0),IF(E20>=0.98,(5),IF(E20>=0.95,(4.5),IF(E20>=0.9,(4),IF(E20>=0.8,(3),IF(E20<=0.69,(1)))))))),"") -> 5 | H20: =ROUND( IF(F20="", 0, MAX(1, 5 - MAX(0, (F20 - TIME(0,6,0)) / TIME(0,1,0) * 0.5)) ), 2 ) -> 5
A21: Sofhia Mae Santiago | B21: 90 | C21: 89 | D21: =B21-C21 -> 1 | E21: =IFERROR(C21/B21,"") -> 0.98888889 | F21: 0.0030787037 | G21: =IFERROR((IF(E21="",(0),IF(E21>=0.98,(5),IF(E21>=0.95,(4.5),IF(E21>=0.9,(4),IF(E21>=0.8,(3),IF(E21<=0.69,(1)))))))),"") -> 5 | H21: =ROUND( IF(F21="", 0, MAX(1, 5 - MAX(0, (F21 - TIME(0,4,0)) / TIME(0,1,0) * 0.5)) ), 2 ) -> 4.78
A22: Cherry Tubongbanua | B22: 172 | C22: 172 | D22: =B22-C22 -> 0 | E22: =IFERROR(C22/B22,"") -> 1 | F22: 0.0033333333 | G22: =IFERROR((IF(E22="",(0),IF(E22>=0.98,(5),IF(E22>=0.95,(4.5),IF(E22>=0.9,(4),IF(E22>=0.8,(3),IF(E22<=0.69,(1)))))))),"") -> 5 | H22: =ROUND( IF(F22="", 0, MAX(1, 5 - MAX(0, (F22 - TIME(0,7,0)) / TIME(0,1,0) * 0.5)) ), 2 ) -> 5
A23: Faith Rivera | B23: 119 | C23: 116 | D23: =B23-C23 -> 3 | E23: =IFERROR(C23/B23,"") -> 0.97478992 | F23: 0.0044907407 | G23: =IFERROR((IF(E23="",(0),IF(E23>=0.98,(5),IF(E23>=0.95,(4.5),IF(E23>=0.9,(4),IF(E23>=0.8,(3),IF(E23<=0.69,(1)))))))),"") -> 4.5 | H23: =ROUND( IF(F23="", 0, MAX(1, 5 - MAX(0, (F23 - TIME(0,8,0)) / TIME(0,1,0) * 0.5)) ), 2 ) -> 5
A24: Danielle Crizaldo | B24: 19 | C24: 19 | D24: =B24-C24 -> 0 | E24: =IFERROR(C24/B24,"") -> 1 | F24: 0.0015972222 | G24: =IFERROR((IF(E24="",(0),IF(E24>=0.98,(5),IF(E24>=0.95,(4.5),IF(E24>=0.9,(4),IF(E24>=0.8,(3),IF(E24<=0.69,(1)))))))),"") -> 5 | H24: =ROUND( IF(F24="", 0, MAX(1, 5 - MAX(0, (F24 - TIME(0,8,0)) / TIME(0,1,0) * 0.5)) ), 2 ) -> 5
A26: Team Initial Scorecard
A27: CSR NAME | B27: Overall QA Spotcheck 40% | C27: QA Jacky Spotcheck 30% | D27: TL Spotcheck 10% | E27: Productivity 30% | F27: PRODUCTIVITY AVERAGE
A28: Dan Mae David | B28: =(C28*0.3)+(D28*0.1) -> #REF! | C28: 1 | D28: =#REF! -> #REF! | E28: =(L6+G17+H17)/15*0.3 -> 0.29 | F28: =(E28/30%)*10 -> 9.6666667
A29: Godwin Reasol | B29: =(C29*0.3)+(D29*0.1) -> #REF! | C29: 1 | D29: =#REF! -> #REF! | E29: =(L7+G18+H18)/15*0.3 -> 0.28 | F29: =(E29/30%)*10 -> 9.3333333
A30: Candy Laid | B30: =(C30*0.3)+(D30*0.1) -> #REF! | C30: 1 | D30: =#REF! -> #REF! | E30: =(L8+G19+H19)/15*0.3 -> 0.2836 | F30: =(E30/30%)*10 -> 9.4533333
A31: Claudette Ibong | B31: =(C31*0.3)+(D31*0.1) -> #REF! | C31: 1 | D31: =#REF! -> #REF! | E31: =(L9+G20+H20)/15*0.3 -> 0.3 | F31: =(E31/30%)*10 -> 10
A32: Sofhia Santiago | B32: =(C32*0.3)+(D32*0.1) -> #REF! | C32: 1 | D32: =#REF! -> #REF! | E32: =(L10+G21+H21)/15*0.3 -> 0.2956 | F32: =(E32/30%)*10 -> 9.8533333
A33: Cherry Tubongbanua | B33: =(C33*0.3)+(D33*0.1) -> #REF! | C33: 1 | D33: =#REF! -> #REF! | E33: =(L11+G22+H22)/15*0.3 -> 0.3 | F33: =(E33/30%)*10 -> 10
A34: Faith Rivera | B34: =(C34*0.3)+(D34*0.1) -> #REF! | C34: 0.71 | D34: =Faith!D54 -> #REF! | E34: =(L12+G23+H23)/15*0.3 -> 0.27 | F34: =(E34/30%)*10 -> 9
A36: OT HOURS for Payroll
A37: CSR NAME | B37: Authorized OT | C37: 46055 | D37: 46056 | E37: 46057 | F37: 46058 | G37: 46059 | H37: 46060 | I37: 46061
C38: Mon | D38: Tue | E38: Wed | F38: Thu | G38: Fri | H38: Sat | I38: Sun
A39: Dan Mae David | B39: =Sum(C39:I39) -> 8 | G39: 8
A40: Godwin Reasol | B40: =Sum(C40:I40) -> 14 | C40: 2 | E40: 2 | G40: 2 | I40: 8
A41: Candy Laid | B41: =Sum(C41:I41) -> 6 | F41: 2 | G41: 2 | H41: 2
A42: Claudette Ibong | B42: =Sum(C42:I42) -> 12 | D42: 2 | F42: 2 | H42: 8
A43: Sofhia Santiago | B43: =Sum(C43:I43) -> 6 | C43: 2 | D43: 2 | E43: 2
A44: Cherry Tubongbanua | B44: =Sum(C44:I44) -> 12 | D44: 2 | F44: 8 | H44: 2
A45: Faith Rivera | B45: =Sum(C45:I45) -> 8 | H45: 8
A46: WEEK: February 9 - February 15
A47: Daily Productivity
A48: NAME OF AGENT | B48: Weekly Target | C48: Weekly Actual | D48: 46062 | E48: 46063 | F48: 46064 | G48: 46065 | H48: 46066 | I48: 46067 | J48: 46068 | K48: % Productivity | L48: Final Score
D49: Mon | E49: =text(E48,"ddd") -> Tue | F49: =text(F48,"ddd") -> Wed | G49: =text(G48,"ddd") -> Thu | H49: =text(H48,"ddd") -> Fri | I49: =text(I48,"ddd") -> Sat | J49: =text(J48,"ddd") -> Sun
A50: Danielle Mae David | B50: =25+35+25+15+5 -> 105 | C50: =SUM(D50:J50) -> 76 | D50: 24 | E50: 36 | F50: A | G50: 11 | H50: 5 | I50: OFF | J50: OFF | K50: =iferror(C50/B50,"-") -> 0.72380952 | L50: =(IF(K50="",(0),IF(K50>=1,(5),IF(K50>=0.9,(4),IF(K50>=0.8,(3),IF(K50>=0.69,(2),IF(K50<=0.69,(1)))))))) -> 2
A51: Godwin Arellano Reasol | B51: =30+25+25+30+25+13 -> 148 | C51: =SUM(D51:J51) -> 137 | D51: 28 | E51: 23 | F51: 27 | G51: 26 | H51: 21 | I51: OFF | J51: 12 | K51: =iferror(C51/B51,"-") -> 0.92567568 | L51: =(IF(K51="",(0),IF(K51>=1,(5),IF(K51>=0.9,(4),IF(K51>=0.8,(3),IF(K51>=0.69,(2),IF(K51<=0.69,(1)))))))) -> 4
A52: Candy Laid | B52: =35+45+25+25+25 -> 155 | C52: =SUM(D52:J52) -> 159 | D52: 38 | E52: OFF | F52: 46 | G52: 24 | H52: 25 | I52: 26 | J52: OFF | K52: =iferror(C52/B52,"-") -> 1.0258065 | L52: =(IF(K52="",(0),IF(K52>=1,(5),IF(K52>=0.9,(4),IF(K52>=0.8,(3),IF(K52>=0.69,(2),IF(K52<=0.69,(1)))))))) -> 5
A53: Mary Claudette Ibong | B53: =30+25+30+25+7 -> 117 | C53: =SUM(D53:J53) -> 119 | D53: OFF | E53: 33 | F53: 23 | G53: 38 | H53: 19 | I53: 6 | J53: OFF | K53: =iferror(C53/B53,"-") -> 1.017094 | L53: =(IF(K53="",(0),IF(K53>=1,(5),IF(K53>=0.9,(4),IF(K53>=0.8,(3),IF(K53>=0.69,(2),IF(K53<=0.69,(1)))))))) -> 5
A54: Sofhia Mae Santiago | B54: =25+35+25+25+25+20 -> 155 | C54: =SUM(D54:J54) -> 162 | D54: 21 | E54: 41 | F54: 26 | G54: OFF | H54: 23 | I54: 29 | J54: 22 | K54: =iferror(C54/B54,"-") -> 1.0451613 | L54: =(IF(K54="",(0),IF(K54>=1,(5),IF(K54>=0.9,(4),IF(K54>=0.8,(3),IF(K54>=0.69,(2),IF(K54<=0.69,(1)))))))) -> 5
A55: Cherry Tubongbanua | B55: =35+25+30+25+25+13 -> 153 | C55: =SUM(D55:J55) -> 140 | D55: 35 | E55: 18 | F55: 32 | G55: 17 | H55: OFF | I55: 26 | J55: 12 | K55: =iferror(C55/B55,"-") -> 0.91503268 | L55: =(IF(K55="",(0),IF(K55>=1,(5),IF(K55>=0.9,(4),IF(K55>=0.8,(3),IF(K55>=0.69,(2),IF(K55<=0.69,(1)))))))) -> 4
A56: Faith Rivera | B56: =20*6 -> 120 | C56: =SUM(D56:J56) -> 128 | D56: 28 | E56: 18 | F56: 18 | G56: 22 | H56: 25 | I56: 17 | J56: OFF | K56: =iferror(C56/B56,"-") -> 1.0666667 | L56: =(IF(K56="",(0),IF(K56>=1,(5),IF(K56>=0.9,(4),IF(K56>=0.8,(3),IF(K56>=0.69,(2),IF(K56<=0.69,(1)))))))) -> 5
A57: Lyra Miclat | B57: =20+10+10+13 -> 53 | C57: =SUM(D57:J57) -> 55 | D57: TRAINING | E57: 23 | F57: OFF | G57: OFF | H57: 10 | I57: 9 | J57: 13 | K57: =iferror(C57/B57,"-") -> 1.0377358 | L57: =(IF(K57="",(0),IF(K57>=1,(5),IF(K57>=0.9,(4),IF(K57>=0.8,(3),IF(K57>=0.69,(2),IF(K57<=0.69,(1)))))))) -> 5
A59: Weekly Call Stats
A60: NAME OF AGENT | B60: Ringing Attempts | C60: Picked Up | D60: Not Picked Up | E60: Picked Up Rate | F60: AHT | G60: Picked Up Rate Score | H60: AHT Rate Score
A62: Danielle Mae David | B62: 78 | C62: 76 | D62: =B62-C62 -> 2 | E62: =IFERROR(C62/B62,"") -> 0.97435897 | F62: 0.0026157407 | G62: =IFERROR((IF(E62="",(0),IF(E62>=0.98,(5),IF(E62>=0.95,(4.5),IF(E62>=0.9,(4),IF(E62>=0.8,(3),IF(E62<=0.69,(1)))))))),"") -> 4.5 | H62: =ROUND( IF(F62="", 0, MAX(1, 5 - MAX(0, (F62 - TIME(0,4,0)) / TIME(0,1,0) * 0.5)) ), 2 ) -> 5
A63: Godwin Arellano Reasol | B63: 138 | C63: 136 | D63: =B63-C63 -> 2 | E63: =IFERROR(C63/B63,"") -> 0.98550725 | F63: 0.0045486111 | G63: =IFERROR((IF(E63="",(0),IF(E63>=0.98,(5),IF(E63>=0.95,(4.5),IF(E63>=0.9,(4),IF(E63>=0.8,(3),IF(E63<=0.69,(1)))))))),"") -> 5 | H63: =ROUND( IF(F63="", 0, MAX(1, 5 - MAX(0, (F63 - TIME(0,6,0)) / TIME(0,1,0) * 0.5)) ), 2 ) -> 4.73
A64: Candy Laid | B64: 151 | C64: 147 | D64: =B64-C64 -> 4 | E64: =IFERROR(C64/B64,"") -> 0.97350993 | F64: 0.0033564815 | G64: =IFERROR((IF(E64="",(0),IF(E64>=0.98,(5),IF(E64>=0.95,(4.5),IF(E64>=0.9,(4),IF(E64>=0.8,(3),IF(E64<=0.69,(1)))))))),"") -> 4.5 | H64: =ROUND( IF(F64="", 0, MAX(1, 5 - MAX(0, (F64 - TIME(0,4,0)) / TIME(0,1,0) * 0.5)) ), 2 ) -> 4.58
A65: Mary Claudette Ibong | B65: 119 | C65: 118 | D65: =B65-C65 -> 1 | E65: =IFERROR(C65/B65,"") -> 0.99159664 | F65: 0.0031365741 | G65: =IFERROR((IF(E65="",(0),IF(E65>=0.98,(5),IF(E65>=0.95,(4.5),IF(E65>=0.9,(4),IF(E65>=0.8,(3),IF(E65<=0.69,(1)))))))),"") -> 5 | H65: =ROUND( IF(F65="", 0, MAX(1, 5 - MAX(0, (F65 - TIME(0,6,0)) / TIME(0,1,0) * 0.5)) ), 2 ) -> 5
A66: Sofhia Mae Santiago | B66: 163 | C66: 161 | D66: =B66-C66 -> 2 | E66: =IFERROR(C66/B66,"") -> 0.98773006 | F66: 0.002962963 | G66: =IFERROR((IF(E66="",(0),IF(E66>=0.98,(5),IF(E66>=0.95,(4.5),IF(E66>=0.9,(4),IF(E66>=0.8,(3),IF(E66<=0.69,(1)))))))),"") -> 5 | H66: =ROUND( IF(F66="", 0, MAX(1, 5 - MAX(0, (F66 - TIME(0,4,0)) / TIME(0,1,0) * 0.5)) ), 2 ) -> 4.87
A67: Cherry Tubongbanua | B67: 140 | C67: 139 | D67: =B67-C67 -> 1 | E67: =IFERROR(C67/B67,"") -> 0.99285714 | F67: 0.0038425926 | G67: =IFERROR((IF(E67="",(0),IF(E67>=0.98,(5),IF(E67>=0.95,(4.5),IF(E67>=0.9,(4),IF(E67>=0.8,(3),IF(E67<=0.69,(1)))))))),"") -> 5 | H67: =ROUND( IF(F67="", 0, MAX(1, 5 - MAX(0, (F67 - TIME(0,6,0)) / TIME(0,1,0) * 0.5)) ), 2 ) -> 5
A68: Faith Rivera | B68: 127 | C68: 126 | D68: =B68-C68 -> 1 | E68: =IFERROR(C68/B68,"") -> 0.99212598 | F68: 0.0043518519 | G68: =IFERROR((IF(E68="",(0),IF(E68>=0.98,(5),IF(E68>=0.95,(4.5),IF(E68>=0.9,(4),IF(E68>=0.8,(3),IF(E68<=0.69,(1)))))))),"") -> 5 | H68: =ROUND( IF(F68="", 0, MAX(1, 5 - MAX(0, (F68 - TIME(0,6,0)) / TIME(0,1,0) * 0.5)) ), 2 ) -> 4.87
A69: Lyra Miclat | B69: 30 | C69: 30 | D69: =B69-C69 -> 0 | E69: =IFERROR(C69/B69,"") -> 1 | F69: 0.0053472222 | G69: =IFERROR((IF(E69="",(0),IF(E69>=0.98,(5),IF(E69>=0.95,(4.5),IF(E69>=0.9,(4),IF(E69>=0.8,(3),IF(E69<=0.69,(1)))))))),"") -> 5 | H69: =ROUND( IF(F69="", 0, MAX(1, 5 - MAX(0, (F69 - TIME(0,8,0)) / TIME(0,1,0) * 0.5)) ), 2 ) -> 5
A71: Team Initial Scorecard
A72: CSR NAME | B72: Overall QA Spotcheck 40% | C72: QA Jacky Spotcheck 30% | D72: TL Spotcheck 10% | E72: Productivity 30% | F72: PRODUCTIVITY AVERAGE
A73: Dan Mae David | B73: =(C73*0.3)+(D73*0.1) -> #REF! | C73: 1 | D73: =#REF! -> #REF! | E73: =(L50+G62+H62)/15*0.3 -> 0.23 | F73: =(E73/30%)*10 -> 7.6666667
A74: Godwin Reasol | B74: =(C74*0.3)+(D74*0.1) -> #REF! | C74: 1 | D74: =#REF! -> #REF! | E74: =(L51+G63+H63)/15*0.3 -> 0.2746 | F74: =(E74/30%)*10 -> 9.1533333
A75: Candy Laid | B75: =(C75*0.3)+(D75*0.1) -> #REF! | C75: 1 | D75: =#REF! -> #REF! | E75: =(L52+G64+H64)/15*0.3 -> 0.2816 | F75: =(E75/30%)*10 -> 9.3866667
A76: Claudette Ibong | B76: =(C76*0.3)+(D76*0.1) -> #REF! | C76: 1 | D76: =#REF! -> #REF! | E76: =(L53+G65+H65)/15*0.3 -> 0.3 | F76: =(E76/30%)*10 -> 10
A77: Sofhia Santiago | B77: =(C77*0.3)+(D77*0.1) -> #REF! | C77: 1 | D77: =#REF! -> #REF! | E77: =(L54+G66+H66)/15*0.3 -> 0.2974 | F77: =(E77/30%)*10 -> 9.9133333
A78: Cherry Tubongbanua | B78: =(C78*0.3)+(D78*0.1) -> #REF! | C78: 1 | D78: =#REF! -> #REF! | E78: =(L55+G67+H67)/15*0.3 -> 0.28 | F78: =(E78/30%)*10 -> 9.3333333
A79: Faith Rivera | B79: =(C79*0.3)+(D79*0.1) -> #REF! | C79: 0.5 | D79: =Faith!D72 -> #REF! | E79: =(L56+G68+H68)/15*0.3 -> 0.2974 | F79: =(E79/30%)*10 -> 9.9133333
A80: Lyra Miclat | B80: =(C80*0.3)+(D80*0.1) -> 0.364 | C80: 0.88 | D80: =Lyra!D53 -> 1 | E80: =(L57+G69+H69)/15*0.3 -> 0.3 | F80: =(E80/30%)*10 -> 10
A82: OT HOURS for Payroll
A83: CSR NAME | B83: Authorized OT | C83: 46062 | D83: 46063 | E83: 46064 | F83: 46065 | G83: 46066 | H83: 46067 | I83: 46068
C84: Mon | D84: Tue | E84: Wed | F84: Thu | G84: Fri | H84: Sat | I84: Sun
A85: Dan Mae David | B85: =Sum(C85:I85) -> 0
A86: Godwin Reasol | B86: =Sum(C86:I86) -> 14 | C86: 2 | E86: 2 | G86: 2 | I86: 8
A87: Candy Laid | B87: =Sum(C87:I87) -> 6 | C87: 2 | E87: 2 | G87: 2
A88: Claudette Ibong | B88: =Sum(C88:I88) -> 12 | D88: 2 | F88: 2 | H88: 8
A89: Sofhia Santiago | B89: =Sum(C89:I89) -> 14 | D89: 2 | E89: 8 | G89: 2 | H89: 2
A90: Cherry Tubongbanua | B90: =Sum(C90:I90) -> 14 | C90: 2 | E90: 2 | F90: 8 | H90: 2
A91: Faith Rivera | B91: =Sum(C91:I91) -> 10 | G91: 8 | H91: 2
A93: LYRA ATTENDANCE | B93: Total Work Hours | C93: 46062 | D93: 46063 | E93: 46064 | F93: 46065 | G93: 46066 | H93: 46067 | I93: 46068
A94: Lyra Miclat | B94: =SUM(C94:I94) -> 40 | C94: 8 | D94: 8 | E94: OFF | F94: OFF | G94: 8 | H94: 8 | I94: 8
A95: WEEK: February 16 - February 22
A96: Daily Productivity
A97: NAME OF AGENT | B97: Weekly Target | C97: Weekly Actual | D97: 46069 | E97: 46070 | F97: 46071 | G97: 46072 | H97: 46073 | I97: 46074 | J97: 46075 | K97: % Productivity | L97: Final Score
D98: Mon | E98: =text(E97,"ddd") -> Tue | F98: =text(F97,"ddd") -> Wed | G98: =text(G97,"ddd") -> Thu | H98: =text(H97,"ddd") -> Fri | I98: =text(I97,"ddd") -> Sat | J98: =text(J97,"ddd") -> Sun
A99: Danielle Mae David | B99: =25+30+15+15+5+15 -> 105 | C99: =SUM(D99:J99) -> 106 | D99: 26 | E99: 30 | F99: 16 | G99: 14 | H99: 4 | I99: OFF | J99: 16 | K99: =iferror(C99/B99,"-") -> 1.0095238 | L99: =(IF(K99="",(0),IF(K99>=1,(5),IF(K99>=0.9,(4),IF(K99>=0.8,(3),IF(K99>=0.69,(2),IF(K99<=0.69,(1)))))))) -> 5
A100: Godwin Arellano Reasol | B100: =30+30+35+30+25+25 -> 175 | C100: =SUM(D100:J100) -> 166 | D100: 28 | E100: 31 | F100: 29 | G100: 32 | H100: 23 | I100: OFF | J100: 23 | K100: =iferror(C100/B100,"-") -> 0.94857143 | L100: =(IF(K100="",(0),IF(K100>=1,(5),IF(K100>=0.9,(4),IF(K100>=0.8,(3),IF(K100>=0.69,(2),IF(K100<=0.69,(1)))))))) -> 4
A101: Candy Laid | B101: =25+35+30+35+30 -> 155 | C101: =SUM(D101:J101) -> 156 | D101: 23 | E101: OFF | F101: 35 | G101: 33 | H101: 35 | I101: 30 | J101: OFF | K101: =iferror(C101/B101,"-") -> 1.0064516 | L101: =(IF(K101="",(0),IF(K101>=1,(5),IF(K101>=0.9,(4),IF(K101>=0.8,(3),IF(K101>=0.69,(2),IF(K101<=0.69,(1)))))))) -> 5
A102: Mary Claudette Ibong | B102: =30+20+30+25+30+2 -> 137 | C102: =SUM(D102:J102) -> 137 | D102: 30 | E102: 18 | F102: 35 | G102: 24 | H102: 28 | I102: 2 | J102: OFF | K102: =iferror(C102/B102,"-") -> 1 | L102: =(IF(K102="",(0),IF(K102>=1,(5),IF(K102>=0.9,(4),IF(K102>=0.8,(3),IF(K102>=0.69,(2),IF(K102<=0.69,(1)))))))) -> 5
A103: Sofhia Mae Santiago | B103: =25+30+35+25+15 -> 130 | C103: =SUM(D103:J103) -> 118 | D103: 22 | E103: 27 | F103: OFF | G103: OFF | H103: 35 | I103: 21 | J103: 13 | K103: =iferror(C103/B103,"-") -> 0.90769231 | L103: =(IF(K103="",(0),IF(K103>=1,(5),IF(K103>=0.9,(4),IF(K103>=0.8,(3),IF(K103>=0.69,(2),IF(K103<=0.69,(1)))))))) -> 4
A104: Cherry Tubongbanua | B104: =30+30+30+30+15 -> 135 | C104: =SUM(D104:J104) -> 137 | D104: 29 | E104: 33 | F104: 25 | G104: OFF | H104: OFF | I104: 33 | J104: 17 | K104: =iferror(C104/B104,"-") -> 1.0148148 | L104: =(IF(K104="",(0),IF(K104>=1,(5),IF(K104>=0.9,(4),IF(K104>=0.8,(3),IF(K104>=0.69,(2),IF(K104<=0.69,(1)))))))) -> 5
A105: Faith Rivera | B105: =25*6 -> 150 | C105: =SUM(D105:J105) -> 131 | D105: 23 | E105: 21 | F105: 26 | G105: 21 | H105: 23 | I105: 17 | J105: OFF | K105: =iferror(C105/B105,"-") -> 0.87333333 | L105: =(IF(K105="",(0),IF(K105>=1,(5),IF(K105>=0.9,(4),IF(K105>=0.8,(3),IF(K105>=0.69,(2),IF(K105<=0.69,(1)))))))) -> 3
A106: Lyra Miclat | B106: =15*6 -> 90 | C106: =SUM(D106:J106) -> 98 | D106: 15 | E106: 16 | F106: OFF | G106: 19 | H106: 17 | I106: 13 | J106: 18 | K106: =iferror(C106/B106,"-") -> 1.0888889 | L106: =(IF(K106="",(0),IF(K106>=1,(5),IF(K106>=0.9,(4),IF(K106>=0.8,(3),IF(K106>=0.69,(2),IF(K106<=0.69,(1)))))))) -> 5
A108: Weekly Call Stats
A109: NAME OF AGENT | B109: Ringing Attempts | C109: Picked Up | D109: Not Picked Up | E109: Picked Up Rate | F109: AHT | G109: Picked Up Rate Score | H109: AHT Rate Score
A111: Danielle Mae David | B111: 108 | C111: 106 | D111: =B111-C111 -> 2 | E111: =IFERROR(C111/B111,"") -> 0.98148148 | F111: 0.0022569444 | G111: =IFERROR((IF(E111="",(0),IF(E111>=0.98,(5),IF(E111>=0.95,(4.5),IF(E111>=0.9,(4),IF(E111>=0.8,(3),IF(E111<=0.69,(1)))))))),"") -> 5 | H111: =ROUND( IF(F111="", 0, MAX(1, 5 - MAX(0, (F111 - TIME(0,4,0)) / TIME(0,1,0) * 0.5)) ), 2 ) -> 5
...

Sheet Daily and Weekly Call Stats
B1: WEEK: August 3,2026 - August 9,2026
B2: Daily Productivity Record
A3: Name of Agent | B3: Weekly Target | C3: Actual Productivity | D3: 46237 | E3: 46238 | F3: 46239 | G3: 46240 | H3: 46241 | I3: 46242 | J3: 46243 | K3: Productivity % | L3: Final Score
D4: =text(D3,"ddd") -> Mon | E4: =text(E3,"ddd") -> Tue | F4: =text(F3,"ddd") -> Wed | G4: =text(G3,"ddd") -> Thu | H4: =text(H3,"ddd") -> Fri | I4: =text(I3,"ddd") -> Sat | J4: =text(J3,"ddd") -> Sun
A5: Daniellel Mae David | B5: =30*5 -> 150 | C5: =SUM(D5:J5) -> 158 | D5: 24 | E5: 31 | F5: 28 | G5: 25 | H5: 44 | I5: 6 | J5: OFF | K5: =iferror(C5/B5,"-") -> 1.0533333 | L5: =(IF(K5="",(0),IF(K5>=1,(5),IF(K5>=0.9,(4),IF(K5>=0.8,(3),IF(K5>=0.69,(2),IF(K5<=0.69,(1)))))))) -> 5
A6: Godwin Arellano Reasol | B6: =30*4+15 -> 135 | C6: =SUM(D6:J6) -> 124 | D6: 29 | E6: 21 | F6: 24 | G6: 14 | H6: 28 | I6: OFF | J6: 8 | K6: =iferror(C6/B6,"-") -> 0.91851852 | L6: =(IF(K6="",(0),IF(K6>=1,(5),IF(K6>=0.9,(4),IF(K6>=0.8,(3),IF(K6>=0.69,(2),IF(K6<=0.69,(1)))))))) -> 4
A7: Candy Laid | B7: =30*5 -> 150 | C7: =SUM(D7:J7) -> 168 | D7: 33 | E7: 28 | F7: OFF | G7: 36 | H7: 38 | I7: 33 | J7: OFF | K7: =iferror(C7/B7,"-") -> 1.12 | L7: =(IF(K7="",(0),IF(K7>=1,(5),IF(K7>=0.9,(4),IF(K7>=0.8,(3),IF(K7>=0.69,(2),IF(K7<=0.69,(1)))))))) -> 5
A8: Mary Claudette Ibong | B8: =30*3+15+20 -> 125 | C8: =SUM(D8:J8) -> 114 | D8: 26 | E8: 23 | F8: 18 | G8: 13 | H8: OFF | I8: 17 | J8: 17 | K8: =iferror(C8/B8,"-") -> 0.912 | L8: =(IF(K8="",(0),IF(K8>=1,(5),IF(K8>=0.9,(4),IF(K8>=0.8,(3),IF(K8>=0.69,(2),IF(K8<=0.69,(1)))))))) -> 4
A9: Sofhia Mae Santiago | B9: =30*4+20 -> 140 | C9: =SUM(D9:J9) -> 128 | D9: 34 | E9: 24 | F9: 27 | G9: 8 | H9: OFF | I9: 16 | J9: 19 | K9: =iferror(C9/B9,"-") -> 0.91428571 | L9: =(IF(K9="",(0),IF(K9>=1,(5),IF(K9>=0.9,(4),IF(K9>=0.8,(3),IF(K9>=0.69,(2),IF(K9<=0.69,(1)))))))) -> 4
A10: Cherry Tubongbanua | B10: =30*5 -> 150 | C10: =SUM(D10:J10) -> 179 | D10: 33 | E10: 36 | F10: 32 | G10: 41 | H10: 27 | I10: 10 | J10: OFF | K10: =iferror(C10/B10,"-") -> 1.1933333 | L10: =(IF(K10="",(0),IF(K10>=1,(5),IF(K10>=0.9,(4),IF(K10>=0.8,(3),IF(K10>=0.69,(2),IF(K10<=0.69,(1)))))))) -> 5
A11: Lyra Miclat | B11: =30*5 -> 150 | C11: =SUM(D11:J11) -> 162 | D11: 39 | E11: 27 | F11: 42 | G11: 28 | H11: 26 | I11: OFF | J11: OFF | K11: =iferror(C11/B11,"-") -> 1.08 | L11: =(IF(K11="",(0),IF(K11>=1,(5),IF(K11>=0.9,(4),IF(K11>=0.8,(3),IF(K11>=0.69,(2),IF(K11<=0.69,(1)))))))) -> 5
A12: Joemica Carino | B12: =30*3+20+15 -> 125 | C12: =SUM(D12:J12) -> 116 | D12: 18 | E12: 14 | F12: OFF | G12: 26 | H12: 29 | I12: 17 | J12: 12 | K12: =iferror(C12/B12,"-") -> 0.928 | L12: =(IF(K12="",(0),IF(K12>=1,(5),IF(K12>=0.9,(4),IF(K12>=0.8,(3),IF(K12>=0.69,(2),IF(K12<=0.69,(1)))))))) -> 4
B14: Weekly Call Stats
A15: Name of Agent | B15: Ringing Attempts | C15: Picked Up | D15: Not Picked Up | E15: Picked Up Rate | F15: AHT | G15: Picked Up Rate Score | H15: AHT Score
A17: Daniellel Mae David | B17: 167 | C17: 158 | D17: =B17-C17 -> 9 | E17: =Iferror(C17/B17,"") -> 0.94610778 | F17: 0.0018865741 | G17: =IFERROR((IF(E17="",(0),IF(E17>=0.98,(5),IF(E17>=0.95,(4.5),IF(E17>=0.9,(4),IF(E17>=0.8,(3),IF(E17<=0.69,(1)))))))),"") -> 4 | H17: =ROUND( IF(F17="", 0, MAX(1, 5 - MAX(0, (F17 - TIME(0,4,0)) / TIME(0,1,0) * 0.5)) ), 2 ) -> 5
A18: Godwin Arellano Reasol | B18: 127 | C18: 124 | D18: =B18-C18 -> 3 | E18: =Iferror(C18/B18,"") -> 0.97637795 | F18: 0.0039467593 | G18: =IFERROR((IF(E18="",(0),IF(E18>=0.98,(5),IF(E18>=0.95,(4.5),IF(E18>=0.9,(4),IF(E18>=0.8,(3),IF(E18<=0.69,(1)))))))),"") -> 4.5 | H18: =ROUND( IF(F18="", 0, MAX(1, 5 - MAX(0, (F18 - TIME(0,4,0)) / TIME(0,1,0) * 0.5)) ), 2 ) -> 4.16
A19: Candy Laid | B19: 181 | C19: 176 | D19: =B19-C19 -> 5 | E19: =Iferror(C19/B19,"") -> 0.97237569 | F19: 0.0034722222 | G19: =IFERROR((IF(E19="",(0),IF(E19>=0.98,(5),IF(E19>=0.95,(4.5),IF(E19>=0.9,(4),IF(E19>=0.8,(3),IF(E19<=0.69,(1)))))))),"") -> 4.5 | H19: =ROUND( IF(F19="", 0, MAX(1, 5 - MAX(0, (F19 - TIME(0,4,0)) / TIME(0,1,0) * 0.5)) ), 2 ) -> 4.5
A20: Mary Claudette Ibong | B20: 115 | C20: 114 | D20: =B20-C20 -> 1 | E20: =Iferror(C20/B20,"") -> 0.99130435 | F20: 0.0035416667 | G20: =IFERROR((IF(E20="",(0),IF(E20>=0.98,(5),IF(E20>=0.95,(4.5),IF(E20>=0.9,(4),IF(E20>=0.8,(3),IF(E20<=0.69,(1)))))))),"") -> 5 | H20: =ROUND( IF(F20="", 0, MAX(1, 5 - MAX(0, (F20 - TIME(0,4,0)) / TIME(0,1,0) * 0.5)) ), 2 ) -> 4.45
A21: Sofhia Mae Santiago | B21: 131 | C21: 128 | D21: =B21-C21 -> 3 | E21: =Iferror(C21/B21,"") -> 0.97709924 | F21: 0.0024189815 | G21: =IFERROR((IF(E21="",(0),IF(E21>=0.98,(5),IF(E21>=0.95,(4.5),IF(E21>=0.9,(4),IF(E21>=0.8,(3),IF(E21<=0.69,(1)))))))),"") -> 4.5 | H21: =ROUND( IF(F21="", 0, MAX(1, 5 - MAX(0, (F21 - TIME(0,4,0)) / TIME(0,1,0) * 0.5)) ), 2 ) -> 5
A22: Cherry Tubongbanua | B22: 180 | C22: 179 | D22: =B22-C22 -> 1 | E22: =Iferror(C22/B22,"") -> 0.99444444 | F22: 0.0046180556 | G22: =IFERROR((IF(E22="",(0),IF(E22>=0.98,(5),IF(E22>=0.95,(4.5),IF(E22>=0.9,(4),IF(E22>=0.8,(3),IF(E22<=0.69,(1)))))))),"") -> 5 | H22: =ROUND( IF(F22="", 0, MAX(1, 5 - MAX(0, (F22 - TIME(0,4,0)) / TIME(0,1,0) * 0.5)) ), 2 ) -> 3.68
A23: Lyra Miclat | B23: 186 | C23: 176 | D23: =B23-C23 -> 10 | E23: =Iferror(C23/B23,"") -> 0.94623656 | F23: 0.0033101852 | G23: =IFERROR((IF(E23="",(0),IF(E23>=0.98,(5),IF(E23>=0.95,(4.5),IF(E23>=0.9,(4),IF(E23>=0.8,(3),IF(E23<=0.69,(1)))))))),"") -> 4 | H23: =ROUND( IF(F23="", 0, MAX(1, 5 - MAX(0, (F23 - TIME(0,4,0)) / TIME(0,1,0) * 0.5)) ), 2 ) -> 4.62
A24: Joemica Carino | B24: 121 | C24: 116 | D24: =B24-C24 -> 5 | E24: =Iferror(C24/B24,"") -> 0.95867769 | F24: 0.0036574074 | G24: =IFERROR((IF(E24="",(0),IF(E24>=0.98,(5),IF(E24>=0.95,(4.5),IF(E24>=0.9,(4),IF(E24>=0.8,(3),IF(E24<=0.69,(1)))))))),"") -> 4.5 | H24: =ROUND( IF(F24="", 0, MAX(1, 5 - MAX(0, (F24 - TIME(0,4,0)) / TIME(0,1,0) * 0.5)) ), 2 ) -> 4.37
B27: Score per Metrics for Scorecard (Initial Productivity and QA Scores) | H27: What Does 30% Productivity Covers?
A28: Name of Agent | B28: QA JACKY SCORE 30% | C28: QA TL SCORE 10% | D28: Final QA Score 40% | E28: Productivity (WORK ETHIC) % (30%) | F28: FINAL Work Ethic Score | H28: 1. Final Score from Daily Productivity Record
H29: 2. Picked Up Rate Score
A30: Daniellel Mae David | B30: 1 | C30: =Dan!D90 -> 1 | D30: =(B30*0.3)+(C30*0.1) -> 0.4 | E30: =(L5+G17+H17)/15*0.3 -> 0.28 | F30: =(E30/30%)*10 -> 9.3333333 | H30: 3.. AHT Score
A31: Godwin Arellano Reasol | B31: 1 | C31: =Godwin!D72 -> 1 | D31: =(B31*0.3)+(C31*0.1) -> 0.4 | E31: =(L6+G18+H18)/15*0.3 -> 0.2532 | F31: =(E31/30%)*10 -> 8.44
A32: Candy Laid | B32: 1 | C32: =Candy!D72 -> 1 | D32: =(B32*0.3)+(C32*0.1) -> 0.4 | E32: =(L7+G19+H19)/15*0.3 -> 0.28 | F32: =(E32/30%)*10 -> 9.3333333 | H32: Computation:
A33: Mary Claudette Ibong | B33: 1 | C33: =Claudette!D54 -> 1 | D33: =(B33*0.3)+(C33*0.1) -> 0.4 | E33: =(L8+G20+H20)/15*0.3 -> 0.269 | F33: =(E33/30%)*10 -> 8.9666667 | H33: Final Productivity % | J33: (Final productivity Score + Picked Up Rate Score + AHT Score) /15 *.30
A34: Sofhia Mae Santiago | B34: 0.85 | C34: =Sofhia!D54 -> 1 | D34: =(B34*0.3)+(C34*0.1) -> 0.355 | E34: =(L9+G21+H21)/15*0.3 -> 0.27 | F34: =(E34/30%)*10 -> 9 | H34: Productivity Score | J34: (Final Productivity % / 30%) *10
A35: Cherry Tubongbanua | B35: 1 | C35: =Cherry!D36 -> 1 | D35: =(B35*0.3)+(C35*0.1) -> 0.4 | E35: =(L10+G22+H22)/15*0.3 -> 0.2736 | F35: =(E35/30%)*10 -> 9.12
A36: Lyra Miclat | B36: 0.25 | C36: =Lyra!D503 -> 1 | D36: =(B36*0.3)+(C36*0.1) -> 0.175 | E36: =(L11+G23+H23)/15*0.3 -> 0.2724 | F36: =(E36/30%)*10 -> 9.08
A37: Joemica Carino | B37: 1 | C37: =Mikka!D448 -> 1 | D37: =(B37*0.3)+(C37*0.1) -> 0.4 | E37: =(L12+G24+H24)/15*0.3 -> 0.2574 | F37: =(E37/30%)*10 -> 8.58
B38: WEEK: August 10,2026 - August 16,2026
B39: Daily Productivity Record
A40: Name of Agent | B40: Weekly Target | C40: Actual Productivity | D40: 46244 | E40: 46245 | F40: 46246 | G40: 46247 | H40: 46248 | I40: 46249 | J40: 46250 | K40: Productivity % | L40: Final Score
D41: =text(D40,"ddd") -> Mon | E41: =text(E40,"ddd") -> Tue | F41: =text(F40,"ddd") -> Wed | G41: =text(G40,"ddd") -> Thu | H41: =text(H40,"ddd") -> Fri | I41: =text(I40,"ddd") -> Sat | J41: =text(J40,"ddd") -> Sun
A42: Daniellel Mae David | B42: =30*5 -> 150 | C42: =SUM(D42:J42) -> 155 | D42: 28 | E42: 22 | F42: 32 | G42: 29 | H42: 35 | I42: 9 | J42: OFF | K42: =iferror(C42/B42,"-") -> 1.0333333 | L42: =(IF(K42="",(0),IF(K42>=1,(5),IF(K42>=0.9,(4),IF(K42>=0.8,(3),IF(K42>=0.69,(2),IF(K42<=0.69,(1)))))))) -> 5
A43: Godwin Arellano Reasol | B43: =30*4+15+25 -> 160 | C43: =SUM(D43:J43) -> 143 | D43: 25 | E43: 27 | F43: 21 | G43: 30 | H43: 29 | I43: OFF | J43: 11 | K43: =iferror(C43/B43,"-") -> 0.89375 | L43: =(IF(K43="",(0),IF(K43>=1,(5),IF(K43>=0.9,(4),IF(K43>=0.8,(3),IF(K43>=0.69,(2),IF(K43<=0.69,(1)))))))) -> 3
A44: Candy Laid | B44: =30*5+15 -> 165 | C44: =SUM(D44:J44) -> 176 | D44: 39 | E44: 28 | F44: OFF | G44: 38 | H44: 25 | I44: 34 | J44: 12 | K44: =iferror(C44/B44,"-") -> 1.0666667 | L44: =(IF(K44="",(0),IF(K44>=1,(5),IF(K44>=0.9,(4),IF(K44>=0.8,(3),IF(K44>=0.69,(2),IF(K44<=0.69,(1)))))))) -> 5
A45: Mary Claudette Ibong | B45: =30*3+15+25+15 -> 145 | C45: =SUM(D45:J45) -> 131 | D45: 27 | E45: 27 | F45: 17 | G45: 15 | H45: OFF | I45: 26 | J45: 19 | K45: =iferror(C45/B45,"-") -> 0.90344828 | L45: =(IF(K45="",(0),IF(K45>=1,(5),IF(K45>=0.9,(4),IF(K45>=0.8,(3),IF(K45>=0.69,(2),IF(K45<=0.69,(1)))))))) -> 4
A46: Sofhia Mae Santiago | B46: =30*4+20 -> 140 | C46: =SUM(D46:J46) -> 129 | D46: 34 | E46: 18 | F46: 31 | G46: 15 | H46: OFF | I46: 17 | J46: 14 | K46: =iferror(C46/B46,"-") -> 0.92142857 | L46: =(IF(K46="",(0),IF(K46>=1,(5),IF(K46>=0.9,(4),IF(K46>=0.8,(3),IF(K46>=0.69,(2),IF(K46<=0.69,(1)))))))) -> 4
A47: Cherry Tubongbanua | B47: =30*6 -> 180 | C47: =SUM(D47:J47) -> 185 | D47: 39 | E47: 30 | F47: 39 | G47: 32 | H47: 27 | I47: 18 | J47: OFF | K47: =iferror(C47/B47,"-") -> 1.0277778 | L47: =(IF(K47="",(0),IF(K47>=1,(5),IF(K47>=0.9,(4),IF(K47>=0.8,(3),IF(K47>=0.69,(2),IF(K47<=0.69,(1)))))))) -> 5
A48: Lyra Miclat | B48: =30*4 -> 120 | C48: =SUM(D48:J48) -> 96 | D48: 34 | E48: 32 | F48: 30 | G48: A | H48: LWOP | I48: OFF | J48: OFF | K48: =iferror(C48/B48,"-") -> 0.8 | L48: =(IF(K48="",(0),IF(K48>=1,(5),IF(K48>=0.9,(4),IF(K48>=0.8,(3),IF(K48>=0.69,(2),IF(K48<=0.69,(1)))))))) -> 3
A49: Joemica Carino | B49: =25+15+30+30+25+15 -> 140 | C49: =SUM(D49:J49) -> 113 | D49: 18 | E49: 10 | F49: OFF | G49: 22 | H49: 22 | I49: 26 | J49: 15 | K49: =iferror(C49/B49,"-") -> 0.80714286 | L49: =(IF(K49="",(0),IF(K49>=1,(5),IF(K49>=0.9,(4),IF(K49>=0.8,(3),IF(K49>=0.69,(2),IF(K49<=0.69,(1)))))))) -> 3
B51: Weekly Call Stats
A52: Name of Agent | B52: Ringing Attempts | C52: Picked Up | D52: Not Picked Up | E52: Picked Up Rate | F52: AHT | G52: Picked Up Rate Score | H52: AHT Score
A54: Daniellel Mae David | B54: 161 | C54: 155 | D54: =B54-C54 -> 6 | E54: =Iferror(C54/B54,"") -> 0.96273292 | F54: 0.0019907407 | G54: =IFERROR((IF(E54="",(0),IF(E54>=0.98,(5),IF(E54>=0.95,(4.5),IF(E54>=0.9,(4),IF(E54>=0.8,(3),IF(E54<=0.69,(1)))))))),"") -> 4.5 | H54: =ROUND( IF(F54="", 0, MAX(1, 5 - MAX(0, (F54 - TIME(0,4,0)) / TIME(0,1,0) * 0.5)) ), 2 ) -> 5
A55: Godwin Arellano Reasol | B55: 146 | C55: 143 | D55: =B55-C55 -> 3 | E55: =Iferror(C55/B55,"") -> 0.97945205 | F55: 0.0036689815 | G55: =IFERROR((IF(E55="",(0),IF(E55>=0.98,(5),IF(E55>=0.95,(4.5),IF(E55>=0.9,(4),IF(E55>=0.8,(3),IF(E55<=0.69,(1)))))))),"") -> 4.5 | H55: =ROUND( IF(F55="", 0, MAX(1, 5 - MAX(0, (F55 - TIME(0,4,0)) / TIME(0,1,0) * 0.5)) ), 2 ) -> 4.36
A56: Candy Laid | B56: 190 | C56: 176 | D56: =B56-C56 -> 14 | E56: =Iferror(C56/B56,"") -> 0.92631579 | F56: 0.003287037 | G56: =IFERROR((IF(E56="",(0),IF(E56>=0.98,(5),IF(E56>=0.95,(4.5),IF(E56>=0.9,(4),IF(E56>=0.8,(3),IF(E56<=0.69,(1)))))))),"") -> 4 | H56: =ROUND( IF(F56="", 0, MAX(1, 5 - MAX(0, (F56 - TIME(0,4,0)) / TIME(0,1,0) * 0.5)) ), 2 ) -> 4.63
A57: Mary Claudette Ibong | B57: 131 | C57: 130 | D57: =B57-C57 -> 1 | E57: =Iferror(C57/B57,"") -> 0.99236641 | F57: 0.0035300926 | G57: =IFERROR((IF(E57="",(0),IF(E57>=0.98,(5),IF(E57>=0.95,(4.5),IF(E57>=0.9,(4),IF(E57>=0.8,(3),IF(E57<=0.69,(1)))))))),"") -> 5 | H57: =ROUND( IF(F57="", 0, MAX(1, 5 - MAX(0, (F57 - TIME(0,4,0)) / TIME(0,1,0) * 0.5)) ), 2 ) -> 4.46
A58: Sofhia Mae Santiago | B58: 132 | C58: 128 | D58: =B58-C58 -> 4 | E58: =Iferror(C58/B58,"") -> 0.96969697 | F58: 0.0020138889 | G58: =IFERROR((IF(E58="",(0),IF(E58>=0.98,(5),IF(E58>=0.95,(4.5),IF(E58>=0.9,(4),IF(E58>=0.8,(3),IF(E58<=0.69,(1)))))))),"") -> 4.5 | H58: =ROUND( IF(F58="", 0, MAX(1, 5 - MAX(0, (F58 - TIME(0,4,0)) / TIME(0,1,0) * 0.5)) ), 2 ) -> 5
A59: Cherry Tubongbanua | B59: 189 | C59: 185 | D59: =B59-C59 -> 4 | E59: =Iferror(C59/B59,"") -> 0.97883598 | F59: 0.0041550926 | G59: =IFERROR((IF(E59="",(0),IF(E59>=0.98,(5),IF(E59>=0.95,(4.5),IF(E59>=0.9,(4),IF(E59>=0.8,(3),IF(E59<=0.69,(1)))))))),"") -> 4.5 | H59: =ROUND( IF(F59="", 0, MAX(1, 5 - MAX(0, (F59 - TIME(0,4,0)) / TIME(0,1,0) * 0.5)) ), 2 ) -> 4.01
A60: Lyra Miclat | B60: 96 | C60: 96 | D60: =B60-C60 -> 0 | E60: =Iferror(C60/B60,"") -> 1 | F60: 0.0034375 | G60: =IFERROR((IF(E60="",(0),IF(E60>=0.98,(5),IF(E60>=0.95,(4.5),IF(E60>=0.9,(4),IF(E60>=0.8,(3),IF(E60<=0.69,(1)))))))),"") -> 5 | H60: =ROUND( IF(F60="", 0, MAX(1, 5 - MAX(0, (F60 - TIME(0,4,0)) / TIME(0,1,0) * 0.5)) ), 2 ) -> 4.53
A61: Joemica Carino | B61: 119 | C61: 113 | D61: =B61-C61 -> 6 | E61: =Iferror(C61/B61,"") -> 0.94957983 | F61: 0.004537037 | G61: =IFERROR((IF(E61="",(0),IF(E61>=0.98,(5),IF(E61>=0.95,(4.5),IF(E61>=0.9,(4),IF(E61>=0.8,(3),IF(E61<=0.69,(1)))))))),"") -> 4 | H61: =ROUND( IF(F61="", 0, MAX(1, 5 - MAX(0, (F61 - TIME(0,4,0)) / TIME(0,1,0) * 0.5)) ), 2 ) -> 3.73
B64: Score per Metrics for Scorecard (Initial Productivity and QA Scores) | H64: What Does 30% Productivity Covers?
A65: Name of Agent | B65: QA JACKY SCORE 30% | C65: QA TL SCORE 10% | D65: Final QA Score 40% | E65: Productivity (WORK ETHIC) % (30%) | F65: FINAL Work Ethic Score | H65: 1. Final Score from Daily Productivity Record
H66: 2. Picked Up Rate Score
A67: Daniellel Mae David | B67: 1 | C67: 1 | D67: =(B67*0.3)+(C67*0.1) -> 0.4 | E67: =(L42+G54+H54)/15*0.3 -> 0.29 | F67: =(E67/30%)*10 -> 9.6666667 | H67: 3.. AHT Score
A68: Godwin Arellano Reasol | B68: 1 | C68: 1 | D68: =(B68*0.3)+(C68*0.1) -> 0.4 | E68: =(L43+G55+H55)/15*0.3 -> 0.2372 | F68: =(E68/30%)*10 -> 7.9066667
A69: Candy Laid | B69: 0.8 | C69: 1 | D69: =(B69*0.3)+(C69*0.1) -> 0.34 | E69: =(L44+G56+H56)/15*0.3 -> 0.2726 | F69: =(E69/30%)*10 -> 9.0866667 | H69: Computation:
A70: Mary Claudette Ibong | B70: 1 | C70: 1 | D70: =(B70*0.3)+(C70*0.1) -> 0.4 | E70: =(L45+G57+H57)/15*0.3 -> 0.2692 | F70: =(E70/30%)*10 -> 8.9733333 | H70: Final Productivity % | J70: (Final productivity Score + Picked Up Rate Score + AHT Score) /15 *.30
A71: Sofhia Mae Santiago | B71: 0.85 | C71: 1 | D71: =(B71*0.3)+(C71*0.1) -> 0.355 | E71: =(L46+G58+H58)/15*0.3 -> 0.27 | F71: =(E71/30%)*10 -> 9 | H71: Productivity Score | J71: (Final Productivity % / 30%) *10
A72: Cherry Tubongbanua | B72: 1 | C72: 1 | D72: =(B72*0.3)+(C72*0.1) -> 0.4 | E72: =(L47+G59+H59)/15*0.3 -> 0.2702 | F72: =(E72/30%)*10 -> 9.0066667
A73: Lyra Miclat | B73: 1 | C73: 0.8 | D73: =(B73*0.3)+(C73*0.1) -> 0.38 | E73: =(L48+G60+H60)/15*0.3 -> 0.2506 | F73: =(E73/30%)*10 -> 8.3533333
A74: Joemica Carino | B74: 1 | C74: 1 | D74: =(B74*0.3)+(C74*0.1) -> 0.4 | E74: =(L49+G61+H61)/15*0.3 -> 0.2146 | F74: =(E74/30%)*10 -> 7.1533333
B75: WEEK: August 17,2026 - August 23,2026
B76: Daily Productivity Record
A77: Name of Agent | B77: Weekly Target | C77: Actual Productivity | D77: 46251 | E77: 46252 | F77: 46253 | G77: 46254 | H77: 46255 | I77: 46256 | J77: 46257 | K77: Productivity % | L77: Final Score
D78: =text(D77,"ddd") -> Mon | E78: =text(E77,"ddd") -> Tue | F78: =text(F77,"ddd") -> Wed | G78: =text(G77,"ddd") -> Thu | H78: =text(H77,"ddd") -> Fri | I78: =text(I77,"ddd") -> Sat | J78: =text(J77,"ddd") -> Sun
A79: Daniellel Mae David | B79: =30*4+15 -> 135 | C79: =SUM(D79:J79) -> 127 | D79: 29 | E79: 22 | F79: 14 | G79: 21 | H79: OFF | I79: 24 | J79: 17 | K79: =iferror(C79/B79,"-") -> 0.94074074 | L79: =(IF(K79="",(0),IF(K79>=1,(5),IF(K79>=0.9,(4),IF(K79>=0.8,(3),IF(K79>=0.69,(2),IF(K79<=0.69,(1)))))))) -> 4
A80: Godwin Arellano Reasol | B80: =35*5 -> 175 | C80: =SUM(D80:J80) -> 174 | D80: 30 | E80: 38 | F80: 28 | G80: 41 | H80: 37 | I80: OFF | J80: OFF | K80: =iferror(C80/B80,"-") -> 0.99428571 | L80: =(IF(K80="",(0),IF(K80>=1,(5),IF(K80>=0.9,(4),IF(K80>=0.8,(3),IF(K80>=0.69,(2),IF(K80<=0.69,(1)))))))) -> 4
A81: Candy Laid | B81: =30*5+15 -> 165 | C81: =SUM(D81:J81) -> 150 | D81: 44 | E81: 27 | F81: OFF | G81: 15 | H81: 31 | I81: 26 | J81: 7 | K81: =iferror(C81/B81,"-") -> 0.90909091 | L81: =(IF(K81="",(0),IF(K81>=1,(5),IF(K81>=0.9,(4),IF(K81>=0.8,(3),IF(K81>=0.69,(2),IF(K81<=0.69,(1)))))))) -> 4
A82: Mary Claudette Ibong | B82: =30*3+20+15 -> 125 | C82: =SUM(D82:J82) -> 117 | D82: 28 | E82: 28 | F82: 25 | G82: OFF | H82: OFF | I82: 20 | J82: 16 | K82: =iferror(C82/B82,"-") -> 0.936 | L82: =(IF(K82="",(0),IF(K82>=1,(5),IF(K82>=0.9,(4),IF(K82>=0.8,(3),IF(K82>=0.69,(2),IF(K82<=0.69,(1)))))))) -> 4
A83: Sofhia Mae Santiago | B83: =30*4+20 -> 140 | C83: =SUM(D83:J83) -> 151 | D83: 38 | E83: 20 | F83: 26 | G83: 29 | H83: 38 | I83: OFF | J83: OFF | K83: =iferror(C83/B83,"-") -> 1.0785714 | L83: =(IF(K83="",(0),IF(K83>=1,(5),IF(K83>=0.9,(4),IF(K83>=0.8,(3),IF(K83>=0.69,(2),IF(K83<=0.69,(1)))))))) -> 5
A84: Cherry Tubongbanua | B84: =30*6 -> 180 | C84: =SUM(D84:J84) -> 190 | D84: 40 | E84: 32 | F84: 39 | G84: 34 | H84: 27 | I84: 18 | J84: OFF | K84: =iferror(C84/B84,"-") -> 1.0555556 | L84: =(IF(K84="",(0),IF(K84>=1,(5),IF(K84>=0.9,(4),IF(K84>=0.8,(3),IF(K84>=0.69,(2),IF(K84<=0.69,(1)))))))) -> 5
A85: Lyra Miclat | B85: =30*4 -> 120 | C85: =SUM(D85:J85) -> 142 | D85: 30 | E85: 34 | F85: 33 | G85: 22 | H85: 23 | I85: OFF | J85: OFF | K85: =iferror(C85/B85,"-") -> 1.1833333 | L85: =(IF(K85="",(0),IF(K85>=1,(5),IF(K85>=0.9,(4),IF(K85>=0.8,(3),IF(K85>=0.69,(2),IF(K85<=0.69,(1)))))))) -> 5
A86: Joemica Carino | B86: =25+15+30+30+25+15 -> 140 | C86: =SUM(D86:J86) -> 106 | D86: 22 | E86: OFF | F86: OFF | G86: 19 | H86: 26 | I86: 25 | J86: 14 | K86: =iferror(C86/B86,"-") -> 0.75714286 | L86: =(IF(K86="",(0),IF(K86>=1,(5),IF(K86>=0.9,(4),IF(K86>=0.8,(3),IF(K86>=0.69,(2),IF(K86<=0.69,(1)))))))) -> 2
B88: Weekly Call Stats
A89: Name of Agent | B89: Ringing Attempts | C89: Picked Up | D89: Not Picked Up | E89: Picked Up Rate | F89: AHT | G89: Picked Up Rate Score | H89: AHT Score
A91: Daniellel Mae David | B91: 130 | C91: 127 | D91: =B91-C91 -> 3 | E91: =Iferror(C91/B91,"") -> 0.97692308 | F91: 0.0019675926 | G91: =IFERROR((IF(E91="",(0),IF(E91>=0.98,(5),IF(E91>=0.95,(4.5),IF(E91>=0.9,(4),IF(E91>=0.8,(3),IF(E91<=0.69,(1)))))))),"") -> 4.5 | H91: =ROUND( IF(F91="", 0, MAX(1, 5 - MAX(0, (F91 - TIME(0,4,0)) / TIME(0,1,0) * 0.5)) ), 2 ) -> 5
A92: Godwin Arellano Reasol | B92: 175 | C92: 174 | D92: =B92-C92 -> 1 | E92: =Iferror(C92/B92,"") -> 0.99428571 | F92: 0.0033680556 | G92: =IFERROR((IF(E92="",(0),IF(E92>=0.98,(5),IF(E92>=0.95,(4.5),IF(E92>=0.9,(4),IF(E92>=0.8,(3),IF(E92<=0.69,(1)))))))),"") -> 5 | H92: =ROUND( IF(F92="", 0, MAX(1, 5 - MAX(0, (F92 - TIME(0,4,0)) / TIME(0,1,0) * 0.5)) ), 2 ) -> 4.58
A93: Candy Laid | B93: 169 | C93: 166 | D93: =B93-C93 -> 3 | E93: =Iferror(C93/B93,"") -> 0.98224852 | F93: 0.0031944444 | G93: =IFERROR((IF(E93="",(0),IF(E93>=0.98,(5),IF(E93>=0.95,(4.5),IF(E93>=0.9,(4),IF(E93>=0.8,(3),IF(E93<=0.69,(1)))))))),"") -> 5 | H93: =ROUND( IF(F93="", 0, MAX(1, 5 - MAX(0, (F93 - TIME(0,4,0)) / TIME(0,1,0) * 0.5)) ), 2 ) -> 4.7
A94: Mary Claudette Ibong | B94: 137 | C94: 132 | D94: =B94-C94 -> 5 | E94: =Iferror(C94/B94,"") -> 0.96350365 | F94: 0.0031944444 | G94: =IFERROR((IF(E94="",(0),IF(E94>=0.98,(5),IF(E94>=0.95,(4.5),IF(E94>=0.9,(4),IF(E94>=0.8,(3),IF(E94<=0.69,(1)))))))),"") -> 4.5 | H94: =ROUND( IF(F94="", 0, MAX(1, 5 - MAX(0, (F94 - TIME(0,4,0)) / TIME(0,1,0) * 0.5)) ), 2 ) -> 4.7
A95: Sofhia Mae Santiago | B95: 158 | C95: 151 | D95: =B95-C95 -> 7 | E95: =Iferror(C95/B95,"") -> 0.9556962 | F95: 0.0022106481 | G95: =IFERROR((IF(E95="",(0),IF(E95>=0.98,(5),IF(E95>=0.95,(4.5),IF(E95>=0.9,(4),IF(E95>=0.8,(3),IF(E95<=0.69,(1)))))))),"") -> 4.5 | H95: =ROUND( IF(F95="", 0, MAX(1, 5 - MAX(0, (F95 - TIME(0,4,0)) / TIME(0,1,0) * 0.5)) ), 2 ) -> 5
A96: Cherry Tubongbanua | B96: 200 | C96: 190 | D96: =B96-C96 -> 10 | E96: =Iferror(C96/B96,"") -> 0.95 | F96: 0.0044097222 | G96: =IFERROR((IF(E96="",(0),IF(E96>=0.98,(5),IF(E96>=0.95,(4.5),IF(E96>=0.9,(4),IF(E96>=0.8,(3),IF(E96<=0.69,(1)))))))),"") -> 4.5 | H96: =ROUND( IF(F96="", 0, MAX(1, 5 - MAX(0, (F96 - TIME(0,4,0)) / TIME(0,1,0) * 0.5)) ), 2 ) -> 3.83
A97: Lyra Miclat | B97: 147 | C97: 142 | D97: =B97-C97 -> 5 | E97: =Iferror(C97/B97,"") -> 0.96598639 | F97: 0.0033680556 | G97: =IFERROR((IF(E97="",(0),IF(E97>=0.98,(5),IF(E97>=0.95,(4.5),IF(E97>=0.9,(4),IF(E97>=0.8,(3),IF(E97<=0.69,(1)))))))),"") -> 4.5 | H97: =ROUND( IF(F97="", 0, MAX(1, 5 - MAX(0, (F97 - TIME(0,4,0)) / TIME(0,1,0) * 0.5)) ), 2 ) -> 4.58
A98: Joemica Carino | B98: 108 | C98: 106 | D98: =B98-C98 -> 2 | E98: =Iferror(C98/B98,"") -> 0.98148148 | F98: 0.0041782407 | G98: =IFERROR((IF(E98="",(0),IF(E98>=0.98,(5),IF(E98>=0.95,(4.5),IF(E98>=0.9,(4),IF(E98>=0.8,(3),IF(E98<=0.69,(1)))))))),"") -> 5 | H98: =ROUND( IF(F98="", 0, MAX(1, 5 - MAX(0, (F98 - TIME(0,4,0)) / TIME(0,1,0) * 0.5)) ), 2 ) -> 3.99
B101: Score per Metrics for Scorecard (Initial Productivity and QA Scores) | H101: What Does 30% Productivity Covers?
A102: Name of Agent | B102: QA JACKY SCORE 30% | C102: QA TL SCORE 10% | D102: Final QA Score 40% | E102: Productivity (WORK ETHIC) % (30%) | F102: FINAL Work Ethic Score | H102: 1. Final Score from Daily Productivity Record
H103: 2. Picked Up Rate Score
A104: Daniellel Mae David | B104: 1 | C104: 1 | D104: =(B104*0.3)+(C104*0.1) -> 0.4 | E104: =(L79+G91+H91)/15*0.3 -> 0.27 | F104: =(E104/30%)*10 -> 9 | H104: 3.. AHT Score
A105: Godwin Arellano Reasol | B105: 1 | C105: 1 | D105: =(B105*0.3)+(C105*0.1) -> 0.4 | E105: =(L80+G92+H92)/15*0.3 -> 0.2716 | F105: =(E105/30%)*10 -> 9.0533333
A106: Candy Laid | B106: 0.7 | C106: 1 | D106: =(B106*0.3)+(C106*0.1) -> 0.31 | E106: =(L81+G93+H93)/15*0.3 -> 0.274 | F106: =(E106/30%)*10 -> 9.1333333 | H106: Computation:
A107: Mary Claudette Ibong | B107: 0.7 | C107: 1 | D107: =(B107*0.3)+(C107*0.1) -> 0.31 | E107: =(L82+G94+H94)/15*0.3 -> 0.264 | F107: =(E107/30%)*10 -> 8.8 | H107: Final Productivity % | J107: (Final productivity Score + Picked Up Rate Score + AHT Score) /15 *.30
A108: Sofhia Mae Santiago | B108: 1 | C108: 1 | D108: =(B108*0.3)+(C108*0.1) -> 0.4 | E108: =(L83+G95+H95)/15*0.3 -> 0.29 | F108: =(E108/30%)*10 -> 9.6666667 | H108: Productivity Score | J108: (Final Productivity % / 30%) *10
A109: Cherry Tubongbanua | B109: 1 | C109: 1 | D109: =(B109*0.3)+(C109*0.1) -> 0.4 | E109: =(L84+G96+H96)/15*0.3 -> 0.2666 | F109: =(E109/30%)*10 -> 8.8866667
A110: Lyra Miclat | B110: 1 | C110: 1 | D110: =(B110*0.3)+(C110*0.1) -> 0.4 | E110: =(L85+G97+H97)/15*0.3 -> 0.2816 | F110: =(E110/30%)*10 -> 9.3866667
A111: Joemica Carino | B111: 1 | C111: 1 | D111: =(B111*0.3)+(C111*0.1) -> 0.4 | E111: =(L86+G98+H98)/15*0.3 -> 0.2198 | F111: =(E111/30%)*10 -> 7.3266667
B112: WEEK: August 24,2026 - August 30,2026
...

Sheet WEEKLY SCORECARD
B1: WEEK:January 26 ,2026 - February 1,2026
B2: Danielle David | C2: Godwin Reasol | D2: Candy Laid | E2: Claudette Ibong | F2: Sofhia Santiago | G2: Cherry Tubongbanua
A3: Week Ending | B3: WEEK: January 26 ,2026 - February 1,2026
A4: ATTENDANCE
A5: Hours Worked | B5: 47.24 | C5: 44 | D5: 46 | E5: 51.93 | F5: 43.54 | G5: 52.44
A6: Hours Scheduled | B6: 40 | C6: 40 | D6: 40 | E6: 40 | F6: 40 | G6: 40
A7: Attendance % | B7: =B5/B6 -> 1.181 | C7: =C5/C6 -> 1.1 | D7: =D5/D6 -> 1.15 | E7: =E5/E6 -> 1.29825 | F7: =F5/F6 -> 1.0885 | G7: =G5/G6 -> 1.311
A8: QUALITY
A9: QA Score | B9: 40 | C9: 39.90 | D9: 37.40 | E9: 40 | F9: 40 | G9: 40
A10: QA Max | B10: 40 | C10: 40 | D10: 40 | E10: 40 | F10: 40 | G10: 40
A11: Quality % | B11: =B9/B10 -> 1 | C11: =C9/C10 -> 0.9975 | D11: =D9/D10 -> 0.935 | E11: =E9/E10 -> 1 | F11: =F9/F10 -> 1 | G11: =G9/G10 -> 1
A12: PRODUCTIVITY
A13: Shift | B13: MID | C13: AM | D13: AM | E13: AM | F13: AM | G13: MID
A14: Team Assignment' | B14: Other Brands | C14: Oricle | D14: Other Brands | E14: Oricle | F14: Other Brands | G14: Oricle
A15: Call Target # | B15: =IF(B5<B6,B6,B5) * IF(B13="AM", IF(B14="Oricle",4, IF(B14="Other Brands",3, IF(B14="Oricle Prio",0.6,""))), IF(B13="MID", IF(B14="Oricle",2.5, IF(B14="Other Brands",3, IF(B14="Oricle Prio",0.6,""))), IF(B13="GY", IF(B14="Oricle",0.9, IF(B14="Other Brands",0.9, IF(B14="Oricle Prio",0.3,""))),"")))-17 -> 124.72 | C15: =IF(C5<C6,C6,C5) * IF(C13="AM", IF(C14="Oricle",4, IF(C14="Other Brands",3, IF(C14="Oricle Prio",0.6,""))), IF(C13="MID", IF(C14="Oricle",2.5, IF(C14="Other Brands",3, IF(C14="Oricle Prio",0.6,""))), IF(C13="GY", IF(C14="Oricle",0.9, IF(C14="Other Brands",0.9, IF(C14="Oricle Prio",0.3,""))),""))) -> 176 | D15: =IF(D5<D6,D6,D5) * IF(D13="AM", IF(D14="Oricle",4, IF(D14="Other Brands",3, IF(D14="Oricle Prio",0.6,""))), IF(D13="MID", IF(D14="Oricle",2.5, IF(D14="Other Brands",3, IF(D14="Oricle Prio",0.6,""))), IF(D13="GY", IF(D14="Oricle",0.9, IF(D14="Other Brands",0.9, IF(D14="Oricle Prio",0.3,""))),""))) -> 138 | E15: =IF(E5<E6,E6,E5) * IF(E13="AM", IF(E14="Oricle",4, IF(E14="Other Brands",3, IF(E14="Oricle Prio",0.6,""))), IF(E13="MID", IF(E14="Oricle",2.5, IF(E14="Other Brands",3, IF(E14="Oricle Prio",0.6,""))), IF(E13="GY", IF(E14="Oricle",0.9, IF(E14="Other Brands",0.9, IF(E14="Oricle Prio",0.3,""))),""))) -> 207.72 | F15: =IF(F5<F6,F6,F5) * IF(F13="AM", IF(F14="Oricle",4, IF(F14="Other Brands",3, IF(F14="Oricle Prio",0.6,""))), IF(F13="MID", IF(F14="Oricle",2.5, IF(F14="Other Brands",3, IF(F14="Oricle Prio",0.6,""))), IF(F13="GY", IF(F14="Oricle",0.9, IF(F14="Other Brands",0.9, IF(F14="Oricle Prio",0.3,""))),""))) -> 130.62 | G15: =IF(G5<G6,G6,G5) * IF(G13="AM", IF(G14="Oricle",4, IF(G14="Other Brands",3, IF(G14="Oricle Prio",0.6,""))), IF(G13="MID", IF(G14="Oricle",2.5, IF(G14="Other Brands",3, IF(G14="Oricle Prio",0.6,""))), IF(G13="GY", IF(G14="Oricle",0.9, IF(G14="Other Brands",0.9, IF(G14="Oricle Prio",0.3,""))),""))) -> 131.1
A16: Total Call # | B16: 144 | C16: 119 | D16: 137 | E16: 187 | F16: 171 | G16: 129
A17: Call Pick Up # | B17: 141 | C17: 119 | D17: 131 | E17: 183 | F17: 169 | G17: 129
A18: Pick Up % | B18: =IF(B16>0,B17/B16,0) -> 0.97916667 | C18: =IF(C16>0,C17/C16,0) -> 1 | D18: =IF(D16>0,D17/D16,0) -> 0.95620438 | E18: =IF(E16>0,E17/E16,0) -> 0.97860963 | F18: =IF(F16>0,F17/F16,0) -> 0.98830409 | G18: =IF(G16>0,G17/G16,0) -> 1 | H18: =IF(H16>0,H17/H16,0) -> 0
A19: Target Completion% | B19: =IF(B15>0,B17/B15,0) -> 1.1305324 | C19: =IF(C15>0,C17/C15,0) -> 0.67613636 | D19: =IF(D15>0,D17/D15,0) -> 0.94927536 | E19: =IF(E15>0,E17/E15,0) -> 0.88099365 | F19: =IF(F15>0,F17/F15,0) -> 1.2938294 | G19: =IF(G15>0,G17/G15,0) -> 0.98398169 | H19: =IF(H15>0,H17/H15,0) -> 0
A20: Productivity % | B20: =average(B18:B19) -> 1.0548495 | C20: =average(C18:C19) -> 0.83806818 | D20: =average(D18:D19) -> 0.95273987 | E20: =average(E18:E19) -> 0.92980164 | F20: =average(F18:F19) -> 1.1410668 | G20: =average(G18:G19) -> 0.99199085 | H20: =average(H18:H19) -> 0
A21: WORK ETHIC (10 pts)
A22: Work Ethic Score | B22: 10 | C22: 9.33 | D22: 8.77 | E22: 9.66 | F22: 8.93 | G22: 9.33 | H22: 9.33
A23: Work Ethic Max | B23: 10 | C23: 10 | D23: 10 | E23: 10 | F23: 10 | G23: 10 | H23: 10
A24: Work Ethic % | B24: =IF(B22=0,0,B22/B23) -> 1 | C24: =IF(C22=0,0,C22/C23) -> 0.933 | D24: =IF(D22=0,0,D22/D23) -> 0.877 | E24: =IF(E22=0,0,E22/E23) -> 0.966 | F24: =IF(F22=0,0,F22/F23) -> 0.893 | G24: =IF(G22=0,0,G22/G23) -> 0.933 | H24: =IF(H22=0,0,H22/H23) -> 0.933
A25: INFRACTIONS (-10 pts)
A26: Number of Infractions | B26: 0 | C26: 0 | D26: 0 | E26: 0 | F26: 0 | G26: 0 | H26: 0
A27: FINAL SCORE
A28: Attendance Weighted (25%) | B28: =B7*25 -> 29.525 | C28: =C7*25 -> 27.5 | D28: =D7*25 -> 28.75 | E28: =E7*25 -> 32.45625 | F28: =F7*25 -> 27.2125 | G28: =G7*25 -> 32.775 | H28: =H7*25 -> 0
A29: Quality Weighted (35%) | B29: =B11*35 -> 35 | C29: =C11*35 -> 34.9125 | D29: =D11*35 -> 32.725 | E29: =E11*35 -> 35 | F29: =F11*35 -> 35 | G29: =G11*35 -> 35 | H29: =H11*35 -> 0
A30: Productivity Weighted (25%) | B30: =if(B7<100%,B20*25,B20*30) -> 31.645486 | C30: =if(C7<100%,C20*25,C20*30) -> 25.142045 | D30: =if(D7<100%,D20*25,D20*30) -> 28.582196 | E30: =if(E7<100%,E20*25,E20*30) -> 27.894049 | F30: =if(F7<100%,F20*25,F20*30) -> 34.232003 | G30: =if(G7<100%,G20*25,G20*30) -> 29.759725 | H30: =if(H7<100%,H20*25,H20*30) -> 0
A31: Work Ethic Weighted (15%) | B31: =B24*15 -> 15 | C31: =C24*15 -> 13.995 | D31: =D24*15 -> 13.155 | E31: =E24*15 -> 14.49 | F31: =F24*15 -> 13.395 | G31: =G24*15 -> 13.995 | H31: =H24*15 -> 13.995
A32: Infractions Penalty | B32: =B26*-10 -> 0 | C32: =C26*-10 -> 0 | D32: =D26*-10 -> 0 | E32: =E26*-10 -> 0 | F32: =F26*-10 -> 0 | G32: =G26*-10 -> 0 | H32: =H26*-10 -> 0
A33: TOTAL SCORE (out of 100) | B33: =B28+B29+B30+B31+B32 -> 111.17049 | C33: =C28+C29+C30+C31+C32 -> 101.54955 | D33: =D28+D29+D30+D31+D32 -> 103.2122 | E33: =E28+E29+E30+E31+E32 -> 109.8403 | F33: =F28+F29+F30+F31+F32 -> 109.8395 | G33: =G28+G29+G30+G31+G32 -> 111.52973 | H33: =H28+H29+H30+H31+H32 -> 13.995
A34: Overall % | B34: =B33/100 -> 1.1117049 | C34: =C33/100 -> 1.0154955 | D34: =D33/100 -> 1.032122 | E34: =E33/100 -> 1.098403 | F34: =F33/100 -> 1.098395 | G34: =G33/100 -> 1.1152973 | H34: =H33/100 -> 0.13995
A35: TEAM RANKING | B35: Good | C35: Good | D35: Good | E35: Good | F35: Good | G35: Top Performer | H35: Low Performer
A36: COMMENTS/ISSUES | H36: -CSR struggles on searching fo the customer's target which prolongs the call. Aside from this, CSR failed to provide proper resolution on some call tickets
A37: ~````````````````````
B38: WEEK: February 2 ,2026 - February 8,2026
B39: Danielle David | C39: Godwin Reasol | D39: Candy Laid | E39: Claudette Ibong | F39: Sofhia Santiago | G39: Cherry Tubongbanua
A40: Week Ending | B40: WEEK: February 2 ,2026 - February 8,2026
A41: ATTENDANCE
A42: Hours Worked | B42: 47.37 | C42: 54.05 | D42: 46.94 | E42: 51.52 | F42: 29.74 | G42: 52.18
A43: Hours Scheduled | B43: 37 | C43: 40 | D43: 40 | E43: 37 | F43: 28.5 | G43: 40
A44: Attendance % | B44: =B42/B43 -> 1.2802703 | C44: =C42/C43 -> 1.35125 | D44: =D42/D43 -> 1.1735 | E44: =E42/E43 -> 1.3924324 | F44: =F42/F43 -> 1.0435088 | G44: =G42/G43 -> 1.3045
A45: QUALITY
A46: QA Score | B46: 40 | C46: 40 | D46: 40 | E46: 40 | F46: 40 | G46: 40
A47: QA Max | B47: 40 | C47: 40 | D47: 40 | E47: 40 | F47: 40 | G47: 40 | H47: 40
A48: Quality % | B48: =B46/B47 -> 1 | C48: =C46/C47 -> 1 | D48: =D46/D47 -> 1 | E48: =E46/E47 -> 1 | F48: =F46/F47 -> 1 | G48: =G46/G47 -> 1 | H48: =H46/H47 -> 0
A49: PRODUCTIVITY
A50: Shift | B50: MID | C50: AM | D50: AM | E50: AM | F50: AM | G50: MID | H50: AM
A51: Team Assignment' | B51: Other Brands | C51: Oricle | D51: Other Brands | E51: Oricle | F51: Other Brands | G51: Oricle | H51: Oricle
A52: Call Target # | B52: =IF(B42<B43,B43,B42) * IF(B50="AM", IF(B51="Oricle",4, IF(B51="Other Brands",3, IF(B51="Oricle Prio",0.6,""))), IF(B50="MID", IF(B51="Oricle",2.5, IF(B51="Other Brands",3, IF(B51="Oricle Prio",0.6,""))), IF(B50="GY", IF(B51="Oricle",0.9, IF(B51="Other Brands",0.9, IF(B51="Oricle Prio",0.3,""))),"")))-17 -> 125.11 | C52: =IF(C42<C43,C43,C42) * IF(C50="AM", IF(C51="Oricle",4, IF(C51="Other Brands",3, IF(C51="Oricle Prio",0.6,""))), IF(C50="MID", IF(C51="Oricle",2.5, IF(C51="Other Brands",3, IF(C51="Oricle Prio",0.6,""))), IF(C50="GY", IF(C51="Oricle",0.9, IF(C51="Other Brands",0.9, IF(C51="Oricle Prio",0.3,""))),""))) -> 216.2 | D52: =IF(D42<D43,D43,D42) * IF(D50="AM", IF(D51="Oricle",4, IF(D51="Other Brands",3, IF(D51="Oricle Prio",0.6,""))), IF(D50="MID", IF(D51="Oricle",2.5, IF(D51="Other Brands",3, IF(D51="Oricle Prio",0.6,""))), IF(D50="GY", IF(D51="Oricle",0.9, IF(D51="Other Brands",0.9, IF(D51="Oricle Prio",0.3,""))),""))) -> 140.82 | E52: =IF(E42<E43,E43,E42) * IF(E50="AM", IF(E51="Oricle",4, IF(E51="Other Brands",3, IF(E51="Oricle Prio",0.6,""))), IF(E50="MID", IF(E51="Oricle",2.5, IF(E51="Other Brands",3, IF(E51="Oricle Prio",0.6,""))), IF(E50="GY", IF(E51="Oricle",0.9, IF(E51="Other Brands",0.9, IF(E51="Oricle Prio",0.3,""))),"")))-25-13 -> 168.08 | F52: =IF(F42<F43,F43,F42) * IF(F50="AM", IF(F51="Oricle",4, IF(F51="Other Brands",3, IF(F51="Oricle Prio",0.6,""))), IF(F50="MID", IF(F51="Oricle",2.5, IF(F51="Other Brands",3, IF(F51="Oricle Prio",0.6,""))), IF(F50="GY", IF(F51="Oricle",0.9, IF(F51="Other Brands",0.9, IF(F51="Oricle Prio",0.3,""))),""))) -> 89.22 | G52: =IF(G42<G43,G43,G42) * IF(G50="AM", IF(G51="Oricle",4, IF(G51="Other Brands",3, IF(G51="Oricle Prio",0.6,""))), IF(G50="MID", IF(G51="Oricle",2.5, IF(G51="Other Brands",3, IF(G51="Oricle Prio",0.6,""))), IF(G50="GY", IF(G51="Oricle",0.9, IF(G51="Other Brands",0.9, IF(G51="Oricle Prio",0.3,""))),""))) -> 130.45 | H52: =IF(H42<#REF!,#REF!,H42) * IF(H50="AM", IF(H51="Oricle",2.5, IF(H51="Other Brands",3, IF(H51="Oricle Prio",0.6,""))), IF(H50="MID", IF(H51="Oricle",2.5, IF(H51="Other Brands",3, IF(H51="Oricle Prio",0.6,""))), IF(H50="GY", IF(H51="Oricle",0.9, IF(H51="Other Brands",0.9, IF(H51="Oricle Prio",0.3,""))),""))) -> #REF!
A53: Total Call # | B53: 130 | C53: 155 | D53: 178 | E53: 183 | F53: 90 | G53: 172
A54: Call Pick Up # | B54: 126 | C54: 154 | D54: 174 | E54: 180 | F54: 89 | G54: 172
A55: Pick Up % | B55: =IF(B53>0,B54/B53,0) -> 0.96923077 | C55: =IF(C53>0,C54/C53,0) -> 0.99354839 | D55: =IF(D53>0,D54/D53,0) -> 0.97752809 | E55: =IF(E53>0,E54/E53,0) -> 0.98360656 | F55: =IF(F53>0,F54/F53,0) -> 0.98888889 | G55: =IF(G53>0,G54/G53,0) -> 1 | H55: =IF(H53>0,H54/H53,0) -> 0
A56: Target Completion% | B56: =IF(B52>0,B54/B52,0) -> 1.0071137 | C56: =IF(C52>0,C54/C52,0) -> 0.71230342 | D56: =IF(D52>0,D54/D52,0) -> 1.2356199 | E56: =IF(E52>0,E54/E52,0) -> 1.0709186 | F56: =IF(F52>0,F54/F52,0) -> 0.99753419 | G56: =IF(G52>0,G54/G52,0) -> 1.3185128 | H56: =IF(H52>0,H54/H52,0) -> #REF!
A57: Productivity % | B57: =average(B55:B56) -> 0.98817225 | C57: =average(C55:C56) -> 0.8529259 | D57: =average(D55:D56) -> 1.106574 | E57: =average(E55:E56) -> 1.0272626 | F57: =average(F55:F56) -> 0.99321154 | G57: =average(G55:G56) -> 1.1592564 | H57: =average(H55:H56) -> #REF!
A58: WORK ETHIC (10 pts)
A59: Work Ethic Score | B59: 9.66 | C59: 9.33 | D59: 9.45 | E59: 10 | F59: 9.85 | G59: 10
A60: Work Ethic Max | B60: 10 | C60: 10 | D60: 10 | E60: 10 | F60: 10 | G60: 10 | H60: 10
A61: Work Ethic % | B61: =IF(B59=0,0,B59/B60) -> 0.966 | C61: =IF(C59=0,0,C59/C60) -> 0.933 | D61: =IF(D59=0,0,D59/D60) -> 0.945 | E61: =IF(E59=0,0,E59/E60) -> 1 | F61: =IF(F59=0,0,F59/F60) -> 0.985 | G61: =IF(G59=0,0,G59/G60) -> 1 | H61: =IF(H59=0,0,H59/H60) -> 0
A62: INFRACTIONS (-10 pts)
A63: Number of Infractions | B63: 0 | C63: 0 | D63: 0 | E63: 0 | F63: 0 | G63: 0 | H63: 0
A64: FINAL SCORE
A65: Attendance Weighted (25%) | B65: =B44*25 -> 32.006757 | C65: =C44*25 -> 33.78125 | D65: =D44*25 -> 29.3375 | E65: =E44*25 -> 34.810811 | F65: =F44*25 -> 26.087719 | G65: =G44*25 -> 32.6125 | H65: =H43*25 -> 0
A66: Quality Weighted (35%) | B66: =B48*35 -> 35 | C66: =C48*35 -> 35 | D66: =D48*35 -> 35 | E66: =E48*35 -> 35 | F66: =F48*35 -> 35 | G66: =G48*35 -> 35 | H66: =H48*35 -> 0
A67: Productivity Weighted (25%) | B67: =IF(AND(B48<85%, B57>100%), 25, B57*25) -> 24.704306 | C67: =IF(AND(C48<85%, C57>100%), 25, C57*25) -> 21.323148 | D67: =IF(AND(D48<85%, D57>100%), 25, D57*25) -> 27.66435 | E67: =IF(AND(E48<85%, E57>100%), 25, E57*25) -> 25.681565 | F67: =IF(AND(F48<85%, F57>100%), 25, F57*25) -> 24.830288 | G67: =IF(AND(G48<85%, G57>100%), 25, G57*25) -> 28.98141 | H67: =IF(AND(H48<85%, H57>100%), 25, H57*25) -> #REF!
A68: Work Ethic Weighted (15%) | B68: =B61*15 -> 14.49 | C68: =C61*15 -> 13.995 | D68: =D61*15 -> 14.175 | E68: =E61*15 -> 15 | F68: =F61*15 -> 14.775 | G68: =G61*15 -> 15 | H68: =H61*15 -> 0
A69: Infractions Penalty | B69: =B63*-10 -> 0 | C69: =C63*-10 -> 0 | D69: =D63*-10 -> 0 | E69: =E63*-10 -> 0 | F69: =F63*-10 -> 0 | G69: =G63*-10 -> 0 | H69: =H63*-10 -> 0
A70: TOTAL SCORE (out of 100) | B70: =B65+B66+B67+B68+B69 -> 106.20106 | C70: =C65+C66+C67+C68+C69 -> 104.0994 | D70: =D65+D66+D67+D68+D69 -> 106.17685 | E70: =E65+E66+E67+E68+E69 -> 110.49238 | F70: =F65+F66+F67+F68+F69 -> 100.69301 | G70: =G65+G66+G67+G68+G69 -> 111.59391 | H70: =H65+H66+H67+H68+H69 -> #REF!
A71: Overall % | B71: =B70/100 -> 1.0620106 | C71: =C70/100 -> 1.040994 | D71: =D70/100 -> 1.0617685 | E71: =E70/100 -> 1.1049238 | F71: =F70/100 -> 1.0069301 | G71: =G70/100 -> 1.1159391 | H71: =H70/100 -> #REF!
A72: TEAM RANKING | B72: Good | C72: Good | D72: Good | E72: Good | F72: Good | G72: Top Performer | H72: Good
A73: COMMENTS/ISSUES
B74: WEEK: February 9 ,2026 - February 15,2026
B75: Danielle David | C75: Godwin Reasol | D75: Candy Laid | E75: Claudette Ibong | F75: Sofhia Santiago | G75: Cherry Tubongbanua | H75: Lyra Miclat
A76: Week Ending | B76: WEEK: February 9 ,2026 - February 15,2026
A77: ATTENDANCE
A78: Hours Worked | B78: 31.53 | C78: 54.51 | D78: 48.26 | E78: 44.06 | F78: 53.22 | G78: 54.41 | H78: 40
A79: Hours Scheduled | B79: 37 | C79: 40 | D79: 40 | E79: 37 | F79: 39.5 | G79: 40 | H79: 40
A80: Attendance % | B80: =B78/B79 -> 0.85216216 | C80: =C78/C79 -> 1.36275 | D80: =D78/D79 -> 1.2065 | E80: =E78/E79 -> 1.1908108 | F80: =F78/F79 -> 1.3473418 | G80: =G78/G79 -> 1.36025 | H80: =H78/H79 -> 1
A81: QUALITY
A82: QA Score | B82: 40 | C82: 40 | D82: 40 | E82: 40 | F82: 40 | G82: 39.83 | H82: 36.4
A83: QA Max | B83: 40 | C83: 40 | D83: 40 | E83: 40 | F83: 40 | G83: 40 | H83: 40
A84: Quality % | B84: =B82/B83 -> 1 | C84: =C82/C83 -> 1 | D84: =D82/D83 -> 1 | E84: =E82/E83 -> 1 | F84: =F82/F83 -> 1 | G84: =G82/G83 -> 0.99575 | H84: =H82/H83 -> 0.91
A85: PRODUCTIVITY
A86: Shift | B86: MID | C86: AM | D86: AM | E86: AM | F86: AM | G86: MID | H86: MID
A87: Team Assignment' | B87: Other Brands | C87: Oricle | D87: Other Brands | E87: Oricle | F87: Other Brands | G87: Oricle | H87: Oricle
A88: Call Target # | B88: =IF(B78<B79,B79,B78) * IF(B86="AM", IF(B87="Oricle",4, IF(B87="Other Brands",3, IF(B87="Oricle Prio",0.6,""))), IF(B86="MID", IF(B87="Oricle",2.5, IF(B87="Other Brands",3, IF(B87="Oricle Prio",0.6,""))), IF(B86="GY", IF(B87="Oricle",0.9, IF(B87="Other Brands",0.9, IF(B87="Oricle Prio",0.3,""))),"")))-17 -> 94 | C88: =IF(C78<C79,C79,C78) * IF(C86="AM", IF(C87="Oricle",4, IF(C87="Other Brands",3, IF(C87="Oricle Prio",0.6,""))), IF(C86="MID", IF(C87="Oricle",2.5, IF(C87="Other Brands",3, IF(C87="Oricle Prio",0.6,""))), IF(C86="GY", IF(C87="Oricle",0.9, IF(C87="Other Brands",0.9, IF(C87="Oricle Prio",0.3,""))),""))) -> 218.04 | D88: =IF(D78<D79,D79,D78) * IF(D86="AM", IF(D87="Oricle",4, IF(D87="Other Brands",3, IF(D87="Oricle Prio",0.6,""))), IF(D86="MID", IF(D87="Oricle",2.5, IF(D87="Other Brands",3, IF(D87="Oricle Prio",0.6,""))), IF(D86="GY", IF(D87="Oricle",0.9, IF(D87="Other Brands",0.9, IF(D87="Oricle Prio",0.3,""))),""))) -> 144.78 | E88: =IF(E78<E79,E79,E78) * IF(E86="AM", IF(E87="Oricle",4, IF(E87="Other Brands",3, IF(E87="Oricle Prio",0.6,""))), IF(E86="MID", IF(E87="Oricle",2.5, IF(E87="Other Brands",3, IF(E87="Oricle Prio",0.6,""))), IF(E86="GY", IF(E87="Oricle",0.9, IF(E87="Other Brands",0.9, IF(E87="Oricle Prio",0.3,""))),"")))-25-13 -> 138.24 | F88: =IF(F78<F79,F79,F78) * IF(F86="AM", IF(F87="Oricle",4, IF(F87="Other Brands",3, IF(F87="Oricle Prio",0.6,""))), IF(F86="MID", IF(F87="Oricle",2.5, IF(F87="Other Brands",3, IF(F87="Oricle Prio",0.6,""))), IF(F86="GY", IF(F87="Oricle",0.9, IF(F87="Other Brands",0.9, IF(F87="Oricle Prio",0.3,""))),""))) -> 159.66 | G88: =IF(G78<G79,G79,G78) * IF(G86="AM", IF(G87="Oricle",4, IF(G87="Other Brands",3, IF(G87="Oricle Prio",0.6,""))), IF(G86="MID", IF(G87="Oricle",2.5, IF(G87="Other Brands",3, IF(G87="Oricle Prio",0.6,""))), IF(G86="GY", IF(G87="Oricle",0.9, IF(G87="Other Brands",0.9, IF(G87="Oricle Prio",0.3,""))),""))) -> 136.025 | H88: 30
A89: Total Call # | B89: 78 | C89: 138 | D89: 151 | E89: 119 | F89: 163 | G89: 140 | H89: 30
A90: Call Pick Up # | B90: 76 | C90: 136 | D90: 147 | E90: 118 | F90: 161 | G90: 139 | H90: 30
A91: Pick Up % | B91: =IF(B89>0,B90/B89,0) -> 0.97435897 | C91: =IF(C89>0,C90/C89,0) -> 0.98550725 | D91: =IF(D89>0,D90/D89,0) -> 0.97350993 | E91: =IF(E89>0,E90/E89,0) -> 0.99159664 | F91: =IF(F89>0,F90/F89,0) -> 0.98773006 | G91: =IF(G89>0,G90/G89,0) -> 0.99285714 | H91: =IF(H89>0,H90/H89,0) -> 1
A92: Target Completion% | B92: =IF(B88>0,B90/B88,0) -> 0.80851064 | C92: =IF(C88>0,C90/C88,0) -> 0.62373876 | D92: =IF(D88>0,D90/D88,0) -> 1.0153336 | E92: =IF(E88>0,E90/E88,0) -> 0.85358796 | F92: =IF(F88>0,F90/F88,0) -> 1.0083928 | G92: =IF(G88>0,G90/G88,0) -> 1.021871 | H92: =IF(H88>0,H90/H88,0) -> 1
A93: Productivity % | B93: =average(B91:B92) -> 0.89143481 | C93: =average(C91:C92) -> 0.804623 | D93: =average(D91:D92) -> 0.99442177 | E93: =average(E91:E92) -> 0.9225923 | F93: =average(F91:F92) -> 0.99806145 | G93: =average(G91:G92) -> 1.0073641 | H93: =average(H91:H92) -> 1
A94: WORK ETHIC (10 pts)
A95: Work Ethic Score | B95: 7.55 | C95: 9.15 | D95: 9.38 | E95: 10 | F95: 9.91 | G95: 9.33 | H95: 10
A96: Work Ethic Max | B96: 10 | C96: 10 | D96: 10 | E96: 10 | F96: 10 | G96: 10 | H96: 10
A97: Work Ethic % | B97: =IF(B95=0,0,B95/B96) -> 0.755 | C97: =IF(C95=0,0,C95/C96) -> 0.915 | D97: =IF(D95=0,0,D95/D96) -> 0.938 | E97: =IF(E95=0,0,E95/E96) -> 1 | F97: =IF(F95=0,0,F95/F96) -> 0.991 | G97: =IF(G95=0,0,G95/G96) -> 0.933 | H97: =IF(H95=0,0,H95/H96) -> 1
A98: INFRACTIONS (-10 pts)
A99: Number of Infractions | B99: 0 | C99: 0 | D99: 0 | E99: 0 | F99: 0 | G99: 0 | H99: 0
A100: FINAL SCORE
...

Sheet Dan
A1: Week (July 6, - July 12,2026)
A2: Ticket Link | B2: Date | C2: Day | D2: SCORE | E2: Notes and Tagging(internal Note and Sticky Note) 5% | F2: COURTESY & EMPATHY 15% | G2: TONE OF VOICE & ELOQUENCE 20% | H2: CALL CONTROL 15% | I2: VERIFICATION 5% | J2: PROBING 5% | K2: MASTERY OF INFORMATION 15% | L2: RESOLUTION 20% | M2: Average | N2: NOTES
A3: https://4ammedia.zendesk.com/agent/tickets/211886 | B3: 46209 | C3: =IF(B3="", "", TEXT(B3, "ddd")) -> Mon | D3: =IF(E3="Yes",0.05,0) +IF(F3="Yes",0.1,0) +IF(G3="Yes",0.15,0) +IF(H3="Yes",0.15,0) +IF(I3="Yes",0.05,0) +IF(J3="Yes",0.05,0) +IF(K3="Yes",0.15,0) +IF(L3="Yes",0.3,0) -> 1 | E3: Yes | F3: Yes | G3: Yes | H3: Yes | I3: Yes | J3: Yes | K3: Yes | L3: Yes
A4: https://4ammedia.zendesk.com/agent/tickets/212102 | B4: 46209 | C4: =IF(B4="", "", TEXT(B4, "ddd")) -> Mon | D4: =IF(E4="Yes",0.05,0) +IF(F4="Yes",0.1,0) +IF(G4="Yes",0.15,0) +IF(H4="Yes",0.15,0) +IF(I4="Yes",0.05,0) +IF(J4="Yes",0.05,0) +IF(K4="Yes",0.15,0) +IF(L4="Yes",0.3,0) -> 1 | E4: Yes | F4: Yes | G4: Yes | H4: Yes | I4: Yes | J4: Yes | K4: Yes | L4: Yes
A5: https://4ammedia.zendesk.com/agent/tickets/212359 | B5: 46209 | C5: =IF(B5="", "", TEXT(B5, "ddd")) -> Mon | D5: =IF(E5="Yes",0.05,0) +IF(F5="Yes",0.1,0) +IF(G5="Yes",0.15,0) +IF(H5="Yes",0.15,0) +IF(I5="Yes",0.05,0) +IF(J5="Yes",0.05,0) +IF(K5="Yes",0.15,0) +IF(L5="Yes",0.3,0) -> 1 | E5: Yes | F5: Yes | G5: Yes | H5: Yes | I5: Yes | J5: Yes | K5: Yes | L5: Yes
A6: https://4ammedia.zendesk.com/agent/tickets/213864 | B6: 46210 | C6: =IF(B6="", "", TEXT(B6, "ddd")) -> Tue | D6: =IF(E6="Yes",0.05,0) +IF(F6="Yes",0.1,0) +IF(G6="Yes",0.15,0) +IF(H6="Yes",0.15,0) +IF(I6="Yes",0.05,0) +IF(J6="Yes",0.05,0) +IF(K6="Yes",0.15,0) +IF(L6="Yes",0.3,0) -> 1 | E6: Yes | F6: Yes | G6: Yes | H6: Yes | I6: Yes | J6: Yes | K6: Yes | L6: Yes
A7: https://4ammedia.zendesk.com/agent/tickets/213999 | B7: 46210 | C7: =IF(B7="", "", TEXT(B7, "ddd")) -> Tue | D7: =IF(E7="Yes",0.05,0) +IF(F7="Yes",0.1,0) +IF(G7="Yes",0.15,0) +IF(H7="Yes",0.15,0) +IF(I7="Yes",0.05,0) +IF(J7="Yes",0.05,0) +IF(K7="Yes",0.15,0) +IF(L7="Yes",0.3,0) -> 1 | E7: Yes | F7: Yes | G7: Yes | H7: Yes | I7: Yes | J7: Yes | K7: Yes | L7: Yes
A8: https://4ammedia.zendesk.com/agent/tickets/214389 | B8: 46210 | C8: =IF(B8="", "", TEXT(B8, "ddd")) -> Tue | D8: =IF(E8="Yes",0.05,0) +IF(F8="Yes",0.1,0) +IF(G8="Yes",0.15,0) +IF(H8="Yes",0.15,0) +IF(I8="Yes",0.05,0) +IF(J8="Yes",0.05,0) +IF(K8="Yes",0.15,0) +IF(L8="Yes",0.3,0) -> 1 | E8: Yes | F8: Yes | G8: Yes | H8: Yes | I8: Yes | J8: Yes | K8: Yes | L8: Yes
A9: https://4ammedia.zendesk.com/agent/tickets/215731 | B9: 46211 | C9: =IF(B9="", "", TEXT(B9, "ddd")) -> Wed | D9: =IF(E9="Yes",0.05,0) +IF(F9="Yes",0.1,0) +IF(G9="Yes",0.15,0) +IF(H9="Yes",0.15,0) +IF(I9="Yes",0.05,0) +IF(J9="Yes",0.05,0) +IF(K9="Yes",0.15,0) +IF(L9="Yes",0.3,0) -> 1 | E9: Yes | F9: Yes | G9: Yes | H9: Yes | I9: Yes | J9: Yes | K9: Yes | L9: Yes
A10: https://4ammedia.zendesk.com/agent/tickets/215937 | B10: 46211 | C10: =IF(B10="", "", TEXT(B10, "ddd")) -> Wed | D10: =IF(E10="Yes",0.05,0) +IF(F10="Yes",0.1,0) +IF(G10="Yes",0.15,0) +IF(H10="Yes",0.15,0) +IF(I10="Yes",0.05,0) +IF(J10="Yes",0.05,0) +IF(K10="Yes",0.15,0) +IF(L10="Yes",0.3,0) -> 1 | E10: Yes | F10: Yes | G10: Yes | H10: Yes | I10: Yes | J10: Yes | K10: Yes | L10: Yes
A11: https://4ammedia.zendesk.com/agent/tickets/215976 | B11: 46211 | C11: =IF(B11="", "", TEXT(B11, "ddd")) -> Wed | D11: =IF(E11="Yes",0.05,0) +IF(F11="Yes",0.1,0) +IF(G11="Yes",0.15,0) +IF(H11="Yes",0.15,0) +IF(I11="Yes",0.05,0) +IF(J11="Yes",0.05,0) +IF(K11="Yes",0.15,0) +IF(L11="Yes",0.3,0) -> 1 | E11: Yes | F11: Yes | G11: Yes | H11: Yes | I11: Yes | J11: Yes | K11: Yes | L11: Yes
A12: https://4ammedia.zendesk.com/agent/tickets/217776 | B12: 46212 | C12: =IF(B12="", "", TEXT(B12, "ddd")) -> Thu | D12: =IF(E12="Yes",0.05,0) +IF(F12="Yes",0.1,0) +IF(G12="Yes",0.15,0) +IF(H12="Yes",0.15,0) +IF(I12="Yes",0.05,0) +IF(J12="Yes",0.05,0) +IF(K12="Yes",0.15,0) +IF(L12="Yes",0.3,0) -> 1 | E12: Yes | F12: Yes | G12: Yes | H12: Yes | I12: Yes | J12: Yes | K12: Yes | L12: Yes
A13: https://4ammedia.zendesk.com/agent/tickets/217908 | B13: 46212 | C13: =IF(B13="", "", TEXT(B13, "ddd")) -> Thu | D13: =IF(E13="Yes",0.05,0) +IF(F13="Yes",0.1,0) +IF(G13="Yes",0.15,0) +IF(H13="Yes",0.15,0) +IF(I13="Yes",0.05,0) +IF(J13="Yes",0.05,0) +IF(K13="Yes",0.15,0) +IF(L13="Yes",0.3,0) -> 1 | E13: Yes | F13: Yes | G13: Yes | H13: Yes | I13: Yes | J13: Yes | K13: Yes | L13: Yes
A14: https://4ammedia.zendesk.com/agent/tickets/218017 | B14: 46212 | C14: =IF(B14="", "", TEXT(B14, "ddd")) -> Thu | D14: =IF(E14="Yes",0.05,0) +IF(F14="Yes",0.1,0) +IF(G14="Yes",0.15,0) +IF(H14="Yes",0.15,0) +IF(I14="Yes",0.05,0) +IF(J14="Yes",0.05,0) +IF(K14="Yes",0.15,0) +IF(L14="Yes",0.3,0) -> 1 | E14: Yes | F14: Yes | G14: Yes | H14: Yes | I14: Yes | J14: Yes | K14: Yes | L14: Yes
... A17: https://4ammedia.zendesk.com/agent/tickets/219749 | B17: 46213 | C17: =IF(B17="", "", TEXT(B17, "ddd")) -> Fri | D17: =IF(E17="Yes",0.05,0) +IF(F17="Yes",0.1,0) +IF(G17="Yes",0.15,0) +IF(H17="Yes",0.15,0) +IF(I17="Yes",0.05,0) +IF(J17="Yes",0.05,0) +IF(K17="Yes",0.15,0) +IF(L17="Yes",0.3,0) -> 1 | E17: Yes | F17: Yes | G17: Yes | H17: Yes | I17: Yes | J17: Yes | K17: Yes | L17: Yes
C18: Final QA Score | D18: =AVERAGE(D3:D17) -> 1 | L18: Final QA Score | M18: =SUM(M3:M17)/75*0.1 -> 0
A19: Week (July 13, - July 19,2026)
A20: Ticket Link | B20: Date | C20: Day | D20: SCORE | E20: Notes and Tagging(internal Note and Sticky Note) 5% | F20: COURTESY & EMPATHY 15% | G20: TONE OF VOICE & ELOQUENCE 20% | H20: CALL CONTROL 15% | I20: VERIFICATION 5% | J20: PROBING 5% | K20: MASTERY OF INFORMATION 15% | L20: RESOLUTION 20% | M20: Average | N20: NOTES
A21: https://4ammedia.zendesk.com/agent/tickets/224286 | B21: 46216 | C21: =IF(B21="", "", TEXT(B21, "ddd")) -> Mon | D21: =IF(E21="Yes",0.05,0) +IF(F21="Yes",0.1,0) +IF(G21="Yes",0.15,0) +IF(H21="Yes",0.15,0) +IF(I21="Yes",0.05,0) +IF(J21="Yes",0.05,0) +IF(K21="Yes",0.15,0) +IF(L21="Yes",0.3,0) -> 1 | E21: Yes | F21: Yes | G21: Yes | H21: Yes | I21: Yes | J21: Yes | K21: Yes | L21: Yes
A22: https://4ammedia.zendesk.com/agent/tickets/224667 | B22: 46216 | C22: =IF(B22="", "", TEXT(B22, "ddd")) -> Mon | D22: =IF(E22="Yes",0.05,0) +IF(F22="Yes",0.1,0) +IF(G22="Yes",0.15,0) +IF(H22="Yes",0.15,0) +IF(I22="Yes",0.05,0) +IF(J22="Yes",0.05,0) +IF(K22="Yes",0.15,0) +IF(L22="Yes",0.3,0) -> 1 | E22: Yes | F22: Yes | G22: Yes | H22: Yes | I22: Yes | J22: Yes | K22: Yes | L22: Yes
A23: https://4ammedia.zendesk.com/agent/tickets/224692 | B23: 46216 | C23: =IF(B23="", "", TEXT(B23, "ddd")) -> Mon | D23: =IF(E23="Yes",0.05,0) +IF(F23="Yes",0.1,0) +IF(G23="Yes",0.15,0) +IF(H23="Yes",0.15,0) +IF(I23="Yes",0.05,0) +IF(J23="Yes",0.05,0) +IF(K23="Yes",0.15,0) +IF(L23="Yes",0.3,0) -> 1 | E23: Yes | F23: Yes | G23: Yes | H23: Yes | I23: Yes | J23: Yes | K23: Yes | L23: Yes
A24: https://4ammedia.zendesk.com/agent/tickets/227009 | B24: 46217 | C24: =IF(B24="", "", TEXT(B24, "ddd")) -> Tue | D24: =IF(E24="Yes",0.05,0) +IF(F24="Yes",0.1,0) +IF(G24="Yes",0.15,0) +IF(H24="Yes",0.15,0) +IF(I24="Yes",0.05,0) +IF(J24="Yes",0.05,0) +IF(K24="Yes",0.15,0) +IF(L24="Yes",0.3,0) -> 1 | E24: Yes | F24: Yes | G24: Yes | H24: Yes | I24: Yes | J24: Yes | K24: Yes | L24: Yes
A25: https://4ammedia.zendesk.com/agent/tickets/227026 | B25: 46217 | C25: =IF(B25="", "", TEXT(B25, "ddd")) -> Tue | D25: =IF(E25="Yes",0.05,0) +IF(F25="Yes",0.1,0) +IF(G25="Yes",0.15,0) +IF(H25="Yes",0.15,0) +IF(I25="Yes",0.05,0) +IF(J25="Yes",0.05,0) +IF(K25="Yes",0.15,0) +IF(L25="Yes",0.3,0) -> 1 | E25: Yes | F25: Yes | G25: Yes | H25: Yes | I25: Yes | J25: Yes | K25: Yes | L25: Yes
A26: https://4ammedia.zendesk.com/agent/tickets/227041 | B26: 46217 | C26: =IF(B26="", "", TEXT(B26, "ddd")) -> Tue | D26: =IF(E26="Yes",0.05,0) +IF(F26="Yes",0.1,0) +IF(G26="Yes",0.15,0) +IF(H26="Yes",0.15,0) +IF(I26="Yes",0.05,0) +IF(J26="Yes",0.05,0) +IF(K26="Yes",0.15,0) +IF(L26="Yes",0.3,0) -> 1 | E26: Yes | F26: Yes | G26: Yes | H26: Yes | I26: Yes | J26: Yes | K26: Yes | L26: Yes
A27: https://4ammedia.zendesk.com/agent/tickets/228642 | B27: 46218 | C27: =IF(B27="", "", TEXT(B27, "ddd")) -> Wed | D27: =IF(E27="Yes",0.05,0) +IF(F27="Yes",0.1,0) +IF(G27="Yes",0.15,0) +IF(H27="Yes",0.15,0) +IF(I27="Yes",0.05,0) +IF(J27="Yes",0.05,0) +IF(K27="Yes",0.15,0) +IF(L27="Yes",0.3,0) -> 1 | E27: Yes | F27: Yes | G27: Yes | H27: Yes | I27: Yes | J27: Yes | K27: Yes | L27: Yes
A28: https://4ammedia.zendesk.com/agent/tickets/228813 | B28: 46218 | C28: =IF(B28="", "", TEXT(B28, "ddd")) -> Wed | D28: =IF(E28="Yes",0.05,0) +IF(F28="Yes",0.1,0) +IF(G28="Yes",0.15,0) +IF(H28="Yes",0.15,0) +IF(I28="Yes",0.05,0) +IF(J28="Yes",0.05,0) +IF(K28="Yes",0.15,0) +IF(L28="Yes",0.3,0) -> 1 | E28: Yes | F28: Yes | G28: Yes | H28: Yes | I28: Yes | J28: Yes | K28: Yes | L28: Yes
A29: https://4ammedia.zendesk.com/agent/tickets/228944 | B29: 46218 | C29: =IF(B29="", "", TEXT(B29, "ddd")) -> Wed | D29: =IF(E29="Yes",0.05,0) +IF(F29="Yes",0.1,0) +IF(G29="Yes",0.15,0) +IF(H29="Yes",0.15,0) +IF(I29="Yes",0.05,0) +IF(J29="Yes",0.05,0) +IF(K29="Yes",0.15,0) +IF(L29="Yes",0.3,0) -> 1 | E29: Yes | F29: Yes | G29: Yes | H29: Yes | I29: Yes | J29: Yes | K29: Yes | L29: Yes
A30: https://4ammedia.zendesk.com/agent/tickets/230672 | B30: 46219 | C30: =IF(B30="", "", TEXT(B30, "ddd")) -> Thu | D30: =IF(E30="Yes",0.05,0) +IF(F30="Yes",0.1,0) +IF(G30="Yes",0.15,0) +IF(H30="Yes",0.15,0) +IF(I30="Yes",0.05,0) +IF(J30="Yes",0.05,0) +IF(K30="Yes",0.15,0) +IF(L30="Yes",0.3,0) -> 1 | E30: Yes | F30: Yes | G30: Yes | H30: Yes | I30: Yes | J30: Yes | K30: Yes | L30: Yes
A31: https://4ammedia.zendesk.com/agent/tickets/230808 | B31: 46219 | C31: =IF(B31="", "", TEXT(B31, "ddd")) -> Thu | D31: =IF(E31="Yes",0.05,0) +IF(F31="Yes",0.1,0) +IF(G31="Yes",0.15,0) +IF(H31="Yes",0.15,0) +IF(I31="Yes",0.05,0) +IF(J31="Yes",0.05,0) +IF(K31="Yes",0.15,0) +IF(L31="Yes",0.3,0) -> 1 | E31: Yes | F31: Yes | G31: Yes | H31: Yes | I31: Yes | J31: Yes | K31: Yes | L31: Yes
A32: https://4ammedia.zendesk.com/agent/tickets/230885 | B32: 46219 | C32: =IF(B32="", "", TEXT(B32, "ddd")) -> Thu | D32: =IF(E32="Yes",0.05,0) +IF(F32="Yes",0.1,0) +IF(G32="Yes",0.15,0) +IF(H32="Yes",0.15,0) +IF(I32="Yes",0.05,0) +IF(J32="Yes",0.05,0) +IF(K32="Yes",0.15,0) +IF(L32="Yes",0.3,0) -> 1 | E32: Yes | F32: Yes | G32: Yes | H32: Yes | I32: Yes | J32: Yes | K32: Yes | L32: Yes
... A35: https://4ammedia.zendesk.com/agent/tickets/232550 | B35: 46220 | C35: =IF(B35="", "", TEXT(B35, "ddd")) -> Fri | D35: =IF(E35="Yes",0.05,0) +IF(F35="Yes",0.1,0) +IF(G35="Yes",0.15,0) +IF(H35="Yes",0.15,0) +IF(I35="Yes",0.05,0) +IF(J35="Yes",0.05,0) +IF(K35="Yes",0.15,0) +IF(L35="Yes",0.3,0) -> 1 | E35: Yes | F35: Yes | G35: Yes | H35: Yes | I35: Yes | J35: Yes | K35: Yes | L35: Yes
C36: Final QA Score | D36: =AVERAGE(D21:D35) -> 1 | L36: Final QA Score | M36: =SUM(M21:M35)/75*0.1 -> 0
A37: Week (July 20, - July 26,2026)
A38: Ticket Link | B38: Date | C38: Day | D38: SCORE | E38: Notes and Tagging(internal Note and Sticky Note) 5% | F38: COURTESY & EMPATHY 15% | G38: TONE OF VOICE & ELOQUENCE 20% | H38: CALL CONTROL 15% | I38: VERIFICATION 5% | J38: PROBING 5% | K38: MASTERY OF INFORMATION 15% | L38: RESOLUTION 20% | M38: Average | N38: NOTES
A39: https://4ammedia.zendesk.com/agent/tickets/237008 | B39: 46223 | C39: =IF(B39="", "", TEXT(B39, "ddd")) -> Mon | D39: =IF(E39="Yes",0.05,0) +IF(F39="Yes",0.1,0) +IF(G39="Yes",0.15,0) +IF(H39="Yes",0.15,0) +IF(I39="Yes",0.05,0) +IF(J39="Yes",0.05,0) +IF(K39="Yes",0.15,0) +IF(L39="Yes",0.3,0) -> 1 | E39: Yes | F39: Yes | G39: Yes | H39: Yes | I39: Yes | J39: Yes | K39: Yes | L39: Yes
A40: https://4ammedia.zendesk.com/agent/tickets/237202 | B40: 46223 | C40: =IF(B40="", "", TEXT(B40, "ddd")) -> Mon | D40: =IF(E40="Yes",0.05,0) +IF(F40="Yes",0.1,0) +IF(G40="Yes",0.15,0) +IF(H40="Yes",0.15,0) +IF(I40="Yes",0.05,0) +IF(J40="Yes",0.05,0) +IF(K40="Yes",0.15,0) +IF(L40="Yes",0.3,0) -> 1 | E40: Yes | F40: Yes | G40: Yes | H40: Yes | I40: Yes | J40: Yes | K40: Yes | L40: Yes
A41: https://4ammedia.zendesk.com/agent/tickets/237280 | B41: 46223 | C41: =IF(B41="", "", TEXT(B41, "ddd")) -> Mon | D41: =IF(E41="Yes",0.05,0) +IF(F41="Yes",0.1,0) +IF(G41="Yes",0.15,0) +IF(H41="Yes",0.15,0) +IF(I41="Yes",0.05,0) +IF(J41="Yes",0.05,0) +IF(K41="Yes",0.15,0) +IF(L41="Yes",0.3,0) -> 1 | E41: Yes | F41: Yes | G41: Yes | H41: Yes | I41: Yes | J41: Yes | K41: Yes | L41: Yes
A42: https://4ammedia.zendesk.com/agent/tickets/239606 | B42: 46224 | C42: =IF(B42="", "", TEXT(B42, "ddd")) -> Tue | D42: =IF(E42="Yes",0.05,0) +IF(F42="Yes",0.1,0) +IF(G42="Yes",0.15,0) +IF(H42="Yes",0.15,0) +IF(I42="Yes",0.05,0) +IF(J42="Yes",0.05,0) +IF(K42="Yes",0.15,0) +IF(L42="Yes",0.3,0) -> 1 | E42: Yes | F42: Yes | G42: Yes | H42: Yes | I42: Yes | J42: Yes | K42: Yes | L42: Yes
A43: https://4ammedia.zendesk.com/agent/tickets/239679 | B43: 46224 | C43: =IF(B43="", "", TEXT(B43, "ddd")) -> Tue | D43: =IF(E43="Yes",0.05,0) +IF(F43="Yes",0.1,0) +IF(G43="Yes",0.15,0) +IF(H43="Yes",0.15,0) +IF(I43="Yes",0.05,0) +IF(J43="Yes",0.05,0) +IF(K43="Yes",0.15,0) +IF(L43="Yes",0.3,0) -> 1 | E43: Yes | F43: Yes | G43: Yes | H43: Yes | I43: Yes | J43: Yes | K43: Yes | L43: Yes
A44: https://4ammedia.zendesk.com/agent/tickets/239705 | B44: 46224 | C44: =IF(B44="", "", TEXT(B44, "ddd")) -> Tue | D44: =IF(E44="Yes",0.05,0) +IF(F44="Yes",0.1,0) +IF(G44="Yes",0.15,0) +IF(H44="Yes",0.15,0) +IF(I44="Yes",0.05,0) +IF(J44="Yes",0.05,0) +IF(K44="Yes",0.15,0) +IF(L44="Yes",0.3,0) -> 1 | E44: Yes | F44: Yes | G44: Yes | H44: Yes | I44: Yes | J44: Yes | K44: Yes | L44: Yes
A45: https://4ammedia.zendesk.com/agent/tickets/241183 | B45: 46225 | C45: =IF(B45="", "", TEXT(B45, "ddd")) -> Wed | D45: =IF(E45="Yes",0.05,0) +IF(F45="Yes",0.1,0) +IF(G45="Yes",0.15,0) +IF(H45="Yes",0.15,0) +IF(I45="Yes",0.05,0) +IF(J45="Yes",0.05,0) +IF(K45="Yes",0.15,0) +IF(L45="Yes",0.3,0) -> 1 | E45: Yes | F45: Yes | G45: Yes | H45: Yes | I45: Yes | J45: Yes | K45: Yes | L45: Yes
A46: https://4ammedia.zendesk.com/agent/tickets/241251 | B46: 46225 | C46: =IF(B46="", "", TEXT(B46, "ddd")) -> Wed | D46: =IF(E46="Yes",0.05,0) +IF(F46="Yes",0.1,0) +IF(G46="Yes",0.15,0) +IF(H46="Yes",0.15,0) +IF(I46="Yes",0.05,0) +IF(J46="Yes",0.05,0) +IF(K46="Yes",0.15,0) +IF(L46="Yes",0.3,0) -> 1 | E46: Yes | F46: Yes | G46: Yes | H46: Yes | I46: Yes | J46: Yes | K46: Yes | L46: Yes
A47: https://4ammedia.zendesk.com/agent/tickets/241382 | B47: 46225 | C47: =IF(B47="", "", TEXT(B47, "ddd")) -> Wed | D47: =IF(E47="Yes",0.05,0) +IF(F47="Yes",0.1,0) +IF(G47="Yes",0.15,0) +IF(H47="Yes",0.15,0) +IF(I47="Yes",0.05,0) +IF(J47="Yes",0.05,0) +IF(K47="Yes",0.15,0) +IF(L47="Yes",0.3,0) -> 1 | E47: Yes | F47: Yes | G47: Yes | H47: Yes | I47: Yes | J47: Yes | K47: Yes | L47: Yes
A48: https://4ammedia.zendesk.com/agent/tickets/243111 | B48: 46226 | C48: =IF(B48="", "", TEXT(B48, "ddd")) -> Thu | D48: =IF(E48="Yes",0.05,0) +IF(F48="Yes",0.1,0) +IF(G48="Yes",0.15,0) +IF(H48="Yes",0.15,0) +IF(I48="Yes",0.05,0) +IF(J48="Yes",0.05,0) +IF(K48="Yes",0.15,0) +IF(L48="Yes",0.3,0) -> 1 | E48: Yes | F48: Yes | G48: Yes | H48: Yes | I48: Yes | J48: Yes | K48: Yes | L48: Yes
A49: https://4ammedia.zendesk.com/agent/tickets/243182 | B49: 46226 | C49: =IF(B49="", "", TEXT(B49, "ddd")) -> Thu | D49: =IF(E49="Yes",0.05,0) +IF(F49="Yes",0.1,0) +IF(G49="Yes",0.15,0) +IF(H49="Yes",0.15,0) +IF(I49="Yes",0.05,0) +IF(J49="Yes",0.05,0) +IF(K49="Yes",0.15,0) +IF(L49="Yes",0.3,0) -> 1 | E49: Yes | F49: Yes | G49: Yes | H49: Yes | I49: Yes | J49: Yes | K49: Yes | L49: Yes
A50: https://4ammedia.zendesk.com/agent/tickets/243211 | B50: 46226 | C50: =IF(B50="", "", TEXT(B50, "ddd")) -> Thu | D50: =IF(E50="Yes",0.05,0) +IF(F50="Yes",0.1,0) +IF(G50="Yes",0.15,0) +IF(H50="Yes",0.15,0) +IF(I50="Yes",0.05,0) +IF(J50="Yes",0.05,0) +IF(K50="Yes",0.15,0) +IF(L50="Yes",0.3,0) -> 1 | E50: Yes | F50: Yes | G50: Yes | H50: Yes | I50: Yes | J50: Yes | K50: Yes | L50: Yes
... A53: https://4ammedia.zendesk.com/agent/tickets/245709 | B53: 46227 | C53: =IF(B53="", "", TEXT(B53, "ddd")) -> Fri | D53: =IF(E53="Yes",0.05,0) +IF(F53="Yes",0.1,0) +IF(G53="Yes",0.15,0) +IF(H53="Yes",0.15,0) +IF(I53="Yes",0.05,0) +IF(J53="Yes",0.05,0) +IF(K53="Yes",0.15,0) +IF(L53="Yes",0.3,0) -> 1 | E53: Yes | F53: Yes | G53: Yes | H53: Yes | I53: Yes | J53: Yes | K53: Yes | L53: Yes
C54: Final QA Score | D54: =AVERAGE(D39:D53) -> 1 | L54: Final QA Score | M54: =SUM(M39:M53)/75*0.1 -> 0
A55: Week (July 27, - Aug 2,2026)
A56: Ticket Link | B56: Date | C56: Day | D56: SCORE | E56: Notes and Tagging(internal Note and Sticky Note) 5% | F56: COURTESY & EMPATHY 15% | G56: TONE OF VOICE & ELOQUENCE 20% | H56: CALL CONTROL 15% | I56: VERIFICATION 5% | J56: PROBING 5% | K56: MASTERY OF INFORMATION 15% | L56: RESOLUTION 20% | M56: Average | N56: NOTES
A57: https://4ammedia.zendesk.com/agent/tickets/250140 | B57: 46230 | C57: =IF(B57="", "", TEXT(B57, "ddd")) -> Mon | D57: =IF(E57="Yes",0.05,0) +IF(F57="Yes",0.1,0) +IF(G57="Yes",0.15,0) +IF(H57="Yes",0.15,0) +IF(I57="Yes",0.05,0) +IF(J57="Yes",0.05,0) +IF(K57="Yes",0.15,0) +IF(L57="Yes",0.3,0) -> 1 | E57: Yes | F57: Yes | G57: Yes | H57: Yes | I57: Yes | J57: Yes | K57: Yes | L57: Yes
A58: https://4ammedia.zendesk.com/agent/tickets/250346 | B58: 46230 | C58: =IF(B58="", "", TEXT(B58, "ddd")) -> Mon | D58: =IF(E58="Yes",0.05,0) +IF(F58="Yes",0.1,0) +IF(G58="Yes",0.15,0) +IF(H58="Yes",0.15,0) +IF(I58="Yes",0.05,0) +IF(J58="Yes",0.05,0) +IF(K58="Yes",0.15,0) +IF(L58="Yes",0.3,0) -> 1 | E58: Yes | F58: Yes | G58: Yes | H58: Yes | I58: Yes | J58: Yes | K58: Yes | L58: Yes
A59: https://4ammedia.zendesk.com/agent/tickets/250375 | B59: 46230 | C59: =IF(B59="", "", TEXT(B59, "ddd")) -> Mon | D59: =IF(E59="Yes",0.05,0) +IF(F59="Yes",0.1,0) +IF(G59="Yes",0.15,0) +IF(H59="Yes",0.15,0) +IF(I59="Yes",0.05,0) +IF(J59="Yes",0.05,0) +IF(K59="Yes",0.15,0) +IF(L59="Yes",0.3,0) -> 1 | E59: Yes | F59: Yes | G59: Yes | H59: Yes | I59: Yes | J59: Yes | K59: Yes | L59: Yes
A60: https://4ammedia.zendesk.com/agent/tickets/252375 | B60: 46231 | C60: =IF(B60="", "", TEXT(B60, "ddd")) -> Tue | D60: =IF(E60="Yes",0.05,0) +IF(F60="Yes",0.1,0) +IF(G60="Yes",0.15,0) +IF(H60="Yes",0.15,0) +IF(I60="Yes",0.05,0) +IF(J60="Yes",0.05,0) +IF(K60="Yes",0.15,0) +IF(L60="Yes",0.3,0) -> 1 | E60: Yes | F60: Yes | G60: Yes | H60: Yes | I60: Yes | J60: Yes | K60: Yes | L60: Yes
A61: https://4ammedia.zendesk.com/agent/tickets/252480 | B61: 46231 | C61: =IF(B61="", "", TEXT(B61, "ddd")) -> Tue | D61: =IF(E61="Yes",0.05,0) +IF(F61="Yes",0.1,0) +IF(G61="Yes",0.15,0) +IF(H61="Yes",0.15,0) +IF(I61="Yes",0.05,0) +IF(J61="Yes",0.05,0) +IF(K61="Yes",0.15,0) +IF(L61="Yes",0.3,0) -> 1 | E61: Yes | F61: Yes | G61: Yes | H61: Yes | I61: Yes | J61: Yes | K61: Yes | L61: Yes
A62: https://4ammedia.zendesk.com/agent/tickets/252489 | B62: 46231 | C62: =IF(B62="", "", TEXT(B62, "ddd")) -> Tue | D62: =IF(E62="Yes",0.05,0) +IF(F62="Yes",0.1,0) +IF(G62="Yes",0.15,0) +IF(H62="Yes",0.15,0) +IF(I62="Yes",0.05,0) +IF(J62="Yes",0.05,0) +IF(K62="Yes",0.15,0) +IF(L62="Yes",0.3,0) -> 1 | E62: Yes | F62: Yes | G62: Yes | H62: Yes | I62: Yes | J62: Yes | K62: Yes | L62: Yes
A63: https://4ammedia.zendesk.com/agent/tickets/254509 | B63: 46232 | C63: =IF(B63="", "", TEXT(B63, "ddd")) -> Wed | D63: =IF(E63="Yes",0.05,0) +IF(F63="Yes",0.1,0) +IF(G63="Yes",0.15,0) +IF(H63="Yes",0.15,0) +IF(I63="Yes",0.05,0) +IF(J63="Yes",0.05,0) +IF(K63="Yes",0.15,0) +IF(L63="Yes",0.3,0) -> 1 | E63: Yes | F63: Yes | G63: Yes | H63: Yes | I63: Yes | J63: Yes | K63: Yes | L63: Yes
A64: https://4ammedia.zendesk.com/agent/tickets/254705 | B64: 46232 | C64: =IF(B64="", "", TEXT(B64, "ddd")) -> Wed | D64: =IF(E64="Yes",0.05,0) +IF(F64="Yes",0.1,0) +IF(G64="Yes",0.15,0) +IF(H64="Yes",0.15,0) +IF(I64="Yes",0.05,0) +IF(J64="Yes",0.05,0) +IF(K64="Yes",0.15,0) +IF(L64="Yes",0.3,0) -> 1 | E64: Yes | F64: Yes | G64: Yes | H64: Yes | I64: Yes | J64: Yes | K64: Yes | L64: Yes
A65: https://4ammedia.zendesk.com/agent/tickets/254848 | B65: 46232 | C65: =IF(B65="", "", TEXT(B65, "ddd")) -> Wed | D65: =IF(E65="Yes",0.05,0) +IF(F65="Yes",0.1,0) +IF(G65="Yes",0.15,0) +IF(H65="Yes",0.15,0) +IF(I65="Yes",0.05,0) +IF(J65="Yes",0.05,0) +IF(K65="Yes",0.15,0) +IF(L65="Yes",0.3,0) -> 1 | E65: Yes | F65: Yes | G65: Yes | H65: Yes | I65: Yes | J65: Yes | K65: Yes | L65: Yes
A66: https://4ammedia.zendesk.com/agent/tickets/256155 | B66: 46233 | C66: =IF(B66="", "", TEXT(B66, "ddd")) -> Thu | D66: =IF(E66="Yes",0.05,0) +IF(F66="Yes",0.1,0) +IF(G66="Yes",0.15,0) +IF(H66="Yes",0.15,0) +IF(I66="Yes",0.05,0) +IF(J66="Yes",0.05,0) +IF(K66="Yes",0.15,0) +IF(L66="Yes",0.3,0) -> 1 | E66: Yes | F66: Yes | G66: Yes | H66: Yes | I66: Yes | J66: Yes | K66: Yes | L66: Yes
A67: https://4ammedia.zendesk.com/agent/tickets/256208 | B67: 46233 | C67: =IF(B67="", "", TEXT(B67, "ddd")) -> Thu | D67: =IF(E67="Yes",0.05,0) +IF(F67="Yes",0.1,0) +IF(G67="Yes",0.15,0) +IF(H67="Yes",0.15,0) +IF(I67="Yes",0.05,0) +IF(J67="Yes",0.05,0) +IF(K67="Yes",0.15,0) +IF(L67="Yes",0.3,0) -> 1 | E67: Yes | F67: Yes | G67: Yes | H67: Yes | I67: Yes | J67: Yes | K67: Yes | L67: Yes
A68: https://4ammedia.zendesk.com/agent/tickets/256468 | B68: 46233 | C68: =IF(B68="", "", TEXT(B68, "ddd")) -> Thu | D68: =IF(E68="Yes",0.05,0) +IF(F68="Yes",0.1,0) +IF(G68="Yes",0.15,0) +IF(H68="Yes",0.15,0) +IF(I68="Yes",0.05,0) +IF(J68="Yes",0.05,0) +IF(K68="Yes",0.15,0) +IF(L68="Yes",0.3,0) -> 1 | E68: Yes | F68: Yes | G68: Yes | H68: Yes | I68: Yes | J68: Yes | K68: Yes | L68: Yes
... A71: https://4ammedia.zendesk.com/agent/tickets/258778 | B71: 46234 | C71: =IF(B71="", "", TEXT(B71, "ddd")) -> Fri | D71: =IF(E71="Yes",0.05,0) +IF(F71="Yes",0.1,0) +IF(G71="Yes",0.15,0) +IF(H71="Yes",0.15,0) +IF(I71="Yes",0.05,0) +IF(J71="Yes",0.05,0) +IF(K71="Yes",0.15,0) +IF(L71="Yes",0.3,0) -> 1 | E71: Yes | F71: Yes | G71: Yes | H71: Yes | I71: Yes | J71: Yes | K71: Yes | L71: Yes
C72: Final QA Score | D72: =AVERAGE(D57:D71) -> 1 | L72: Final QA Score | M72: =SUM(M57:M71)/75*0.1 -> 0
A73: Week (Aug 3, - Aug 9,2026)
A74: Ticket Link | B74: Date | C74: Day | D74: SCORE | E74: Notes and Tagging(internal Note and Sticky Note) 5% | F74: COURTESY & EMPATHY 15% | G74: TONE OF VOICE & ELOQUENCE 20% | H74: CALL CONTROL 15% | I74: VERIFICATION 5% | J74: PROBING 5% | K74: MASTERY OF INFORMATION 15% | L74: RESOLUTION 20% | M74: Average | N74: NOTES
A75: https://4ammedia.zendesk.com/agent/tickets/263704 | B75: 46237 | C75: =IF(B75="", "", TEXT(B75, "ddd")) -> Mon | D75: =IF(E75="Yes",0.05,0) +IF(F75="Yes",0.1,0) +IF(G75="Yes",0.15,0) +IF(H75="Yes",0.15,0) +IF(I75="Yes",0.05,0) +IF(J75="Yes",0.05,0) +IF(K75="Yes",0.15,0) +IF(L75="Yes",0.3,0) -> 1 | E75: Yes | F75: Yes | G75: Yes | H75: Yes | I75: Yes | J75: Yes | K75: Yes | L75: Yes
A76: https://4ammedia.zendesk.com/agent/tickets/263960 | B76: 46237 | C76: =IF(B76="", "", TEXT(B76, "ddd")) -> Mon | D76: =IF(E76="Yes",0.05,0) +IF(F76="Yes",0.1,0) +IF(G76="Yes",0.15,0) +IF(H76="Yes",0.15,0) +IF(I76="Yes",0.05,0) +IF(J76="Yes",0.05,0) +IF(K76="Yes",0.15,0) +IF(L76="Yes",0.3,0) -> 1 | E76: Yes | F76: Yes | G76: Yes | H76: Yes | I76: Yes | J76: Yes | K76: Yes | L76: Yes
A77: https://4ammedia.zendesk.com/agent/tickets/264061 | B77: 46237 | C77: =IF(B77="", "", TEXT(B77, "ddd")) -> Mon | D77: =IF(E77="Yes",0.05,0) +IF(F77="Yes",0.1,0) +IF(G77="Yes",0.15,0) +IF(H77="Yes",0.15,0) +IF(I77="Yes",0.05,0) +IF(J77="Yes",0.05,0) +IF(K77="Yes",0.15,0) +IF(L77="Yes",0.3,0) -> 1 | E77: Yes | F77: Yes | G77: Yes | H77: Yes | I77: Yes | J77: Yes | K77: Yes | L77: Yes
A78: https://4ammedia.zendesk.com/agent/tickets/266030 | B78: 46238 | C78: =IF(B78="", "", TEXT(B78, "ddd")) -> Tue | D78: =IF(E78="Yes",0.05,0) +IF(F78="Yes",0.1,0) +IF(G78="Yes",0.15,0) +IF(H78="Yes",0.15,0) +IF(I78="Yes",0.05,0) +IF(J78="Yes",0.05,0) +IF(K78="Yes",0.15,0) +IF(L78="Yes",0.3,0) -> 1 | E78: Yes | F78: Yes | G78: Yes | H78: Yes | I78: Yes | J78: Yes | K78: Yes | L78: Yes
A79: https://4ammedia.zendesk.com/agent/tickets/266363 | B79: 46238 | C79: =IF(B79="", "", TEXT(B79, "ddd")) -> Tue | D79: =IF(E79="Yes",0.05,0) +IF(F79="Yes",0.1,0) +IF(G79="Yes",0.15,0) +IF(H79="Yes",0.15,0) +IF(I79="Yes",0.05,0) +IF(J79="Yes",0.05,0) +IF(K79="Yes",0.15,0) +IF(L79="Yes",0.3,0) -> 1 | E79: Yes | F79: Yes | G79: Yes | H79: Yes | I79: Yes | J79: Yes | K79: Yes | L79: Yes
A80: https://4ammedia.zendesk.com/agent/tickets/266418 | B80: 46238 | C80: =IF(B80="", "", TEXT(B80, "ddd")) -> Tue | D80: =IF(E80="Yes",0.05,0) +IF(F80="Yes",0.1,0) +IF(G80="Yes",0.15,0) +IF(H80="Yes",0.15,0) +IF(I80="Yes",0.05,0) +IF(J80="Yes",0.05,0) +IF(K80="Yes",0.15,0) +IF(L80="Yes",0.3,0) -> 1 | E80: Yes | F80: Yes | G80: Yes | H80: Yes | I80: Yes | J80: Yes | K80: Yes | L80: Yes
A81: https://4ammedia.zendesk.com/agent/tickets/267920 | B81: 46239 | C81: =IF(B81="", "", TEXT(B81, "ddd")) -> Wed | D81: =IF(E81="Yes",0.05,0) +IF(F81="Yes",0.1,0) +IF(G81="Yes",0.15,0) +IF(H81="Yes",0.15,0) +IF(I81="Yes",0.05,0) +IF(J81="Yes",0.05,0) +IF(K81="Yes",0.15,0) +IF(L81="Yes",0.3,0) -> 1 | E81: Yes | F81: Yes | G81: Yes | H81: Yes | I81: Yes | J81: Yes | K81: Yes | L81: Yes
A82: https://4ammedia.zendesk.com/agent/tickets/268016 | B82: 46239 | C82: =IF(B82="", "", TEXT(B82, "ddd")) -> Wed | D82: =IF(E82="Yes",0.05,0) +IF(F82="Yes",0.1,0) +IF(G82="Yes",0.15,0) +IF(H82="Yes",0.15,0) +IF(I82="Yes",0.05,0) +IF(J82="Yes",0.05,0) +IF(K82="Yes",0.15,0) +IF(L82="Yes",0.3,0) -> 1 | E82: Yes | F82: Yes | G82: Yes | H82: Yes | I82: Yes | J82: Yes | K82: Yes | L82: Yes
A83: https://4ammedia.zendesk.com/agent/tickets/268066 | B83: 46239 | C83: =IF(B83="", "", TEXT(B83, "ddd")) -> Wed | D83: =IF(E83="Yes",0.05,0) +IF(F83="Yes",0.1,0) +IF(G83="Yes",0.15,0) +IF(H83="Yes",0.15,0) +IF(I83="Yes",0.05,0) +IF(J83="Yes",0.05,0) +IF(K83="Yes",0.15,0) +IF(L83="Yes",0.3,0) -> 1 | E83: Yes | F83: Yes | G83: Yes | H83: Yes | I83: Yes | J83: Yes | K83: Yes | L83: Yes
A84: https://4ammedia.zendesk.com/agent/tickets/270012 | B84: 46240 | C84: =IF(B84="", "", TEXT(B84, "ddd")) -> Thu | D84: =IF(E84="Yes",0.05,0) +IF(F84="Yes",0.1,0) +IF(G84="Yes",0.15,0) +IF(H84="Yes",0.15,0) +IF(I84="Yes",0.05,0) +IF(J84="Yes",0.05,0) +IF(K84="Yes",0.15,0) +IF(L84="Yes",0.3,0) -> 1 | E84: Yes | F84: Yes | G84: Yes | H84: Yes | I84: Yes | J84: Yes | K84: Yes | L84: Yes
A85: https://4ammedia.zendesk.com/agent/tickets/270169 | B85: 46240 | C85: =IF(B85="", "", TEXT(B85, "ddd")) -> Thu | D85: =IF(E85="Yes",0.05,0) +IF(F85="Yes",0.1,0) +IF(G85="Yes",0.15,0) +IF(H85="Yes",0.15,0) +IF(I85="Yes",0.05,0) +IF(J85="Yes",0.05,0) +IF(K85="Yes",0.15,0) +IF(L85="Yes",0.3,0) -> 1 | E85: Yes | F85: Yes | G85: Yes | H85: Yes | I85: Yes | J85: Yes | K85: Yes | L85: Yes
A86: https://4ammedia.zendesk.com/agent/tickets/270176 | B86: 46240 | C86: =IF(B86="", "", TEXT(B86, "ddd")) -> Thu | D86: =IF(E86="Yes",0.05,0) +IF(F86="Yes",0.1,0) +IF(G86="Yes",0.15,0) +IF(H86="Yes",0.15,0) +IF(I86="Yes",0.05,0) +IF(J86="Yes",0.05,0) +IF(K86="Yes",0.15,0) +IF(L86="Yes",0.3,0) -> 1 | E86: Yes | F86: Yes | G86: Yes | H86: Yes | I86: Yes | J86: Yes | K86: Yes | L86: Yes
... A89: https://4ammedia.zendesk.com/agent/tickets/271253 | B89: 46241 | C89: =IF(B89="", "", TEXT(B89, "ddd")) -> Fri | D89: =IF(E89="Yes",0.05,0) +IF(F89="Yes",0.1,0) +IF(G89="Yes",0.15,0) +IF(H89="Yes",0.15,0) +IF(I89="Yes",0.05,0) +IF(J89="Yes",0.05,0) +IF(K89="Yes",0.15,0) +IF(L89="Yes",0.3,0) -> 1 | E89: Yes | F89: Yes | G89: Yes | H89: Yes | I89: Yes | J89: Yes | K89: Yes | L89: Yes
C90: Final QA Score | D90: =AVERAGE(D75:D89) -> 1 | L90: Final QA Score | M90: =SUM(M75:M89)/75*0.1 -> 0
A91: Week (Aug 10, - Aug 16,2026)
A92: Ticket Link | B92: Date | C92: Day | D92: SCORE | E92: Notes and Tagging(internal Note and Sticky Note) 5% | F92: COURTESY & EMPATHY 15% | G92: TONE OF VOICE & ELOQUENCE 20% | H92: CALL CONTROL 15% | I92: VERIFICATION 5% | J92: PROBING 5% | K92: MASTERY OF INFORMATION 15% | L92: RESOLUTION 20% | M92: Average | N92: NOTES
A93: https://4ammedia.zendesk.com/agent/tickets/276138 | B93: 46244 | C93: =IF(B93="", "", TEXT(B93, "ddd")) -> Mon | D93: =IF(E93="Yes",0.05,0) +IF(F93="Yes",0.1,0) +IF(G93="Yes",0.15,0) +IF(H93="Yes",0.15,0) +IF(I93="Yes",0.05,0) +IF(J93="Yes",0.05,0) +IF(K93="Yes",0.15,0) +IF(L93="Yes",0.3,0) -> 1 | E93: Yes | F93: Yes | G93: Yes | H93: Yes | I93: Yes | J93: Yes | K93: Yes | L93: Yes
A94: https://4ammedia.zendesk.com/agent/tickets/276508 | B94: 46244 | C94: =IF(B94="", "", TEXT(B94, "ddd")) -> Mon | D94: =IF(E94="Yes",0.05,0) +IF(F94="Yes",0.1,0) +IF(G94="Yes",0.15,0) +IF(H94="Yes",0.15,0) +IF(I94="Yes",0.05,0) +IF(J94="Yes",0.05,0) +IF(K94="Yes",0.15,0) +IF(L94="Yes",0.3,0) -> 1 | E94: Yes | F94: Yes | G94: Yes | H94: Yes | I94: Yes | J94: Yes | K94: Yes | L94: Yes
A95: https://4ammedia.zendesk.com/agent/tickets/276705 | B95: 46244 | C95: =IF(B95="", "", TEXT(B95, "ddd")) -> Mon | D95: =IF(E95="Yes",0.05,0) +IF(F95="Yes",0.1,0) +IF(G95="Yes",0.15,0) +IF(H95="Yes",0.15,0) +IF(I95="Yes",0.05,0) +IF(J95="Yes",0.05,0) +IF(K95="Yes",0.15,0) +IF(L95="Yes",0.3,0) -> 1 | E95: Yes | F95: Yes | G95: Yes | H95: Yes | I95: Yes | J95: Yes | K95: Yes | L95: Yes
A96: https://4ammedia.zendesk.com/agent/tickets/278659 | B96: 46245 | C96: =IF(B96="", "", TEXT(B96, "ddd")) -> Tue | D96: =IF(E96="Yes",0.05,0) +IF(F96="Yes",0.1,0) +IF(G96="Yes",0.15,0) +IF(H96="Yes",0.15,0) +IF(I96="Yes",0.05,0) +IF(J96="Yes",0.05,0) +IF(K96="Yes",0.15,0) +IF(L96="Yes",0.3,0) -> 1 | E96: Yes | F96: Yes | G96: Yes | H96: Yes | I96: Yes | J96: Yes | K96: Yes | L96: Yes
A97: https://4ammedia.zendesk.com/agent/tickets/278758 | B97: 46245 | C97: =IF(B97="", "", TEXT(B97, "ddd")) -> Tue | D97: =IF(E97="Yes",0.05,0) +IF(F97="Yes",0.1,0) +IF(G97="Yes",0.15,0) +IF(H97="Yes",0.15,0) +IF(I97="Yes",0.05,0) +IF(J97="Yes",0.05,0) +IF(K97="Yes",0.15,0) +IF(L97="Yes",0.3,0) -> 1 | E97: Yes | F97: Yes | G97: Yes | H97: Yes | I97: Yes | J97: Yes | K97: Yes | L97: Yes
A98: https://4ammedia.zendesk.com/agent/tickets/278946 | B98: 46245 | C98: =IF(B98="", "", TEXT(B98, "ddd")) -> Tue | D98: =IF(E98="Yes",0.05,0) +IF(F98="Yes",0.1,0) +IF(G98="Yes",0.15,0) +IF(H98="Yes",0.15,0) +IF(I98="Yes",0.05,0) +IF(J98="Yes",0.05,0) +IF(K98="Yes",0.15,0) +IF(L98="Yes",0.3,0) -> 1 | E98: Yes | F98: Yes | G98: Yes | H98: Yes | I98: Yes | J98: Yes | K98: Yes | L98: Yes
A99: https://4ammedia.zendesk.com/agent/tickets/280541 | B99: 46246 | C99: =IF(B99="", "", TEXT(B99, "ddd")) -> Wed | D99: =IF(E99="Yes",0.05,0) +IF(F99="Yes",0.1,0) +IF(G99="Yes",0.15,0) +IF(H99="Yes",0.15,0) +IF(I99="Yes",0.05,0) +IF(J99="Yes",0.05,0) +IF(K99="Yes",0.15,0) +IF(L99="Yes",0.3,0) -> 1 | E99: Yes | F99: Yes | G99: Yes | H99: Yes | I99: Yes | J99: Yes | K99: Yes | L99: Yes
A100: https://4ammedia.zendesk.com/agent/tickets/280603 | B100: 46246 | C100: =IF(B100="", "", TEXT(B100, "ddd")) -> Wed | D100: =IF(E100="Yes",0.05,0) +IF(F100="Yes",0.1,0) +IF(G100="Yes",0.15,0) +IF(H100="Yes",0.15,0) +IF(I100="Yes",0.05,0) +IF(J100="Yes",0.05,0) +IF(K100="Yes",0.15,0) +IF(L100="Yes",0.3,0) -> 1 | E100: Yes | F100: Yes | G100: Yes | H100: Yes | I100: Yes | J100: Yes | K100: Yes | L100: Yes
A101: https://4ammedia.zendesk.com/agent/tickets/280670 | B101: 46246 | C101: =IF(B101="", "", TEXT(B101, "ddd")) -> Wed | D101: =IF(E101="Yes",0.05,0) +IF(F101="Yes",0.1,0) +IF(G101="Yes",0.15,0) +IF(H101="Yes",0.15,0) +IF(I101="Yes",0.05,0) +IF(J101="Yes",0.05,0) +IF(K101="Yes",0.15,0) +IF(L101="Yes",0.3,0) -> 1 | E101: Yes | F101: Yes | G101: Yes | H101: Yes | I101: Yes | J101: Yes | K101: Yes | L101: Yes
A102: https://4ammedia.zendesk.com/agent/tickets/282613 | B102: 46247 | C102: =IF(B102="", "", TEXT(B102, "ddd")) -> Thu | D102: =IF(E102="Yes",0.05,0) +IF(F102="Yes",0.1,0) +IF(G102="Yes",0.15,0) +IF(H102="Yes",0.15,0) +IF(I102="Yes",0.05,0) +IF(J102="Yes",0.05,0) +IF(K102="Yes",0.15,0) +IF(L102="Yes",0.3,0) -> 1 | E102: Yes | F102: Yes | G102: Yes | H102: Yes | I102: Yes | J102: Yes | K102: Yes | L102: Yes
A103: https://4ammedia.zendesk.com/agent/tickets/282712 | B103: 46247 | C103: =IF(B103="", "", TEXT(B103, "ddd")) -> Thu | D103: =IF(E103="Yes",0.05,0) +IF(F103="Yes",0.1,0) +IF(G103="Yes",0.15,0) +IF(H103="Yes",0.15,0) +IF(I103="Yes",0.05,0) +IF(J103="Yes",0.05,0) +IF(K103="Yes",0.15,0) +IF(L103="Yes",0.3,0) -> 1 | E103: Yes | F103: Yes | G103: Yes | H103: Yes | I103: Yes | J103: Yes | K103: Yes | L103: Yes
A104: https://4ammedia.zendesk.com/agent/tickets/282803 | B104: 46247 | C104: =IF(B104="", "", TEXT(B104, "ddd")) -> Thu | D104: =IF(E104="Yes",0.05,0) +IF(F104="Yes",0.1,0) +IF(G104="Yes",0.15,0) +IF(H104="Yes",0.15,0) +IF(I104="Yes",0.05,0) +IF(J104="Yes",0.05,0) +IF(K104="Yes",0.15,0) +IF(L104="Yes",0.3,0) -> 1 | E104: Yes | F104: Yes | G104: Yes | H104: Yes | I104: Yes | J104: Yes | K104: Yes | L104: Yes
... A107: https://4ammedia.zendesk.com/agent/tickets/284348 | B107: 46248 | C107: =IF(B107="", "", TEXT(B107, "ddd")) -> Fri | D107: =IF(E107="Yes",0.05,0) +IF(F107="Yes",0.1,0) +IF(G107="Yes",0.15,0) +IF(H107="Yes",0.15,0) +IF(I107="Yes",0.05,0) +IF(J107="Yes",0.05,0) +IF(K107="Yes",0.15,0) +IF(L107="Yes",0.3,0) -> 1 | E107: Yes | F107: Yes | G107: Yes | H107: Yes | I107: Yes | J107: Yes | K107: Yes | L107: Yes
C108: Final QA Score | D108: =AVERAGE(D93:D107) -> 1 | L108: Final QA Score | M108: =SUM(M93:M107)/75*0.1 -> 0
A109: Week (Aug 17, - Aug 23,2026)
A110: Ticket Link | B110: Date | C110: Day | D110: SCORE | E110: Notes and Tagging(internal Note and Sticky Note) 5% | F110: COURTESY & EMPATHY 15% | G110: TONE OF VOICE & ELOQUENCE 20% | H110: CALL CONTROL 15% | I110: VERIFICATION 5% | J110: PROBING 5% | K110: MASTERY OF INFORMATION 15% | L110: RESOLUTION 20% | M110: Average | N110: NOTES
A111: https://4ammedia.zendesk.com/agent/tickets/289277 | B111: 46251 | C111: =IF(B111="", "", TEXT(B111, "ddd")) -> Mon | D111: =IF(E111="Yes",0.05,0) +IF(F111="Yes",0.1,0) +IF(G111="Yes",0.15,0) +IF(H111="Yes",0.15,0) +IF(I111="Yes",0.05,0) +IF(J111="Yes",0.05,0) +IF(K111="Yes",0.15,0) +IF(L111="Yes",0.3,0) -> 1 | E111: Yes | F111: Yes | G111: Yes | H111: Yes | I111: Yes | J111: Yes | K111: Yes | L111: Yes
A112: https://4ammedia.zendesk.com/agent/tickets/289679 | B112: 46251 | C112: =IF(B112="", "", TEXT(B112, "ddd")) -> Mon | D112: =IF(E112="Yes",0.05,0) +IF(F112="Yes",0.1,0) +IF(G112="Yes",0.15,0) +IF(H112="Yes",0.15,0) +IF(I112="Yes",0.05,0) +IF(J112="Yes",0.05,0) +IF(K112="Yes",0.15,0) +IF(L112="Yes",0.3,0) -> 1 | E112: Yes | F112: Yes | G112: Yes | H112: Yes | I112: Yes | J112: Yes | K112: Yes | L112: Yes
...

Sheet Godwin
A1: Week (July 13, - July 19,2026)
A2: Ticket Link | B2: Date | C2: Day | D2: SCORE | E2: Notes and Tagging(internal Note and Sticky Note) 5% | F2: COURTESY & EMPATHY 15% | G2: TONE OF VOICE & ELOQUENCE 20% | H2: CALL CONTROL 15% | I2: VERIFICATION 5% | J2: PROBING 5% | K2: MASTERY OF INFORMATION 15% | L2: RESOLUTION 20% | M2: Average | N2: NOTES
A3: https://4ammedia.zendesk.com/agent/tickets/223595 | B3: 46216 | C3: =IF(B3="", "", TEXT(B3, "ddd")) -> Mon | D3: =IF(E3="Yes",0.05,0) +IF(F3="Yes",0.1,0) +IF(G3="Yes",0.15,0) +IF(H3="Yes",0.15,0) +IF(I3="Yes",0.05,0) +IF(J3="Yes",0.05,0) +IF(K3="Yes",0.15,0) +IF(L3="Yes",0.3,0) -> 1 | E3: Yes | F3: Yes | G3: Yes | H3: Yes | I3: Yes | J3: Yes | K3: Yes | L3: Yes
A4: https://4ammedia.zendesk.com/agent/tickets/224343 | B4: 46216 | C4: =IF(B4="", "", TEXT(B4, "ddd")) -> Mon | D4: =IF(E4="Yes",0.05,0) +IF(F4="Yes",0.1,0) +IF(G4="Yes",0.15,0) +IF(H4="Yes",0.15,0) +IF(I4="Yes",0.05,0) +IF(J4="Yes",0.05,0) +IF(K4="Yes",0.15,0) +IF(L4="Yes",0.3,0) -> 1 | E4: Yes | F4: Yes | G4: Yes | H4: Yes | I4: Yes | J4: Yes | K4: Yes | L4: Yes
A5: https://4ammedia.zendesk.com/agent/tickets/224486 | B5: 46216 | C5: =IF(B5="", "", TEXT(B5, "ddd")) -> Mon | D5: =IF(E5="Yes",0.05,0) +IF(F5="Yes",0.1,0) +IF(G5="Yes",0.15,0) +IF(H5="Yes",0.15,0) +IF(I5="Yes",0.05,0) +IF(J5="Yes",0.05,0) +IF(K5="Yes",0.15,0) +IF(L5="Yes",0.3,0) -> 1 | E5: Yes | F5: Yes | G5: Yes | H5: Yes | I5: Yes | J5: Yes | K5: Yes | L5: Yes
A6: https://4ammedia.zendesk.com/agent/tickets/226136 | B6: 46217 | C6: =IF(B6="", "", TEXT(B6, "ddd")) -> Tue | D6: =IF(E6="Yes",0.05,0) +IF(F6="Yes",0.1,0) +IF(G6="Yes",0.15,0) +IF(H6="Yes",0.15,0) +IF(I6="Yes",0.05,0) +IF(J6="Yes",0.05,0) +IF(K6="Yes",0.15,0) +IF(L6="Yes",0.3,0) -> 1 | E6: Yes | F6: Yes | G6: Yes | H6: Yes | I6: Yes | J6: Yes | K6: Yes | L6: Yes
A7: https://4ammedia.zendesk.com/agent/tickets/226291 | B7: 46217 | C7: =IF(B7="", "", TEXT(B7, "ddd")) -> Tue | D7: =IF(E7="Yes",0.05,0) +IF(F7="Yes",0.1,0) +IF(G7="Yes",0.15,0) +IF(H7="Yes",0.15,0) +IF(I7="Yes",0.05,0) +IF(J7="Yes",0.05,0) +IF(K7="Yes",0.15,0) +IF(L7="Yes",0.3,0) -> 1 | E7: Yes | F7: Yes | G7: Yes | H7: Yes | I7: Yes | J7: Yes | K7: Yes | L7: Yes
A8: https://4ammedia.zendesk.com/agent/tickets/226607 | B8: 46217 | C8: =IF(B8="", "", TEXT(B8, "ddd")) -> Tue | D8: =IF(E8="Yes",0.05,0) +IF(F8="Yes",0.1,0) +IF(G8="Yes",0.15,0) +IF(H8="Yes",0.15,0) +IF(I8="Yes",0.05,0) +IF(J8="Yes",0.05,0) +IF(K8="Yes",0.15,0) +IF(L8="Yes",0.3,0) -> 1 | E8: Yes | F8: Yes | G8: Yes | H8: Yes | I8: Yes | J8: Yes | K8: Yes | L8: Yes
A9: https://4ammedia.zendesk.com/agent/tickets/228198 | B9: 46218 | C9: =IF(B9="", "", TEXT(B9, "ddd")) -> Wed | D9: =IF(E9="Yes",0.05,0) +IF(F9="Yes",0.1,0) +IF(G9="Yes",0.15,0) +IF(H9="Yes",0.15,0) +IF(I9="Yes",0.05,0) +IF(J9="Yes",0.05,0) +IF(K9="Yes",0.15,0) +IF(L9="Yes",0.3,0) -> 1 | E9: Yes | F9: Yes | G9: Yes | H9: Yes | I9: Yes | J9: Yes | K9: Yes | L9: Yes
A10: https://4ammedia.zendesk.com/agent/tickets/228419 | B10: 46218 | C10: =IF(B10="", "", TEXT(B10, "ddd")) -> Wed | D10: =IF(E10="Yes",0.05,0) +IF(F10="Yes",0.1,0) +IF(G10="Yes",0.15,0) +IF(H10="Yes",0.15,0) +IF(I10="Yes",0.05,0) +IF(J10="Yes",0.05,0) +IF(K10="Yes",0.15,0) +IF(L10="Yes",0.3,0) -> 1 | E10: Yes | F10: Yes | G10: Yes | H10: Yes | I10: Yes | J10: Yes | K10: Yes | L10: Yes
A11: https://4ammedia.zendesk.com/agent/tickets/228441 | B11: 46218 | C11: =IF(B11="", "", TEXT(B11, "ddd")) -> Wed | D11: =IF(E11="Yes",0.05,0) +IF(F11="Yes",0.1,0) +IF(G11="Yes",0.15,0) +IF(H11="Yes",0.15,0) +IF(I11="Yes",0.05,0) +IF(J11="Yes",0.05,0) +IF(K11="Yes",0.15,0) +IF(L11="Yes",0.3,0) -> 1 | E11: Yes | F11: Yes | G11: Yes | H11: Yes | I11: Yes | J11: Yes | K11: Yes | L11: Yes
A12: https://4ammedia.zendesk.com/agent/tickets/229821 | B12: 46219 | C12: =IF(B12="", "", TEXT(B12, "ddd")) -> Thu | D12: =IF(E12="Yes",0.05,0) +IF(F12="Yes",0.1,0) +IF(G12="Yes",0.15,0) +IF(H12="Yes",0.15,0) +IF(I12="Yes",0.05,0) +IF(J12="Yes",0.05,0) +IF(K12="Yes",0.15,0) +IF(L12="Yes",0.3,0) -> 1 | E12: Yes | F12: Yes | G12: Yes | H12: Yes | I12: Yes | J12: Yes | K12: Yes | L12: Yes
A13: https://4ammedia.zendesk.com/agent/tickets/230130 | B13: 46219 | C13: =IF(B13="", "", TEXT(B13, "ddd")) -> Thu | D13: =IF(E13="Yes",0.05,0) +IF(F13="Yes",0.1,0) +IF(G13="Yes",0.15,0) +IF(H13="Yes",0.15,0) +IF(I13="Yes",0.05,0) +IF(J13="Yes",0.05,0) +IF(K13="Yes",0.15,0) +IF(L13="Yes",0.3,0) -> 1 | E13: Yes | F13: Yes | G13: Yes | H13: Yes | I13: Yes | J13: Yes | K13: Yes | L13: Yes
A14: https://4ammedia.zendesk.com/agent/tickets/230168 | B14: 46219 | C14: =IF(B14="", "", TEXT(B14, "ddd")) -> Thu | D14: =IF(E14="Yes",0.05,0) +IF(F14="Yes",0.1,0) +IF(G14="Yes",0.15,0) +IF(H14="Yes",0.15,0) +IF(I14="Yes",0.05,0) +IF(J14="Yes",0.05,0) +IF(K14="Yes",0.15,0) +IF(L14="Yes",0.3,0) -> 1 | E14: Yes | F14: Yes | G14: Yes | H14: Yes | I14: Yes | J14: Yes | K14: Yes | L14: Yes
... A17: https://4ammedia.zendesk.com/agent/tickets/232457 | B17: 46220 | C17: =IF(B17="", "", TEXT(B17, "ddd")) -> Fri | D17: =IF(E17="Yes",0.05,0) +IF(F17="Yes",0.1,0) +IF(G17="Yes",0.15,0) +IF(H17="Yes",0.15,0) +IF(I17="Yes",0.05,0) +IF(J17="Yes",0.05,0) +IF(K17="Yes",0.15,0) +IF(L17="Yes",0.3,0) -> 1 | E17: Yes | F17: Yes | G17: Yes | H17: Yes | I17: Yes | J17: Yes | K17: Yes | L17: Yes
C18: Final QA Score | D18: =AVERAGE(D3:D17) -> 1 | L18: Final QA Score | M18: =SUM(M3:M17)/75*0.1 -> 0
A19: Week (July 20, - July 26,2026)
A20: Ticket Link | B20: Date | C20: Day | D20: SCORE | E20: Notes and Tagging(internal Note and Sticky Note) 5% | F20: COURTESY & EMPATHY 15% | G20: TONE OF VOICE & ELOQUENCE 20% | H20: CALL CONTROL 15% | I20: VERIFICATION 5% | J20: PROBING 5% | K20: MASTERY OF INFORMATION 15% | L20: RESOLUTION 20% | M20: Average | N20: NOTES
A21: https://4ammedia.zendesk.com/agent/tickets/236232 | B21: 46223 | C21: =IF(B21="", "", TEXT(B21, "ddd")) -> Mon | D21: =IF(E21="Yes",0.05,0) +IF(F21="Yes",0.1,0) +IF(G21="Yes",0.15,0) +IF(H21="Yes",0.15,0) +IF(I21="Yes",0.05,0) +IF(J21="Yes",0.05,0) +IF(K21="Yes",0.15,0) +IF(L21="Yes",0.3,0) -> 1 | E21: Yes | F21: Yes | G21: Yes | H21: Yes | I21: Yes | J21: Yes | K21: Yes | L21: Yes
A22: https://4ammedia.zendesk.com/agent/tickets/236317 | B22: 46223 | C22: =IF(B22="", "", TEXT(B22, "ddd")) -> Mon | D22: =IF(E22="Yes",0.05,0) +IF(F22="Yes",0.1,0) +IF(G22="Yes",0.15,0) +IF(H22="Yes",0.15,0) +IF(I22="Yes",0.05,0) +IF(J22="Yes",0.05,0) +IF(K22="Yes",0.15,0) +IF(L22="Yes",0.3,0) -> 1 | E22: Yes | F22: Yes | G22: Yes | H22: Yes | I22: Yes | J22: Yes | K22: Yes | L22: Yes
A23: https://4ammedia.zendesk.com/agent/tickets/236484 | B23: 46223 | C23: =IF(B23="", "", TEXT(B23, "ddd")) -> Mon | D23: =IF(E23="Yes",0.05,0) +IF(F23="Yes",0.1,0) +IF(G23="Yes",0.15,0) +IF(H23="Yes",0.15,0) +IF(I23="Yes",0.05,0) +IF(J23="Yes",0.05,0) +IF(K23="Yes",0.15,0) +IF(L23="Yes",0.3,0) -> 1 | E23: Yes | F23: Yes | G23: Yes | H23: Yes | I23: Yes | J23: Yes | K23: Yes | L23: Yes
A24: https://4ammedia.zendesk.com/agent/tickets/238404 | B24: 46224 | C24: =IF(B24="", "", TEXT(B24, "ddd")) -> Tue | D24: =IF(E24="Yes",0.05,0) +IF(F24="Yes",0.1,0) +IF(G24="Yes",0.15,0) +IF(H24="Yes",0.15,0) +IF(I24="Yes",0.05,0) +IF(J24="Yes",0.05,0) +IF(K24="Yes",0.15,0) +IF(L24="Yes",0.3,0) -> 1 | E24: Yes | F24: Yes | G24: Yes | H24: Yes | I24: Yes | J24: Yes | K24: Yes | L24: Yes
A25: https://4ammedia.zendesk.com/agent/tickets/238524 | B25: 46224 | C25: =IF(B25="", "", TEXT(B25, "ddd")) -> Tue | D25: =IF(E25="Yes",0.05,0) +IF(F25="Yes",0.1,0) +IF(G25="Yes",0.15,0) +IF(H25="Yes",0.15,0) +IF(I25="Yes",0.05,0) +IF(J25="Yes",0.05,0) +IF(K25="Yes",0.15,0) +IF(L25="Yes",0.3,0) -> 1 | E25: Yes | F25: Yes | G25: Yes | H25: Yes | I25: Yes | J25: Yes | K25: Yes | L25: Yes
A26: https://4ammedia.zendesk.com/agent/tickets/238723 | B26: 46224 | C26: =IF(B26="", "", TEXT(B26, "ddd")) -> Tue | D26: =IF(E26="Yes",0.05,0) +IF(F26="Yes",0.1,0) +IF(G26="Yes",0.15,0) +IF(H26="Yes",0.15,0) +IF(I26="Yes",0.05,0) +IF(J26="Yes",0.05,0) +IF(K26="Yes",0.15,0) +IF(L26="Yes",0.3,0) -> 1 | E26: Yes | F26: Yes | G26: Yes | H26: Yes | I26: Yes | J26: Yes | K26: Yes | L26: Yes
A27: https://4ammedia.zendesk.com/agent/tickets/241119 | B27: 46225 | C27: =IF(B27="", "", TEXT(B27, "ddd")) -> Wed | D27: =IF(E27="Yes",0.05,0) +IF(F27="Yes",0.1,0) +IF(G27="Yes",0.15,0) +IF(H27="Yes",0.15,0) +IF(I27="Yes",0.05,0) +IF(J27="Yes",0.05,0) +IF(K27="Yes",0.15,0) +IF(L27="Yes",0.3,0) -> 1 | E27: Yes | F27: Yes | G27: Yes | H27: Yes | I27: Yes | J27: Yes | K27: Yes | L27: Yes
A28: https://4ammedia.zendesk.com/agent/tickets/241250 | B28: 46225 | C28: =IF(B28="", "", TEXT(B28, "ddd")) -> Wed | D28: =IF(E28="Yes",0.05,0) +IF(F28="Yes",0.1,0) +IF(G28="Yes",0.15,0) +IF(H28="Yes",0.15,0) +IF(I28="Yes",0.05,0) +IF(J28="Yes",0.05,0) +IF(K28="Yes",0.15,0) +IF(L28="Yes",0.3,0) -> 1 | E28: Yes | F28: Yes | G28: Yes | H28: Yes | I28: Yes | J28: Yes | K28: Yes | L28: Yes
A29: https://4ammedia.zendesk.com/agent/tickets/241481 | B29: 46225 | C29: =IF(B29="", "", TEXT(B29, "ddd")) -> Wed | D29: =IF(E29="Yes",0.05,0) +IF(F29="Yes",0.1,0) +IF(G29="Yes",0.15,0) +IF(H29="Yes",0.15,0) +IF(I29="Yes",0.05,0) +IF(J29="Yes",0.05,0) +IF(K29="Yes",0.15,0) +IF(L29="Yes",0.3,0) -> 1 | E29: Yes | F29: Yes | G29: Yes | H29: Yes | I29: Yes | J29: Yes | K29: Yes | L29: Yes
A30: https://4ammedia.zendesk.com/agent/tickets/243006 | B30: 46226 | C30: =IF(B30="", "", TEXT(B30, "ddd")) -> Thu | D30: =IF(E30="Yes",0.05,0) +IF(F30="Yes",0.1,0) +IF(G30="Yes",0.15,0) +IF(H30="Yes",0.15,0) +IF(I30="Yes",0.05,0) +IF(J30="Yes",0.05,0) +IF(K30="Yes",0.15,0) +IF(L30="Yes",0.3,0) -> 1 | E30: Yes | F30: Yes | G30: Yes | H30: Yes | I30: Yes | J30: Yes | K30: Yes | L30: Yes
A31: https://4ammedia.zendesk.com/agent/tickets/243358 | B31: 46226 | C31: =IF(B31="", "", TEXT(B31, "ddd")) -> Thu | D31: =IF(E31="Yes",0.05,0) +IF(F31="Yes",0.1,0) +IF(G31="Yes",0.15,0) +IF(H31="Yes",0.15,0) +IF(I31="Yes",0.05,0) +IF(J31="Yes",0.05,0) +IF(K31="Yes",0.15,0) +IF(L31="Yes",0.3,0) -> 1 | E31: Yes | F31: Yes | G31: Yes | H31: Yes | I31: Yes | J31: Yes | K31: Yes | L31: Yes
A32: https://4ammedia.zendesk.com/agent/tickets/243437 | B32: 46226 | C32: =IF(B32="", "", TEXT(B32, "ddd")) -> Thu | D32: =IF(E32="Yes",0.05,0) +IF(F32="Yes",0.1,0) +IF(G32="Yes",0.15,0) +IF(H32="Yes",0.15,0) +IF(I32="Yes",0.05,0) +IF(J32="Yes",0.05,0) +IF(K32="Yes",0.15,0) +IF(L32="Yes",0.3,0) -> 1 | E32: Yes | F32: Yes | G32: Yes | H32: Yes | I32: Yes | J32: Yes | K32: Yes | L32: Yes
... A35: https://4ammedia.zendesk.com/agent/tickets/245726 | B35: 46227 | C35: =IF(B35="", "", TEXT(B35, "ddd")) -> Fri | D35: =IF(E35="Yes",0.05,0) +IF(F35="Yes",0.1,0) +IF(G35="Yes",0.15,0) +IF(H35="Yes",0.15,0) +IF(I35="Yes",0.05,0) +IF(J35="Yes",0.05,0) +IF(K35="Yes",0.15,0) +IF(L35="Yes",0.3,0) -> 1 | E35: Yes | F35: Yes | G35: Yes | H35: Yes | I35: Yes | J35: Yes | K35: Yes | L35: Yes
C36: Final QA Score | D36: =AVERAGE(D21:D35) -> 1 | L36: Final QA Score | M36: =SUM(M21:M35)/75*0.1 -> 0
A37: Week (July 27, - Aug 2,2026)
A38: Ticket Link | B38: Date | C38: Day | D38: SCORE | E38: Notes and Tagging(internal Note and Sticky Note) 5% | F38: COURTESY & EMPATHY 15% | G38: TONE OF VOICE & ELOQUENCE 20% | H38: CALL CONTROL 15% | I38: VERIFICATION 5% | J38: PROBING 5% | K38: MASTERY OF INFORMATION 15% | L38: RESOLUTION 20% | M38: Average | N38: NOTES
A39: https://4ammedia.zendesk.com/agent/tickets/247831 | B39: 46230 | C39: =IF(B39="", "", TEXT(B39, "ddd")) -> Mon | D39: =IF(E39="Yes",0.05,0) +IF(F39="Yes",0.1,0) +IF(G39="Yes",0.15,0) +IF(H39="Yes",0.15,0) +IF(I39="Yes",0.05,0) +IF(J39="Yes",0.05,0) +IF(K39="Yes",0.15,0) +IF(L39="Yes",0.3,0) -> 1 | E39: Yes | F39: Yes | G39: Yes | H39: Yes | I39: Yes | J39: Yes | K39: Yes | L39: Yes
A40: https://4ammedia.zendesk.com/agent/tickets/249356 | B40: 46230 | C40: =IF(B40="", "", TEXT(B40, "ddd")) -> Mon | D40: =IF(E40="Yes",0.05,0) +IF(F40="Yes",0.1,0) +IF(G40="Yes",0.15,0) +IF(H40="Yes",0.15,0) +IF(I40="Yes",0.05,0) +IF(J40="Yes",0.05,0) +IF(K40="Yes",0.15,0) +IF(L40="Yes",0.3,0) -> 1 | E40: Yes | F40: Yes | G40: Yes | H40: Yes | I40: Yes | J40: Yes | K40: Yes | L40: Yes
A41: https://4ammedia.zendesk.com/agent/tickets/249531 | B41: 46230 | C41: =IF(B41="", "", TEXT(B41, "ddd")) -> Mon | D41: =IF(E41="Yes",0.05,0) +IF(F41="Yes",0.1,0) +IF(G41="Yes",0.15,0) +IF(H41="Yes",0.15,0) +IF(I41="Yes",0.05,0) +IF(J41="Yes",0.05,0) +IF(K41="Yes",0.15,0) +IF(L41="Yes",0.3,0) -> 1 | E41: Yes | F41: Yes | G41: Yes | H41: Yes | I41: Yes | J41: Yes | K41: Yes | L41: Yes
A42: https://4ammedia.zendesk.com/agent/tickets/251980 | B42: 46231 | C42: =IF(B42="", "", TEXT(B42, "ddd")) -> Tue | D42: =IF(E42="Yes",0.05,0) +IF(F42="Yes",0.1,0) +IF(G42="Yes",0.15,0) +IF(H42="Yes",0.15,0) +IF(I42="Yes",0.05,0) +IF(J42="Yes",0.05,0) +IF(K42="Yes",0.15,0) +IF(L42="Yes",0.3,0) -> 1 | E42: Yes | F42: Yes | G42: Yes | H42: Yes | I42: Yes | J42: Yes | K42: Yes | L42: Yes
A43: https://4ammedia.zendesk.com/agent/tickets/252411 | B43: 46231 | C43: =IF(B43="", "", TEXT(B43, "ddd")) -> Tue | D43: =IF(E43="Yes",0.05,0) +IF(F43="Yes",0.1,0) +IF(G43="Yes",0.15,0) +IF(H43="Yes",0.15,0) +IF(I43="Yes",0.05,0) +IF(J43="Yes",0.05,0) +IF(K43="Yes",0.15,0) +IF(L43="Yes",0.3,0) -> 1 | E43: Yes | F43: Yes | G43: Yes | H43: Yes | I43: Yes | J43: Yes | K43: Yes | L43: Yes
A44: https://4ammedia.zendesk.com/agent/tickets/252497 | B44: 46231 | C44: =IF(B44="", "", TEXT(B44, "ddd")) -> Tue | D44: =IF(E44="Yes",0.05,0) +IF(F44="Yes",0.1,0) +IF(G44="Yes",0.15,0) +IF(H44="Yes",0.15,0) +IF(I44="Yes",0.05,0) +IF(J44="Yes",0.05,0) +IF(K44="Yes",0.15,0) +IF(L44="Yes",0.3,0) -> 1 | E44: Yes | F44: Yes | G44: Yes | H44: Yes | I44: Yes | J44: Yes | K44: Yes | L44: Yes
A45: https://4ammedia.zendesk.com/agent/tickets/253885 | B45: 46232 | C45: =IF(B45="", "", TEXT(B45, "ddd")) -> Wed | D45: =IF(E45="Yes",0.05,0) +IF(F45="Yes",0.1,0) +IF(G45="Yes",0.15,0) +IF(H45="Yes",0.15,0) +IF(I45="Yes",0.05,0) +IF(J45="Yes",0.05,0) +IF(K45="Yes",0.15,0) +IF(L45="Yes",0.3,0) -> 1 | E45: Yes | F45: Yes | G45: Yes | H45: Yes | I45: Yes | J45: Yes | K45: Yes | L45: Yes
A46: https://4ammedia.zendesk.com/agent/tickets/254070 | B46: 46232 | C46: =IF(B46="", "", TEXT(B46, "ddd")) -> Wed | D46: =IF(E46="Yes",0.05,0) +IF(F46="Yes",0.1,0) +IF(G46="Yes",0.15,0) +IF(H46="Yes",0.15,0) +IF(I46="Yes",0.05,0) +IF(J46="Yes",0.05,0) +IF(K46="Yes",0.15,0) +IF(L46="Yes",0.3,0) -> 1 | E46: Yes | F46: Yes | G46: Yes | H46: Yes | I46: Yes | J46: Yes | K46: Yes | L46: Yes
A47: https://4ammedia.zendesk.com/agent/tickets/254145 | B47: 46232 | C47: =IF(B47="", "", TEXT(B47, "ddd")) -> Wed | D47: =IF(E47="Yes",0.05,0) +IF(F47="Yes",0.1,0) +IF(G47="Yes",0.15,0) +IF(H47="Yes",0.15,0) +IF(I47="Yes",0.05,0) +IF(J47="Yes",0.05,0) +IF(K47="Yes",0.15,0) +IF(L47="Yes",0.3,0) -> 1 | E47: Yes | F47: Yes | G47: Yes | H47: Yes | I47: Yes | J47: Yes | K47: Yes | L47: Yes
A48: https://4ammedia.zendesk.com/agent/tickets/256360 | B48: 46233 | C48: =IF(B48="", "", TEXT(B48, "ddd")) -> Thu | D48: =IF(E48="Yes",0.05,0) +IF(F48="Yes",0.1,0) +IF(G48="Yes",0.15,0) +IF(H48="Yes",0.15,0) +IF(I48="Yes",0.05,0) +IF(J48="Yes",0.05,0) +IF(K48="Yes",0.15,0) +IF(L48="Yes",0.3,0) -> 1 | E48: Yes | F48: Yes | G48: Yes | H48: Yes | I48: Yes | J48: Yes | K48: Yes | L48: Yes
A49: https://4ammedia.zendesk.com/agent/tickets/256474 | B49: 46233 | C49: =IF(B49="", "", TEXT(B49, "ddd")) -> Thu | D49: =IF(E49="Yes",0.05,0) +IF(F49="Yes",0.1,0) +IF(G49="Yes",0.15,0) +IF(H49="Yes",0.15,0) +IF(I49="Yes",0.05,0) +IF(J49="Yes",0.05,0) +IF(K49="Yes",0.15,0) +IF(L49="Yes",0.3,0) -> 1 | E49: Yes | F49: Yes | G49: Yes | H49: Yes | I49: Yes | J49: Yes | K49: Yes | L49: Yes
A50: https://4ammedia.zendesk.com/agent/tickets/256580 | B50: 46233 | C50: =IF(B50="", "", TEXT(B50, "ddd")) -> Thu | D50: =IF(E50="Yes",0.05,0) +IF(F50="Yes",0.1,0) +IF(G50="Yes",0.15,0) +IF(H50="Yes",0.15,0) +IF(I50="Yes",0.05,0) +IF(J50="Yes",0.05,0) +IF(K50="Yes",0.15,0) +IF(L50="Yes",0.3,0) -> 1 | E50: Yes | F50: Yes | G50: Yes | H50: Yes | I50: Yes | J50: Yes | K50: Yes | L50: Yes
C51: =IF(B51="", "", TEXT(B51, "ddd")) | D51: =IF(E51="Yes",0.05,0) +IF(F51="Yes",0.1,0) +IF(G51="Yes",0.15,0) +IF(H51="Yes",0.15,0) +IF(I51="Yes",0.05,0) +IF(J51="Yes",0.05,0) +IF(K51="Yes",0.15,0) +IF(L51="Yes",0.3,0) -> 1 | E51: Yes | F51: Yes | G51: Yes | H51: Yes | I51: Yes | J51: Yes | K51: Yes | L51: Yes
C52: =IF(B52="", "", TEXT(B52, "ddd")) | D52: =IF(E52="Yes",0.05,0) +IF(F52="Yes",0.1,0) +IF(G52="Yes",0.15,0) +IF(H52="Yes",0.15,0) +IF(I52="Yes",0.05,0) +IF(J52="Yes",0.05,0) +IF(K52="Yes",0.15,0) +IF(L52="Yes",0.3,0) -> 1 | E52: Yes | F52: Yes | G52: Yes | H52: Yes | I52: Yes | J52: Yes | K52: Yes | L52: Yes
C53: =IF(B53="", "", TEXT(B53, "ddd")) | D53: =IF(E53="Yes",0.05,0) +IF(F53="Yes",0.1,0) +IF(G53="Yes",0.15,0) +IF(H53="Yes",0.15,0) +IF(I53="Yes",0.05,0) +IF(J53="Yes",0.05,0) +IF(K53="Yes",0.15,0) +IF(L53="Yes",0.3,0) -> 1 | E53: Yes | F53: Yes | G53: Yes | H53: Yes | I53: Yes | J53: Yes | K53: Yes | L53: Yes
C54: Final QA Score | D54: =AVERAGE(D39:D53) -> 1 | L54: Final QA Score | M54: =SUM(M39:M53)/75*0.1 -> 0
A55: Week (Aug 3, - Aug 9,2026)
A56: Ticket Link | B56: Date | C56: Day | D56: SCORE | E56: Notes and Tagging(internal Note and Sticky Note) 5% | F56: COURTESY & EMPATHY 15% | G56: TONE OF VOICE & ELOQUENCE 20% | H56: CALL CONTROL 15% | I56: VERIFICATION 5% | J56: PROBING 5% | K56: MASTERY OF INFORMATION 15% | L56: RESOLUTION 20% | M56: Average | N56: NOTES
A57: https://4ammedia.zendesk.com/agent/tickets/262381 | B57: 46237 | C57: =IF(B57="", "", TEXT(B57, "ddd")) -> Mon | D57: =IF(E57="Yes",0.05,0) +IF(F57="Yes",0.1,0) +IF(G57="Yes",0.15,0) +IF(H57="Yes",0.15,0) +IF(I57="Yes",0.05,0) +IF(J57="Yes",0.05,0) +IF(K57="Yes",0.15,0) +IF(L57="Yes",0.3,0) -> 1 | E57: Yes | F57: Yes | G57: Yes | H57: Yes | I57: Yes | J57: Yes | K57: Yes | L57: Yes
A58: https://4ammedia.zendesk.com/agent/tickets/262604 | B58: 46237 | C58: =IF(B58="", "", TEXT(B58, "ddd")) -> Mon | D58: =IF(E58="Yes",0.05,0) +IF(F58="Yes",0.1,0) +IF(G58="Yes",0.15,0) +IF(H58="Yes",0.15,0) +IF(I58="Yes",0.05,0) +IF(J58="Yes",0.05,0) +IF(K58="Yes",0.15,0) +IF(L58="Yes",0.3,0) -> 1 | E58: Yes | F58: Yes | G58: Yes | H58: Yes | I58: Yes | J58: Yes | K58: Yes | L58: Yes
A59: https://4ammedia.zendesk.com/agent/tickets/262925 | B59: 46237 | C59: =IF(B59="", "", TEXT(B59, "ddd")) -> Mon | D59: =IF(E59="Yes",0.05,0) +IF(F59="Yes",0.1,0) +IF(G59="Yes",0.15,0) +IF(H59="Yes",0.15,0) +IF(I59="Yes",0.05,0) +IF(J59="Yes",0.05,0) +IF(K59="Yes",0.15,0) +IF(L59="Yes",0.3,0) -> 1 | E59: Yes | F59: Yes | G59: Yes | H59: Yes | I59: Yes | J59: Yes | K59: Yes | L59: Yes
A60: https://4ammedia.zendesk.com/agent/tickets/265328 | B60: 46238 | C60: =IF(B60="", "", TEXT(B60, "ddd")) -> Tue | D60: =IF(E60="Yes",0.05,0) +IF(F60="Yes",0.1,0) +IF(G60="Yes",0.15,0) +IF(H60="Yes",0.15,0) +IF(I60="Yes",0.05,0) +IF(J60="Yes",0.05,0) +IF(K60="Yes",0.15,0) +IF(L60="Yes",0.3,0) -> 1 | E60: Yes | F60: Yes | G60: Yes | H60: Yes | I60: Yes | J60: Yes | K60: Yes | L60: Yes
A61: https://4ammedia.zendesk.com/agent/tickets/265718 | B61: 46238 | C61: =IF(B61="", "", TEXT(B61, "ddd")) -> Tue | D61: =IF(E61="Yes",0.05,0) +IF(F61="Yes",0.1,0) +IF(G61="Yes",0.15,0) +IF(H61="Yes",0.15,0) +IF(I61="Yes",0.05,0) +IF(J61="Yes",0.05,0) +IF(K61="Yes",0.15,0) +IF(L61="Yes",0.3,0) -> 1 | E61: Yes | F61: Yes | G61: Yes | H61: Yes | I61: Yes | J61: Yes | K61: Yes | L61: Yes
A62: https://4ammedia.zendesk.com/agent/tickets/265930 | B62: 46238 | C62: =IF(B62="", "", TEXT(B62, "ddd")) -> Tue | D62: =IF(E62="Yes",0.05,0) +IF(F62="Yes",0.1,0) +IF(G62="Yes",0.15,0) +IF(H62="Yes",0.15,0) +IF(I62="Yes",0.05,0) +IF(J62="Yes",0.05,0) +IF(K62="Yes",0.15,0) +IF(L62="Yes",0.3,0) -> 1 | E62: Yes | F62: Yes | G62: Yes | H62: Yes | I62: Yes | J62: Yes | K62: Yes | L62: Yes
A63: https://4ammedia.zendesk.com/agent/tickets/267443 | B63: 46239 | C63: =IF(B63="", "", TEXT(B63, "ddd")) -> Wed | D63: =IF(E63="Yes",0.05,0) +IF(F63="Yes",0.1,0) +IF(G63="Yes",0.15,0) +IF(H63="Yes",0.15,0) +IF(I63="Yes",0.05,0) +IF(J63="Yes",0.05,0) +IF(K63="Yes",0.15,0) +IF(L63="Yes",0.3,0) -> 1 | E63: Yes | F63: Yes | G63: Yes | H63: Yes | I63: Yes | J63: Yes | K63: Yes | L63: Yes
A64: https://4ammedia.zendesk.com/agent/tickets/267753 | B64: 46239 | C64: =IF(B64="", "", TEXT(B64, "ddd")) -> Wed | D64: =IF(E64="Yes",0.05,0) +IF(F64="Yes",0.1,0) +IF(G64="Yes",0.15,0) +IF(H64="Yes",0.15,0) +IF(I64="Yes",0.05,0) +IF(J64="Yes",0.05,0) +IF(K64="Yes",0.15,0) +IF(L64="Yes",0.3,0) -> 1 | E64: Yes | F64: Yes | G64: Yes | H64: Yes | I64: Yes | J64: Yes | K64: Yes | L64: Yes
A65: https://4ammedia.zendesk.com/agent/tickets/267888 | B65: 46239 | C65: =IF(B65="", "", TEXT(B65, "ddd")) -> Wed | D65: =IF(E65="Yes",0.05,0) +IF(F65="Yes",0.1,0) +IF(G65="Yes",0.15,0) +IF(H65="Yes",0.15,0) +IF(I65="Yes",0.05,0) +IF(J65="Yes",0.05,0) +IF(K65="Yes",0.15,0) +IF(L65="Yes",0.3,0) -> 1 | E65: Yes | F65: Yes | G65: Yes | H65: Yes | I65: Yes | J65: Yes | K65: Yes | L65: Yes
A66: https://4ammedia.zendesk.com/agent/tickets/269172 | B66: 46240 | C66: =IF(B66="", "", TEXT(B66, "ddd")) -> Thu | D66: =IF(E66="Yes",0.05,0) +IF(F66="Yes",0.1,0) +IF(G66="Yes",0.15,0) +IF(H66="Yes",0.15,0) +IF(I66="Yes",0.05,0) +IF(J66="Yes",0.05,0) +IF(K66="Yes",0.15,0) +IF(L66="Yes",0.3,0) -> 1 | E66: Yes | F66: Yes | G66: Yes | H66: Yes | I66: Yes | J66: Yes | K66: Yes | L66: Yes
A67: https://4ammedia.zendesk.com/agent/tickets/269233 | B67: 46240 | C67: =IF(B67="", "", TEXT(B67, "ddd")) -> Thu | D67: =IF(E67="Yes",0.05,0) +IF(F67="Yes",0.1,0) +IF(G67="Yes",0.15,0) +IF(H67="Yes",0.15,0) +IF(I67="Yes",0.05,0) +IF(J67="Yes",0.05,0) +IF(K67="Yes",0.15,0) +IF(L67="Yes",0.3,0) -> 1 | E67: Yes | F67: Yes | G67: Yes | H67: Yes | I67: Yes | J67: Yes | K67: Yes | L67: Yes
A68: https://4ammedia.zendesk.com/agent/tickets/269399 | B68: 46240 | C68: =IF(B68="", "", TEXT(B68, "ddd")) -> Thu | D68: =IF(E68="Yes",0.05,0) +IF(F68="Yes",0.1,0) +IF(G68="Yes",0.15,0) +IF(H68="Yes",0.15,0) +IF(I68="Yes",0.05,0) +IF(J68="Yes",0.05,0) +IF(K68="Yes",0.15,0) +IF(L68="Yes",0.3,0) -> 1 | E68: Yes | F68: Yes | G68: Yes | H68: Yes | I68: Yes | J68: Yes | K68: Yes | L68: Yes
... A71: https://4ammedia.zendesk.com/agent/tickets/271870 | B71: 46241 | C71: =IF(B71="", "", TEXT(B71, "ddd")) -> Fri | D71: =IF(E71="Yes",0.05,0) +IF(F71="Yes",0.1,0) +IF(G71="Yes",0.15,0) +IF(H71="Yes",0.15,0) +IF(I71="Yes",0.05,0) +IF(J71="Yes",0.05,0) +IF(K71="Yes",0.15,0) +IF(L71="Yes",0.3,0) -> 1 | E71: Yes | F71: Yes | G71: Yes | H71: Yes | I71: Yes | J71: Yes | K71: Yes | L71: Yes
C72: Final QA Score | D72: =AVERAGE(D57:D71) -> 1 | L72: Final QA Score | M72: =SUM(M57:M71)/75*0.1 -> 0
A73: Week (Aug 10, - Aug 16,2026)
A74: Ticket Link | B74: Date | C74: Day | D74: SCORE | E74: Notes and Tagging(internal Note and Sticky Note) 5% | F74: COURTESY & EMPATHY 15% | G74: TONE OF VOICE & ELOQUENCE 20% | H74: CALL CONTROL 15% | I74: VERIFICATION 5% | J74: PROBING 5% | K74: MASTERY OF INFORMATION 15% | L74: RESOLUTION 20% | M74: Average | N74: NOTES
A75: https://4ammedia.zendesk.com/agent/tickets/275579 | B75: 46244 | C75: =IF(B75="", "", TEXT(B75, "ddd")) -> Mon | D75: =IF(E75="Yes",0.05,0) +IF(F75="Yes",0.1,0) +IF(G75="Yes",0.15,0) +IF(H75="Yes",0.15,0) +IF(I75="Yes",0.05,0) +IF(J75="Yes",0.05,0) +IF(K75="Yes",0.15,0) +IF(L75="Yes",0.3,0) -> 1 | E75: Yes | F75: Yes | G75: Yes | H75: Yes | I75: Yes | J75: Yes | K75: Yes | L75: Yes
A76: https://4ammedia.zendesk.com/agent/tickets/275985 | B76: 46244 | C76: =IF(B76="", "", TEXT(B76, "ddd")) -> Mon | D76: =IF(E76="Yes",0.05,0) +IF(F76="Yes",0.1,0) +IF(G76="Yes",0.15,0) +IF(H76="Yes",0.15,0) +IF(I76="Yes",0.05,0) +IF(J76="Yes",0.05,0) +IF(K76="Yes",0.15,0) +IF(L76="Yes",0.3,0) -> 1 | E76: Yes | F76: Yes | G76: Yes | H76: Yes | I76: Yes | J76: Yes | K76: Yes | L76: Yes
A77: https://4ammedia.zendesk.com/agent/tickets/276302 | B77: 46244 | C77: =IF(B77="", "", TEXT(B77, "ddd")) -> Mon | D77: =IF(E77="Yes",0.05,0) +IF(F77="Yes",0.1,0) +IF(G77="Yes",0.15,0) +IF(H77="Yes",0.15,0) +IF(I77="Yes",0.05,0) +IF(J77="Yes",0.05,0) +IF(K77="Yes",0.15,0) +IF(L77="Yes",0.3,0) -> 1 | E77: Yes | F77: Yes | G77: Yes | H77: Yes | I77: Yes | J77: Yes | K77: Yes | L77: Yes
A78: https://4ammedia.zendesk.com/agent/tickets/278094 | B78: 46245 | C78: =IF(B78="", "", TEXT(B78, "ddd")) -> Tue | D78: =IF(E78="Yes",0.05,0) +IF(F78="Yes",0.1,0) +IF(G78="Yes",0.15,0) +IF(H78="Yes",0.15,0) +IF(I78="Yes",0.05,0) +IF(J78="Yes",0.05,0) +IF(K78="Yes",0.15,0) +IF(L78="Yes",0.3,0) -> 1 | E78: Yes | F78: Yes | G78: Yes | H78: Yes | I78: Yes | J78: Yes | K78: Yes | L78: Yes
A79: https://4ammedia.zendesk.com/agent/tickets/278245 | B79: 46245 | C79: =IF(B79="", "", TEXT(B79, "ddd")) -> Tue | D79: =IF(E79="Yes",0.05,0) +IF(F79="Yes",0.1,0) +IF(G79="Yes",0.15,0) +IF(H79="Yes",0.15,0) +IF(I79="Yes",0.05,0) +IF(J79="Yes",0.05,0) +IF(K79="Yes",0.15,0) +IF(L79="Yes",0.3,0) -> 1 | E79: Yes | F79: Yes | G79: Yes | H79: Yes | I79: Yes | J79: Yes | K79: Yes | L79: Yes
A80: https://4ammedia.zendesk.com/agent/tickets/278640 | B80: 46245 | C80: =IF(B80="", "", TEXT(B80, "ddd")) -> Tue | D80: =IF(E80="Yes",0.05,0) +IF(F80="Yes",0.1,0) +IF(G80="Yes",0.15,0) +IF(H80="Yes",0.15,0) +IF(I80="Yes",0.05,0) +IF(J80="Yes",0.05,0) +IF(K80="Yes",0.15,0) +IF(L80="Yes",0.3,0) -> 1 | E80: Yes | F80: Yes | G80: Yes | H80: Yes | I80: Yes | J80: Yes | K80: Yes | L80: Yes
A81: https://4ammedia.zendesk.com/agent/tickets/280410 | B81: 46246 | C81: =IF(B81="", "", TEXT(B81, "ddd")) -> Wed | D81: =IF(E81="Yes",0.05,0) +IF(F81="Yes",0.1,0) +IF(G81="Yes",0.15,0) +IF(H81="Yes",0.15,0) +IF(I81="Yes",0.05,0) +IF(J81="Yes",0.05,0) +IF(K81="Yes",0.15,0) +IF(L81="Yes",0.3,0) -> 1 | E81: Yes | F81: Yes | G81: Yes | H81: Yes | I81: Yes | J81: Yes | K81: Yes | L81: Yes
A82: https://4ammedia.zendesk.com/agent/tickets/280676 | B82: 46246 | C82: =IF(B82="", "", TEXT(B82, "ddd")) -> Wed | D82: =IF(E82="Yes",0.05,0) +IF(F82="Yes",0.1,0) +IF(G82="Yes",0.15,0) +IF(H82="Yes",0.15,0) +IF(I82="Yes",0.05,0) +IF(J82="Yes",0.05,0) +IF(K82="Yes",0.15,0) +IF(L82="Yes",0.3,0) -> 1 | E82: Yes | F82: Yes | G82: Yes | H82: Yes | I82: Yes | J82: Yes | K82: Yes | L82: Yes
A83: https://4ammedia.zendesk.com/agent/tickets/280914 | B83: 46246 | C83: =IF(B83="", "", TEXT(B83, "ddd")) -> Wed | D83: =IF(E83="Yes",0.05,0) +IF(F83="Yes",0.1,0) +IF(G83="Yes",0.15,0) +IF(H83="Yes",0.15,0) +IF(I83="Yes",0.05,0) +IF(J83="Yes",0.05,0) +IF(K83="Yes",0.15,0) +IF(L83="Yes",0.3,0) -> 1 | E83: Yes | F83: Yes | G83: Yes | H83: Yes | I83: Yes | J83: Yes | K83: Yes | L83: Yes
A84: https://4ammedia.zendesk.com/agent/tickets/282002 | B84: 46247 | C84: =IF(B84="", "", TEXT(B84, "ddd")) -> Thu | D84: =IF(E84="Yes",0.05,0) +IF(F84="Yes",0.1,0) +IF(G84="Yes",0.15,0) +IF(H84="Yes",0.15,0) +IF(I84="Yes",0.05,0) +IF(J84="Yes",0.05,0) +IF(K84="Yes",0.15,0) +IF(L84="Yes",0.3,0) -> 1 | E84: Yes | F84: Yes | G84: Yes | H84: Yes | I84: Yes | J84: Yes | K84: Yes | L84: Yes
A85: https://4ammedia.zendesk.com/agent/tickets/282158 | B85: 46247 | C85: =IF(B85="", "", TEXT(B85, "ddd")) -> Thu | D85: =IF(E85="Yes",0.05,0) +IF(F85="Yes",0.1,0) +IF(G85="Yes",0.15,0) +IF(H85="Yes",0.15,0) +IF(I85="Yes",0.05,0) +IF(J85="Yes",0.05,0) +IF(K85="Yes",0.15,0) +IF(L85="Yes",0.3,0) -> 1 | E85: Yes | F85: Yes | G85: Yes | H85: Yes | I85: Yes | J85: Yes | K85: Yes | L85: Yes
A86: https://4ammedia.zendesk.com/agent/tickets/282278 | B86: 46247 | C86: =IF(B86="", "", TEXT(B86, "ddd")) -> Thu | D86: =IF(E86="Yes",0.05,0) +IF(F86="Yes",0.1,0) +IF(G86="Yes",0.15,0) +IF(H86="Yes",0.15,0) +IF(I86="Yes",0.05,0) +IF(J86="Yes",0.05,0) +IF(K86="Yes",0.15,0) +IF(L86="Yes",0.3,0) -> 1 | E86: Yes | F86: Yes | G86: Yes | H86: Yes | I86: Yes | J86: Yes | K86: Yes | L86: Yes
... A89: https://4ammedia.zendesk.com/agent/tickets/284590 | B89: 46248 | C89: =IF(B89="", "", TEXT(B89, "ddd")) -> Fri | D89: =IF(E89="Yes",0.05,0) +IF(F89="Yes",0.1,0) +IF(G89="Yes",0.15,0) +IF(H89="Yes",0.15,0) +IF(I89="Yes",0.05,0) +IF(J89="Yes",0.05,0) +IF(K89="Yes",0.15,0) +IF(L89="Yes",0.3,0) -> 1 | E89: Yes | F89: Yes | G89: Yes | H89: Yes | I89: Yes | J89: Yes | K89: Yes | L89: Yes
C90: Final QA Score | D90: =AVERAGE(D75:D89) -> 1 | L90: Final QA Score | M90: =SUM(M75:M89)/75*0.1 -> 0
A91: Week (Aug 17, - Aug 23,2026)
A92: Ticket Link | B92: Date | C92: Day | D92: SCORE | E92: Notes and Tagging(internal Note and Sticky Note) 5% | F92: COURTESY & EMPATHY 15% | G92: TONE OF VOICE & ELOQUENCE 20% | H92: CALL CONTROL 15% | I92: VERIFICATION 5% | J92: PROBING 5% | K92: MASTERY OF INFORMATION 15% | L92: RESOLUTION 20% | M92: Average | N92: NOTES
A93: https://4ammedia.zendesk.com/agent/tickets/288671 | B93: 46251 | C93: =IF(B93="", "", TEXT(B93, "ddd")) -> Mon | D93: =IF(E93="Yes",0.05,0) +IF(F93="Yes",0.1,0) +IF(G93="Yes",0.15,0) +IF(H93="Yes",0.15,0) +IF(I93="Yes",0.05,0) +IF(J93="Yes",0.05,0) +IF(K93="Yes",0.15,0) +IF(L93="Yes",0.3,0) -> 1 | E93: Yes | F93: Yes | G93: Yes | H93: Yes | I93: Yes | J93: Yes | K93: Yes | L93: Yes
A94: https://4ammedia.zendesk.com/agent/tickets/288745 | B94: 46251 | C94: =IF(B94="", "", TEXT(B94, "ddd")) -> Mon | D94: =IF(E94="Yes",0.05,0) +IF(F94="Yes",0.1,0) +IF(G94="Yes",0.15,0) +IF(H94="Yes",0.15,0) +IF(I94="Yes",0.05,0) +IF(J94="Yes",0.05,0) +IF(K94="Yes",0.15,0) +IF(L94="Yes",0.3,0) -> 1 | E94: Yes | F94: Yes | G94: Yes | H94: Yes | I94: Yes | J94: Yes | K94: Yes | L94: Yes
A95: https://4ammedia.zendesk.com/agent/tickets/288947 | B95: 46251 | C95: =IF(B95="", "", TEXT(B95, "ddd")) -> Mon | D95: =IF(E95="Yes",0.05,0) +IF(F95="Yes",0.1,0) +IF(G95="Yes",0.15,0) +IF(H95="Yes",0.15,0) +IF(I95="Yes",0.05,0) +IF(J95="Yes",0.05,0) +IF(K95="Yes",0.15,0) +IF(L95="Yes",0.3,0) -> 1 | E95: Yes | F95: Yes | G95: Yes | H95: Yes | I95: Yes | J95: Yes | K95: Yes | L95: Yes
A96: https://4ammedia.zendesk.com/agent/tickets/291083 | B96: 46252 | C96: =IF(B96="", "", TEXT(B96, "ddd")) -> Tue | D96: =IF(E96="Yes",0.05,0) +IF(F96="Yes",0.1,0) +IF(G96="Yes",0.15,0) +IF(H96="Yes",0.15,0) +IF(I96="Yes",0.05,0) +IF(J96="Yes",0.05,0) +IF(K96="Yes",0.15,0) +IF(L96="Yes",0.3,0) -> 1 | E96: Yes | F96: Yes | G96: Yes | H96: Yes | I96: Yes | J96: Yes | K96: Yes | L96: Yes
A97: https://4ammedia.zendesk.com/agent/tickets/291209 | B97: 46252 | C97: =IF(B97="", "", TEXT(B97, "ddd")) -> Tue | D97: =IF(E97="Yes",0.05,0) +IF(F97="Yes",0.1,0) +IF(G97="Yes",0.15,0) +IF(H97="Yes",0.15,0) +IF(I97="Yes",0.05,0) +IF(J97="Yes",0.05,0) +IF(K97="Yes",0.15,0) +IF(L97="Yes",0.3,0) -> 1 | E97: Yes | F97: Yes | G97: Yes | H97: Yes | I97: Yes | J97: Yes | K97: Yes | L97: Yes
A98: https://4ammedia.zendesk.com/agent/tickets/291253 | B98: 46252 | C98: =IF(B98="", "", TEXT(B98, "ddd")) -> Tue | D98: =IF(E98="Yes",0.05,0) +IF(F98="Yes",0.1,0) +IF(G98="Yes",0.15,0) +IF(H98="Yes",0.15,0) +IF(I98="Yes",0.05,0) +IF(J98="Yes",0.05,0) +IF(K98="Yes",0.15,0) +IF(L98="Yes",0.3,0) -> 1 | E98: Yes | F98: Yes | G98: Yes | H98: Yes | I98: Yes | J98: Yes | K98: Yes | L98: Yes
A99: https://4ammedia.zendesk.com/agent/tickets/293555 | B99: 46253 | C99: =IF(B99="", "", TEXT(B99, "ddd")) -> Wed | D99: =IF(E99="Yes",0.05,0) +IF(F99="Yes",0.1,0) +IF(G99="Yes",0.15,0) +IF(H99="Yes",0.15,0) +IF(I99="Yes",0.05,0) +IF(J99="Yes",0.05,0) +IF(K99="Yes",0.15,0) +IF(L99="Yes",0.3,0) -> 1 | E99: Yes | F99: Yes | G99: Yes | H99: Yes | I99: Yes | J99: Yes | K99: Yes | L99: Yes
A100: https://4ammedia.zendesk.com/agent/tickets/293616 | B100: 46253 | C100: =IF(B100="", "", TEXT(B100, "ddd")) -> Wed | D100: =IF(E100="Yes",0.05,0) +IF(F100="Yes",0.1,0) +IF(G100="Yes",0.15,0) +IF(H100="Yes",0.15,0) +IF(I100="Yes",0.05,0) +IF(J100="Yes",0.05,0) +IF(K100="Yes",0.15,0) +IF(L100="Yes",0.3,0) -> 1 | E100: Yes | F100: Yes | G100: Yes | H100: Yes | I100: Yes | J100: Yes | K100: Yes | L100: Yes
A101: https://4ammedia.zendesk.com/agent/tickets/293805 | B101: 46253 | C101: =IF(B101="", "", TEXT(B101, "ddd")) -> Wed | D101: =IF(E101="Yes",0.05,0) +IF(F101="Yes",0.1,0) +IF(G101="Yes",0.15,0) +IF(H101="Yes",0.15,0) +IF(I101="Yes",0.05,0) +IF(J101="Yes",0.05,0) +IF(K101="Yes",0.15,0) +IF(L101="Yes",0.3,0) -> 1 | E101: Yes | F101: Yes | G101: Yes | H101: Yes | I101: Yes | J101: Yes | K101: Yes | L101: Yes
A102: https://4ammedia.zendesk.com/agent/tickets/295178 | B102: 46254 | C102: =IF(B102="", "", TEXT(B102, "ddd")) -> Thu | D102: =IF(E102="Yes",0.05,0) +IF(F102="Yes",0.1,0) +IF(G102="Yes",0.15,0) +IF(H102="Yes",0.15,0) +IF(I102="Yes",0.05,0) +IF(J102="Yes",0.05,0) +IF(K102="Yes",0.15,0) +IF(L102="Yes",0.3,0) -> 1 | E102: Yes | F102: Yes | G102: Yes | H102: Yes | I102: Yes | J102: Yes | K102: Yes | L102: Yes
A103: https://4ammedia.zendesk.com/agent/tickets/295491 | B103: 46254 | C103: =IF(B103="", "", TEXT(B103, "ddd")) -> Thu | D103: =IF(E103="Yes",0.05,0) +IF(F103="Yes",0.1,0) +IF(G103="Yes",0.15,0) +IF(H103="Yes",0.15,0) +IF(I103="Yes",0.05,0) +IF(J103="Yes",0.05,0) +IF(K103="Yes",0.15,0) +IF(L103="Yes",0.3,0) -> 1 | E103: Yes | F103: Yes | G103: Yes | H103: Yes | I103: Yes | J103: Yes | K103: Yes | L103: Yes
A104: https://4ammedia.zendesk.com/agent/tickets/295536 | B104: 46254 | C104: =IF(B104="", "", TEXT(B104, "ddd")) -> Thu | D104: =IF(E104="Yes",0.05,0) +IF(F104="Yes",0.1,0) +IF(G104="Yes",0.15,0) +IF(H104="Yes",0.15,0) +IF(I104="Yes",0.05,0) +IF(J104="Yes",0.05,0) +IF(K104="Yes",0.15,0) +IF(L104="Yes",0.3,0) -> 1 | E104: Yes | F104: Yes | G104: Yes | H104: Yes | I104: Yes | J104: Yes | K104: Yes | L104: Yes
... A107: https://4ammedia.zendesk.com/agent/tickets/297034 | B107: 46255 | C107: =IF(B107="", "", TEXT(B107, "ddd")) -> Fri | D107: =IF(E107="Yes",0.05,0) +IF(F107="Yes",0.1,0) +IF(G107="Yes",0.15,0) +IF(H107="Yes",0.15,0) +IF(I107="Yes",0.05,0) +IF(J107="Yes",0.05,0) +IF(K107="Yes",0.15,0) +IF(L107="Yes",0.3,0) -> 1 | E107: Yes | F107: Yes | G107: Yes | H107: Yes | I107: Yes | J107: Yes | K107: Yes | L107: Yes
C108: Final QA Score | D108: =AVERAGE(D93:D107) -> 1 | L108: Final QA Score | M108: =SUM(M93:M107)/75*0.1 -> 0
A109: Week (Aug 24, - Aug 30,2026)
A110: Ticket Link | B110: Date | C110: Day | D110: SCORE | E110: Notes and Tagging(internal Note and Sticky Note) 5% | F110: COURTESY & EMPATHY 15% | G110: TONE OF VOICE & ELOQUENCE 20% | H110: CALL CONTROL 15% | I110: VERIFICATION 5% | J110: PROBING 5% | K110: MASTERY OF INFORMATION 15% | L110: RESOLUTION 20% | M110: Average | N110: NOTES
...

Sheet Candy
A1: Week (July 13, - July 19,2026)
A2: Ticket Link | B2: Date | C2: Day | D2: SCORE | E2: Notes and Tagging(internal Note and Sticky Note) 5% | F2: COURTESY & EMPATHY 15% | G2: TONE OF VOICE & ELOQUENCE 20% | H2: CALL CONTROL 15% | I2: VERIFICATION 5% | J2: PROBING 5% | K2: MASTERY OF INFORMATION 15% | L2: RESOLUTION 20% | M2: Average | N2: NOTES
A3: https://4ammedia.zendesk.com/agent/tickets/224171 | B3: 46216 | C3: =IF(B3="", "", TEXT(B3, "ddd")) -> Mon | D3: =IF(E3="Yes",0.05,0) +IF(F3="Yes",0.1,0) +IF(G3="Yes",0.15,0) +IF(H3="Yes",0.15,0) +IF(I3="Yes",0.05,0) +IF(J3="Yes",0.05,0) +IF(K3="Yes",0.15,0) +IF(L3="Yes",0.3,0) -> 1 | E3: Yes | F3: Yes | G3: Yes | H3: Yes | I3: Yes | J3: Yes | K3: Yes | L3: Yes
A4: https://4ammedia.zendesk.com/agent/tickets/224395 | B4: 46216 | C4: =IF(B4="", "", TEXT(B4, "ddd")) -> Mon | D4: =IF(E4="Yes",0.05,0) +IF(F4="Yes",0.1,0) +IF(G4="Yes",0.15,0) +IF(H4="Yes",0.15,0) +IF(I4="Yes",0.05,0) +IF(J4="Yes",0.05,0) +IF(K4="Yes",0.15,0) +IF(L4="Yes",0.3,0) -> 1 | E4: Yes | F4: Yes | G4: Yes | H4: Yes | I4: Yes | J4: Yes | K4: Yes | L4: Yes
A5: https://4ammedia.zendesk.com/agent/tickets/224688 | B5: 46216 | C5: =IF(B5="", "", TEXT(B5, "ddd")) -> Mon | D5: =IF(E5="Yes",0.05,0) +IF(F5="Yes",0.1,0) +IF(G5="Yes",0.15,0) +IF(H5="Yes",0.15,0) +IF(I5="Yes",0.05,0) +IF(J5="Yes",0.05,0) +IF(K5="Yes",0.15,0) +IF(L5="Yes",0.3,0) -> 1 | E5: Yes | F5: Yes | G5: Yes | H5: Yes | I5: Yes | J5: Yes | K5: Yes | L5: Yes
A6: https://4ammedia.zendesk.com/agent/tickets/226879 | B6: 46217 | C6: =IF(B6="", "", TEXT(B6, "ddd")) -> Tue | D6: =IF(E6="Yes",0.05,0) +IF(F6="Yes",0.1,0) +IF(G6="Yes",0.15,0) +IF(H6="Yes",0.15,0) +IF(I6="Yes",0.05,0) +IF(J6="Yes",0.05,0) +IF(K6="Yes",0.15,0) +IF(L6="Yes",0.3,0) -> 1 | E6: Yes | F6: Yes | G6: Yes | H6: Yes | I6: Yes | J6: Yes | K6: Yes | L6: Yes
A7: https://4ammedia.zendesk.com/agent/tickets/226958 | B7: 46217 | C7: =IF(B7="", "", TEXT(B7, "ddd")) -> Tue | D7: =IF(E7="Yes",0.05,0) +IF(F7="Yes",0.1,0) +IF(G7="Yes",0.15,0) +IF(H7="Yes",0.15,0) +IF(I7="Yes",0.05,0) +IF(J7="Yes",0.05,0) +IF(K7="Yes",0.15,0) +IF(L7="Yes",0.3,0) -> 1 | E7: Yes | F7: Yes | G7: Yes | H7: Yes | I7: Yes | J7: Yes | K7: Yes | L7: Yes
A8: https://4ammedia.zendesk.com/agent/tickets/226976 | B8: 46217 | C8: =IF(B8="", "", TEXT(B8, "ddd")) -> Tue | D8: =IF(E8="Yes",0.05,0) +IF(F8="Yes",0.1,0) +IF(G8="Yes",0.15,0) +IF(H8="Yes",0.15,0) +IF(I8="Yes",0.05,0) +IF(J8="Yes",0.05,0) +IF(K8="Yes",0.15,0) +IF(L8="Yes",0.3,0) -> 1 | E8: Yes | F8: Yes | G8: Yes | H8: Yes | I8: Yes | J8: Yes | K8: Yes | L8: Yes
A9: https://4ammedia.zendesk.com/agent/tickets/229944 | B9: 46219 | C9: =IF(B9="", "", TEXT(B9, "ddd")) -> Thu | D9: =IF(E9="Yes",0.05,0) +IF(F9="Yes",0.1,0) +IF(G9="Yes",0.15,0) +IF(H9="Yes",0.15,0) +IF(I9="Yes",0.05,0) +IF(J9="Yes",0.05,0) +IF(K9="Yes",0.15,0) +IF(L9="Yes",0.3,0) -> 1 | E9: Yes | F9: Yes | G9: Yes | H9: Yes | I9: Yes | J9: Yes | K9: Yes | L9: Yes
A10: https://4ammedia.zendesk.com/agent/tickets/229987 | B10: 46219 | C10: =IF(B10="", "", TEXT(B10, "ddd")) -> Thu | D10: =IF(E10="Yes",0.05,0) +IF(F10="Yes",0.1,0) +IF(G10="Yes",0.15,0) +IF(H10="Yes",0.15,0) +IF(I10="Yes",0.05,0) +IF(J10="Yes",0.05,0) +IF(K10="Yes",0.15,0) +IF(L10="Yes",0.3,0) -> 1 | E10: Yes | F10: Yes | G10: Yes | H10: Yes | I10: Yes | J10: Yes | K10: Yes | L10: Yes
A11: https://4ammedia.zendesk.com/agent/tickets/230022 | B11: 46219 | C11: =IF(B11="", "", TEXT(B11, "ddd")) -> Thu | D11: =IF(E11="Yes",0.05,0) +IF(F11="Yes",0.1,0) +IF(G11="Yes",0.15,0) +IF(H11="Yes",0.15,0) +IF(I11="Yes",0.05,0) +IF(J11="Yes",0.05,0) +IF(K11="Yes",0.15,0) +IF(L11="Yes",0.3,0) -> 1 | E11: Yes | F11: Yes | G11: Yes | H11: Yes | I11: Yes | J11: Yes | K11: Yes | L11: Yes
A12: https://4ammedia.zendesk.com/agent/tickets/232305 | B12: 46220 | C12: =IF(B12="", "", TEXT(B12, "ddd")) -> Fri | D12: =IF(E12="Yes",0.05,0) +IF(F12="Yes",0.1,0) +IF(G12="Yes",0.15,0) +IF(H12="Yes",0.15,0) +IF(I12="Yes",0.05,0) +IF(J12="Yes",0.05,0) +IF(K12="Yes",0.15,0) +IF(L12="Yes",0.3,0) -> 1 | E12: Yes | F12: Yes | G12: Yes | H12: Yes | I12: Yes | J12: Yes | K12: Yes | L12: Yes
A13: https://4ammedia.zendesk.com/agent/tickets/232580 | B13: 46220 | C13: =IF(B13="", "", TEXT(B13, "ddd")) -> Fri | D13: =IF(E13="Yes",0.05,0) +IF(F13="Yes",0.1,0) +IF(G13="Yes",0.15,0) +IF(H13="Yes",0.15,0) +IF(I13="Yes",0.05,0) +IF(J13="Yes",0.05,0) +IF(K13="Yes",0.15,0) +IF(L13="Yes",0.3,0) -> 1 | E13: Yes | F13: Yes | G13: Yes | H13: Yes | I13: Yes | J13: Yes | K13: Yes | L13: Yes
A14: https://4ammedia.zendesk.com/agent/tickets/232772 | B14: 46220 | C14: =IF(B14="", "", TEXT(B14, "ddd")) -> Fri | D14: =IF(E14="Yes",0.05,0) +IF(F14="Yes",0.1,0) +IF(G14="Yes",0.15,0) +IF(H14="Yes",0.15,0) +IF(I14="Yes",0.05,0) +IF(J14="Yes",0.05,0) +IF(K14="Yes",0.15,0) +IF(L14="Yes",0.3,0) -> 1 | E14: Yes | F14: Yes | G14: Yes | H14: Yes | I14: Yes | J14: Yes | K14: Yes | L14: Yes
A15: https://4ammedia.zendesk.com/agent/tickets/233703 | B15: 46221 | C15: =IF(B15="", "", TEXT(B15, "ddd")) -> Sat | D15: =IF(E15="Yes",0.05,0) +IF(F15="Yes",0.1,0) +IF(G15="Yes",0.15,0) +IF(H15="Yes",0.15,0) +IF(I15="Yes",0.05,0) +IF(J15="Yes",0.05,0) +IF(K15="Yes",0.15,0) +IF(L15="Yes",0.3,0) -> 0
A16: https://4ammedia.zendesk.com/agent/tickets/233776 | B16: 46221 | C16: =IF(B16="", "", TEXT(B16, "ddd")) -> Sat | D16: =IF(E16="Yes",0.05,0) +IF(F16="Yes",0.1,0) +IF(G16="Yes",0.15,0) +IF(H16="Yes",0.15,0) +IF(I16="Yes",0.05,0) +IF(J16="Yes",0.05,0) +IF(K16="Yes",0.15,0) +IF(L16="Yes",0.3,0) -> 0
A17: https://4ammedia.zendesk.com/agent/tickets/233878 | B17: 46221 | C17: =IF(B17="", "", TEXT(B17, "ddd")) -> Sat | D17: =IF(E17="Yes",0.05,0) +IF(F17="Yes",0.1,0) +IF(G17="Yes",0.15,0) +IF(H17="Yes",0.15,0) +IF(I17="Yes",0.05,0) +IF(J17="Yes",0.05,0) +IF(K17="Yes",0.15,0) +IF(L17="Yes",0.3,0) -> 0
C18: Final QA Score | D18: =AVERAGE(D3:D17) -> 0.8 | L18: Final QA Score | M18: =SUM(M3:M17)/75*0.1 -> 0
A19: Week (July 20, - July 26,2026)
A20: Ticket Link | B20: Date | C20: Day | D20: SCORE | E20: Notes and Tagging(internal Note and Sticky Note) 5% | F20: COURTESY & EMPATHY 15% | G20: TONE OF VOICE & ELOQUENCE 20% | H20: CALL CONTROL 15% | I20: VERIFICATION 5% | J20: PROBING 5% | K20: MASTERY OF INFORMATION 15% | L20: RESOLUTION 20% | M20: Average | N20: NOTES
A21: https://4ammedia.zendesk.com/agent/tickets/236767 | B21: 46223 | C21: =IF(B21="", "", TEXT(B21, "ddd")) -> Mon | D21: =IF(E21="Yes",0.05,0) +IF(F21="Yes",0.1,0) +IF(G21="Yes",0.15,0) +IF(H21="Yes",0.15,0) +IF(I21="Yes",0.05,0) +IF(J21="Yes",0.05,0) +IF(K21="Yes",0.15,0) +IF(L21="Yes",0.3,0) -> 1 | E21: Yes | F21: Yes | G21: Yes | H21: Yes | I21: Yes | J21: Yes | K21: Yes | L21: Yes
A22: https://4ammedia.zendesk.com/agent/tickets/236819 | B22: 46223 | C22: =IF(B22="", "", TEXT(B22, "ddd")) -> Mon | D22: =IF(E22="Yes",0.05,0) +IF(F22="Yes",0.1,0) +IF(G22="Yes",0.15,0) +IF(H22="Yes",0.15,0) +IF(I22="Yes",0.05,0) +IF(J22="Yes",0.05,0) +IF(K22="Yes",0.15,0) +IF(L22="Yes",0.3,0) -> 1 | E22: Yes | F22: Yes | G22: Yes | H22: Yes | I22: Yes | J22: Yes | K22: Yes | L22: Yes
A23: https://4ammedia.zendesk.com/agent/tickets/236994 | B23: 46223 | C23: =IF(B23="", "", TEXT(B23, "ddd")) -> Mon | D23: =IF(E23="Yes",0.05,0) +IF(F23="Yes",0.1,0) +IF(G23="Yes",0.15,0) +IF(H23="Yes",0.15,0) +IF(I23="Yes",0.05,0) +IF(J23="Yes",0.05,0) +IF(K23="Yes",0.15,0) +IF(L23="Yes",0.3,0) -> 1 | E23: Yes | F23: Yes | G23: Yes | H23: Yes | I23: Yes | J23: Yes | K23: Yes | L23: Yes
A24: https://4ammedia.zendesk.com/agent/tickets/238482 | B24: 46224 | C24: =IF(B24="", "", TEXT(B24, "ddd")) -> Tue | D24: =IF(E24="Yes",0.05,0) +IF(F24="Yes",0.1,0) +IF(G24="Yes",0.15,0) +IF(H24="Yes",0.15,0) +IF(I24="Yes",0.05,0) +IF(J24="Yes",0.05,0) +IF(K24="Yes",0.15,0) +IF(L24="Yes",0.3,0) -> 1 | E24: Yes | F24: Yes | G24: Yes | H24: Yes | I24: Yes | J24: Yes | K24: Yes | L24: Yes
A25: https://4ammedia.zendesk.com/agent/tickets/238840 | B25: 46224 | C25: =IF(B25="", "", TEXT(B25, "ddd")) -> Tue | D25: =IF(E25="Yes",0.05,0) +IF(F25="Yes",0.1,0) +IF(G25="Yes",0.15,0) +IF(H25="Yes",0.15,0) +IF(I25="Yes",0.05,0) +IF(J25="Yes",0.05,0) +IF(K25="Yes",0.15,0) +IF(L25="Yes",0.3,0) -> 1 | E25: Yes | F25: Yes | G25: Yes | H25: Yes | I25: Yes | J25: Yes | K25: Yes | L25: Yes
A26: https://4ammedia.zendesk.com/agent/tickets/238931 | B26: 46224 | C26: =IF(B26="", "", TEXT(B26, "ddd")) -> Tue | D26: =IF(E26="Yes",0.05,0) +IF(F26="Yes",0.1,0) +IF(G26="Yes",0.15,0) +IF(H26="Yes",0.15,0) +IF(I26="Yes",0.05,0) +IF(J26="Yes",0.05,0) +IF(K26="Yes",0.15,0) +IF(L26="Yes",0.3,0) -> 1 | E26: Yes | F26: Yes | G26: Yes | H26: Yes | I26: Yes | J26: Yes | K26: Yes | L26: Yes
A27: https://4ammedia.zendesk.com/agent/tickets/243327 | B27: 46226 | C27: =IF(B27="", "", TEXT(B27, "ddd")) -> Thu | D27: =IF(E27="Yes",0.05,0) +IF(F27="Yes",0.1,0) +IF(G27="Yes",0.15,0) +IF(H27="Yes",0.15,0) +IF(I27="Yes",0.05,0) +IF(J27="Yes",0.05,0) +IF(K27="Yes",0.15,0) +IF(L27="Yes",0.3,0) -> 1 | E27: Yes | F27: Yes | G27: Yes | H27: Yes | I27: Yes | J27: Yes | K27: Yes | L27: Yes
A28: https://4ammedia.zendesk.com/agent/tickets/243512 | B28: 46226 | C28: =IF(B28="", "", TEXT(B28, "ddd")) -> Thu | D28: =IF(E28="Yes",0.05,0) +IF(F28="Yes",0.1,0) +IF(G28="Yes",0.15,0) +IF(H28="Yes",0.15,0) +IF(I28="Yes",0.05,0) +IF(J28="Yes",0.05,0) +IF(K28="Yes",0.15,0) +IF(L28="Yes",0.3,0) -> 1 | E28: Yes | F28: Yes | G28: Yes | H28: Yes | I28: Yes | J28: Yes | K28: Yes | L28: Yes
A29: https://4ammedia.zendesk.com/agent/tickets/243575 | B29: 46226 | C29: =IF(B29="", "", TEXT(B29, "ddd")) -> Thu | D29: =IF(E29="Yes",0.05,0) +IF(F29="Yes",0.1,0) +IF(G29="Yes",0.15,0) +IF(H29="Yes",0.15,0) +IF(I29="Yes",0.05,0) +IF(J29="Yes",0.05,0) +IF(K29="Yes",0.15,0) +IF(L29="Yes",0.3,0) -> 1 | E29: Yes | F29: Yes | G29: Yes | H29: Yes | I29: Yes | J29: Yes | K29: Yes | L29: Yes
A30: https://4ammedia.zendesk.com/agent/tickets/245259 | B30: 46227 | C30: =IF(B30="", "", TEXT(B30, "ddd")) -> Fri | D30: =IF(E30="Yes",0.05,0) +IF(F30="Yes",0.1,0) +IF(G30="Yes",0.15,0) +IF(H30="Yes",0.15,0) +IF(I30="Yes",0.05,0) +IF(J30="Yes",0.05,0) +IF(K30="Yes",0.15,0) +IF(L30="Yes",0.3,0) -> 1 | E30: Yes | F30: Yes | G30: Yes | H30: Yes | I30: Yes | J30: Yes | K30: Yes | L30: Yes
A31: https://4ammedia.zendesk.com/agent/tickets/245393 | B31: 46227 | C31: =IF(B31="", "", TEXT(B31, "ddd")) -> Fri | D31: =IF(E31="Yes",0.05,0) +IF(F31="Yes",0.1,0) +IF(G31="Yes",0.15,0) +IF(H31="Yes",0.15,0) +IF(I31="Yes",0.05,0) +IF(J31="Yes",0.05,0) +IF(K31="Yes",0.15,0) +IF(L31="Yes",0.3,0) -> 1 | E31: Yes | F31: Yes | G31: Yes | H31: Yes | I31: Yes | J31: Yes | K31: Yes | L31: Yes
A32: https://4ammedia.zendesk.com/agent/tickets/245522 | B32: 46227 | C32: =IF(B32="", "", TEXT(B32, "ddd")) -> Fri | D32: =IF(E32="Yes",0.05,0) +IF(F32="Yes",0.1,0) +IF(G32="Yes",0.15,0) +IF(H32="Yes",0.15,0) +IF(I32="Yes",0.05,0) +IF(J32="Yes",0.05,0) +IF(K32="Yes",0.15,0) +IF(L32="Yes",0.3,0) -> 1 | E32: Yes | F32: Yes | G32: Yes | H32: Yes | I32: Yes | J32: Yes | K32: Yes | L32: Yes
B33: 46228 | C33: =IF(B33="", "", TEXT(B33, "ddd")) -> Sat | D33: =IF(E33="Yes",0.05,0) +IF(F33="Yes",0.1,0) +IF(G33="Yes",0.15,0) +IF(H33="Yes",0.15,0) +IF(I33="Yes",0.05,0) +IF(J33="Yes",0.05,0) +IF(K33="Yes",0.15,0) +IF(L33="Yes",0.3,0) -> 0
B34: 46228 | C34: =IF(B34="", "", TEXT(B34, "ddd")) -> Sat | D34: =IF(E34="Yes",0.05,0) +IF(F34="Yes",0.1,0) +IF(G34="Yes",0.15,0) +IF(H34="Yes",0.15,0) +IF(I34="Yes",0.05,0) +IF(J34="Yes",0.05,0) +IF(K34="Yes",0.15,0) +IF(L34="Yes",0.3,0) -> 0
B35: 46228 | C35: =IF(B35="", "", TEXT(B35, "ddd")) -> Sat | D35: =IF(E35="Yes",0.05,0) +IF(F35="Yes",0.1,0) +IF(G35="Yes",0.15,0) +IF(H35="Yes",0.15,0) +IF(I35="Yes",0.05,0) +IF(J35="Yes",0.05,0) +IF(K35="Yes",0.15,0) +IF(L35="Yes",0.3,0) -> 0
C36: Final QA Score | D36: =AVERAGE(D21:D35) -> 0.8 | L36: Final QA Score | M36: =SUM(M21:M35)/75*0.1 -> 0
A37: Week (July 27, - Aug 2,2026)
A38: Ticket Link | B38: Date | C38: Day | D38: SCORE | E38: Notes and Tagging(internal Note and Sticky Note) 5% | F38: COURTESY & EMPATHY 15% | G38: TONE OF VOICE & ELOQUENCE 20% | H38: CALL CONTROL 15% | I38: VERIFICATION 5% | J38: PROBING 5% | K38: MASTERY OF INFORMATION 15% | L38: RESOLUTION 20% | M38: Average | N38: NOTES
A39: https://4ammedia.zendesk.com/agent/tickets/249958 | B39: 46230 | C39: =IF(B39="", "", TEXT(B39, "ddd")) -> Mon | D39: =IF(E39="Yes",0.05,0) +IF(F39="Yes",0.1,0) +IF(G39="Yes",0.15,0) +IF(H39="Yes",0.15,0) +IF(I39="Yes",0.05,0) +IF(J39="Yes",0.05,0) +IF(K39="Yes",0.15,0) +IF(L39="Yes",0.3,0) -> 1 | E39: Yes | F39: Yes | G39: Yes | H39: Yes | I39: Yes | J39: Yes | K39: Yes | L39: Yes
A40: https://4ammedia.zendesk.com/agent/tickets/250188 | B40: 46230 | C40: =IF(B40="", "", TEXT(B40, "ddd")) -> Mon | D40: =IF(E40="Yes",0.05,0) +IF(F40="Yes",0.1,0) +IF(G40="Yes",0.15,0) +IF(H40="Yes",0.15,0) +IF(I40="Yes",0.05,0) +IF(J40="Yes",0.05,0) +IF(K40="Yes",0.15,0) +IF(L40="Yes",0.3,0) -> 1 | E40: Yes | F40: Yes | G40: Yes | H40: Yes | I40: Yes | J40: Yes | K40: Yes | L40: Yes
A41: https://4ammedia.zendesk.com/agent/tickets/250486 | B41: 46230 | C41: =IF(B41="", "", TEXT(B41, "ddd")) -> Mon | D41: =IF(E41="Yes",0.05,0) +IF(F41="Yes",0.1,0) +IF(G41="Yes",0.15,0) +IF(H41="Yes",0.15,0) +IF(I41="Yes",0.05,0) +IF(J41="Yes",0.05,0) +IF(K41="Yes",0.15,0) +IF(L41="Yes",0.3,0) -> 1 | E41: Yes | F41: Yes | G41: Yes | H41: Yes | I41: Yes | J41: Yes | K41: Yes | L41: Yes
A42: https://4ammedia.zendesk.com/agent/tickets/251635 | B42: 46231 | C42: =IF(B42="", "", TEXT(B42, "ddd")) -> Tue | D42: =IF(E42="Yes",0.05,0) +IF(F42="Yes",0.1,0) +IF(G42="Yes",0.15,0) +IF(H42="Yes",0.15,0) +IF(I42="Yes",0.05,0) +IF(J42="Yes",0.05,0) +IF(K42="Yes",0.15,0) +IF(L42="Yes",0.3,0) -> 1 | E42: Yes | F42: Yes | G42: Yes | H42: Yes | I42: Yes | J42: Yes | K42: Yes | L42: Yes
A43: https://4ammedia.zendesk.com/agent/tickets/251778 | B43: 46231 | C43: =IF(B43="", "", TEXT(B43, "ddd")) -> Tue | D43: =IF(E43="Yes",0.05,0) +IF(F43="Yes",0.1,0) +IF(G43="Yes",0.15,0) +IF(H43="Yes",0.15,0) +IF(I43="Yes",0.05,0) +IF(J43="Yes",0.05,0) +IF(K43="Yes",0.15,0) +IF(L43="Yes",0.3,0) -> 1 | E43: Yes | F43: Yes | G43: Yes | H43: Yes | I43: Yes | J43: Yes | K43: Yes | L43: Yes
A44: https://4ammedia.zendesk.com/agent/tickets/251811 | B44: 46231 | C44: =IF(B44="", "", TEXT(B44, "ddd")) -> Tue | D44: =IF(E44="Yes",0.05,0) +IF(F44="Yes",0.1,0) +IF(G44="Yes",0.15,0) +IF(H44="Yes",0.15,0) +IF(I44="Yes",0.05,0) +IF(J44="Yes",0.05,0) +IF(K44="Yes",0.15,0) +IF(L44="Yes",0.3,0) -> 1 | E44: Yes | F44: Yes | G44: Yes | H44: Yes | I44: Yes | J44: Yes | K44: Yes | L44: Yes
A45: https://4ammedia.zendesk.com/agent/tickets/256053 | B45: 46233 | C45: =IF(B45="", "", TEXT(B45, "ddd")) -> Thu | D45: =IF(E45="Yes",0.05,0) +IF(F45="Yes",0.1,0) +IF(G45="Yes",0.15,0) +IF(H45="Yes",0.15,0) +IF(I45="Yes",0.05,0) +IF(J45="Yes",0.05,0) +IF(K45="Yes",0.15,0) +IF(L45="Yes",0.3,0) -> 1 | E45: Yes | F45: Yes | G45: Yes | H45: Yes | I45: Yes | J45: Yes | K45: Yes | L45: Yes
A46: https://4ammedia.zendesk.com/agent/tickets/256357 | B46: 46233 | C46: =IF(B46="", "", TEXT(B46, "ddd")) -> Thu | D46: =IF(E46="Yes",0.05,0) +IF(F46="Yes",0.1,0) +IF(G46="Yes",0.15,0) +IF(H46="Yes",0.15,0) +IF(I46="Yes",0.05,0) +IF(J46="Yes",0.05,0) +IF(K46="Yes",0.15,0) +IF(L46="Yes",0.3,0) -> 1 | E46: Yes | F46: Yes | G46: Yes | H46: Yes | I46: Yes | J46: Yes | K46: Yes | L46: Yes
A47: https://4ammedia.zendesk.com/agent/tickets/256430 | B47: 46233 | C47: =IF(B47="", "", TEXT(B47, "ddd")) -> Thu | D47: =IF(E47="Yes",0.05,0) +IF(F47="Yes",0.1,0) +IF(G47="Yes",0.15,0) +IF(H47="Yes",0.15,0) +IF(I47="Yes",0.05,0) +IF(J47="Yes",0.05,0) +IF(K47="Yes",0.15,0) +IF(L47="Yes",0.3,0) -> 1 | E47: Yes | F47: Yes | G47: Yes | H47: Yes | I47: Yes | J47: Yes | K47: Yes | L47: Yes
A48: https://4ammedia.zendesk.com/agent/tickets/258177 | B48: 46234 | C48: =IF(B48="", "", TEXT(B48, "ddd")) -> Fri | D48: =IF(E48="Yes",0.05,0) +IF(F48="Yes",0.1,0) +IF(G48="Yes",0.15,0) +IF(H48="Yes",0.15,0) +IF(I48="Yes",0.05,0) +IF(J48="Yes",0.05,0) +IF(K48="Yes",0.15,0) +IF(L48="Yes",0.3,0) -> 1 | E48: Yes | F48: Yes | G48: Yes | H48: Yes | I48: Yes | J48: Yes | K48: Yes | L48: Yes
A49: https://4ammedia.zendesk.com/agent/tickets/258315 | B49: 46234 | C49: =IF(B49="", "", TEXT(B49, "ddd")) -> Fri | D49: =IF(E49="Yes",0.05,0) +IF(F49="Yes",0.1,0) +IF(G49="Yes",0.15,0) +IF(H49="Yes",0.15,0) +IF(I49="Yes",0.05,0) +IF(J49="Yes",0.05,0) +IF(K49="Yes",0.15,0) +IF(L49="Yes",0.3,0) -> 1 | E49: Yes | F49: Yes | G49: Yes | H49: Yes | I49: Yes | J49: Yes | K49: Yes | L49: Yes
A50: https://4ammedia.zendesk.com/agent/tickets/258549 | B50: 46234 | C50: =IF(B50="", "", TEXT(B50, "ddd")) -> Fri | D50: =IF(E50="Yes",0.05,0) +IF(F50="Yes",0.1,0) +IF(G50="Yes",0.15,0) +IF(H50="Yes",0.15,0) +IF(I50="Yes",0.05,0) +IF(J50="Yes",0.05,0) +IF(K50="Yes",0.15,0) +IF(L50="Yes",0.3,0) -> 1 | E50: Yes | F50: Yes | G50: Yes | H50: Yes | I50: Yes | J50: Yes | K50: Yes | L50: Yes
... A53: https://4ammedia.zendesk.com/agent/tickets/259666 | B53: 46235 | C53: =IF(B53="", "", TEXT(B53, "ddd")) -> Sat | D53: =IF(E53="Yes",0.05,0) +IF(F53="Yes",0.1,0) +IF(G53="Yes",0.15,0) +IF(H53="Yes",0.15,0) +IF(I53="Yes",0.05,0) +IF(J53="Yes",0.05,0) +IF(K53="Yes",0.15,0) +IF(L53="Yes",0.3,0) -> 1 | E53: Yes | F53: Yes | G53: Yes | H53: Yes | I53: Yes | J53: Yes | K53: Yes | L53: Yes
C54: Final QA Score | D54: =AVERAGE(D39:D53) -> 1 | L54: Final QA Score | M54: =SUM(M39:M53)/75*0.1 -> 0
A55: Week (Aug 3, - Aug 9,2026)
A56: Ticket Link | B56: Date | C56: Day | D56: SCORE | E56: Notes and Tagging(internal Note and Sticky Note) 5% | F56: COURTESY & EMPATHY 15% | G56: TONE OF VOICE & ELOQUENCE 20% | H56: CALL CONTROL 15% | I56: VERIFICATION 5% | J56: PROBING 5% | K56: MASTERY OF INFORMATION 15% | L56: RESOLUTION 20% | M56: Average | N56: NOTES
A57: https://4ammedia.zendesk.com/agent/tickets/262621 | B57: 46237 | C57: =IF(B57="", "", TEXT(B57, "ddd")) -> Mon | D57: =IF(E57="Yes",0.05,0) +IF(F57="Yes",0.1,0) +IF(G57="Yes",0.15,0) +IF(H57="Yes",0.15,0) +IF(I57="Yes",0.05,0) +IF(J57="Yes",0.05,0) +IF(K57="Yes",0.15,0) +IF(L57="Yes",0.3,0) -> 1 | E57: Yes | F57: Yes | G57: Yes | H57: Yes | I57: Yes | J57: Yes | K57: Yes | L57: Yes
A58: https://4ammedia.zendesk.com/agent/tickets/263090 | B58: 46237 | C58: =IF(B58="", "", TEXT(B58, "ddd")) -> Mon | D58: =IF(E58="Yes",0.05,0) +IF(F58="Yes",0.1,0) +IF(G58="Yes",0.15,0) +IF(H58="Yes",0.15,0) +IF(I58="Yes",0.05,0) +IF(J58="Yes",0.05,0) +IF(K58="Yes",0.15,0) +IF(L58="Yes",0.3,0) -> 1 | E58: Yes | F58: Yes | G58: Yes | H58: Yes | I58: Yes | J58: Yes | K58: Yes | L58: Yes
A59: https://4ammedia.zendesk.com/agent/tickets/263327 | B59: 46237 | C59: =IF(B59="", "", TEXT(B59, "ddd")) -> Mon | D59: =IF(E59="Yes",0.05,0) +IF(F59="Yes",0.1,0) +IF(G59="Yes",0.15,0) +IF(H59="Yes",0.15,0) +IF(I59="Yes",0.05,0) +IF(J59="Yes",0.05,0) +IF(K59="Yes",0.15,0) +IF(L59="Yes",0.3,0) -> 1 | E59: Yes | F59: Yes | G59: Yes | H59: Yes | I59: Yes | J59: Yes | K59: Yes | L59: Yes
A60: https://4ammedia.zendesk.com/agent/tickets/265709 | B60: 46238 | C60: =IF(B60="", "", TEXT(B60, "ddd")) -> Tue | D60: =IF(E60="Yes",0.05,0) +IF(F60="Yes",0.1,0) +IF(G60="Yes",0.15,0) +IF(H60="Yes",0.15,0) +IF(I60="Yes",0.05,0) +IF(J60="Yes",0.05,0) +IF(K60="Yes",0.15,0) +IF(L60="Yes",0.3,0) -> 1 | E60: Yes | F60: Yes | G60: Yes | H60: Yes | I60: Yes | J60: Yes | K60: Yes | L60: Yes
A61: https://4ammedia.zendesk.com/agent/tickets/266101 | B61: 46238 | C61: =IF(B61="", "", TEXT(B61, "ddd")) -> Tue | D61: =IF(E61="Yes",0.05,0) +IF(F61="Yes",0.1,0) +IF(G61="Yes",0.15,0) +IF(H61="Yes",0.15,0) +IF(I61="Yes",0.05,0) +IF(J61="Yes",0.05,0) +IF(K61="Yes",0.15,0) +IF(L61="Yes",0.3,0) -> 1 | E61: Yes | F61: Yes | G61: Yes | H61: Yes | I61: Yes | J61: Yes | K61: Yes | L61: Yes
A62: https://4ammedia.zendesk.com/agent/tickets/266324 | B62: 46238 | C62: =IF(B62="", "", TEXT(B62, "ddd")) -> Tue | D62: =IF(E62="Yes",0.05,0) +IF(F62="Yes",0.1,0) +IF(G62="Yes",0.15,0) +IF(H62="Yes",0.15,0) +IF(I62="Yes",0.05,0) +IF(J62="Yes",0.05,0) +IF(K62="Yes",0.15,0) +IF(L62="Yes",0.3,0) -> 1 | E62: Yes | F62: Yes | G62: Yes | H62: Yes | I62: Yes | J62: Yes | K62: Yes | L62: Yes
A63: https://4ammedia.zendesk.com/agent/tickets/269106 | B63: 46240 | C63: =IF(B63="", "", TEXT(B63, "ddd")) -> Thu | D63: =IF(E63="Yes",0.05,0) +IF(F63="Yes",0.1,0) +IF(G63="Yes",0.15,0) +IF(H63="Yes",0.15,0) +IF(I63="Yes",0.05,0) +IF(J63="Yes",0.05,0) +IF(K63="Yes",0.15,0) +IF(L63="Yes",0.3,0) -> 1 | E63: Yes | F63: Yes | G63: Yes | H63: Yes | I63: Yes | J63: Yes | K63: Yes | L63: Yes
A64: https://4ammedia.zendesk.com/agent/tickets/269318 | B64: 46240 | C64: =IF(B64="", "", TEXT(B64, "ddd")) -> Thu | D64: =IF(E64="Yes",0.05,0) +IF(F64="Yes",0.1,0) +IF(G64="Yes",0.15,0) +IF(H64="Yes",0.15,0) +IF(I64="Yes",0.05,0) +IF(J64="Yes",0.05,0) +IF(K64="Yes",0.15,0) +IF(L64="Yes",0.3,0) -> 1 | E64: Yes | F64: Yes | G64: Yes | H64: Yes | I64: Yes | J64: Yes | K64: Yes | L64: Yes
A65: https://4ammedia.zendesk.com/agent/tickets/269390 | B65: 46240 | C65: =IF(B65="", "", TEXT(B65, "ddd")) -> Thu | D65: =IF(E65="Yes",0.05,0) +IF(F65="Yes",0.1,0) +IF(G65="Yes",0.15,0) +IF(H65="Yes",0.15,0) +IF(I65="Yes",0.05,0) +IF(J65="Yes",0.05,0) +IF(K65="Yes",0.15,0) +IF(L65="Yes",0.3,0) -> 1 | E65: Yes | F65: Yes | G65: Yes | H65: Yes | I65: Yes | J65: Yes | K65: Yes | L65: Yes
A66: https://4ammedia.zendesk.com/agent/tickets/271300 | B66: 46241 | C66: =IF(B66="", "", TEXT(B66, "ddd")) -> Fri | D66: =IF(E66="Yes",0.05,0) +IF(F66="Yes",0.1,0) +IF(G66="Yes",0.15,0) +IF(H66="Yes",0.15,0) +IF(I66="Yes",0.05,0) +IF(J66="Yes",0.05,0) +IF(K66="Yes",0.15,0) +IF(L66="Yes",0.3,0) -> 1 | E66: Yes | F66: Yes | G66: Yes | H66: Yes | I66: Yes | J66: Yes | K66: Yes | L66: Yes
A67: https://4ammedia.zendesk.com/agent/tickets/271439 | B67: 46241 | C67: =IF(B67="", "", TEXT(B67, "ddd")) -> Fri | D67: =IF(E67="Yes",0.05,0) +IF(F67="Yes",0.1,0) +IF(G67="Yes",0.15,0) +IF(H67="Yes",0.15,0) +IF(I67="Yes",0.05,0) +IF(J67="Yes",0.05,0) +IF(K67="Yes",0.15,0) +IF(L67="Yes",0.3,0) -> 1 | E67: Yes | F67: Yes | G67: Yes | H67: Yes | I67: Yes | J67: Yes | K67: Yes | L67: Yes
A68: https://4ammedia.zendesk.com/agent/tickets/271410 | B68: 46241 | C68: =IF(B68="", "", TEXT(B68, "ddd")) -> Fri | D68: =IF(E68="Yes",0.05,0) +IF(F68="Yes",0.1,0) +IF(G68="Yes",0.15,0) +IF(H68="Yes",0.15,0) +IF(I68="Yes",0.05,0) +IF(J68="Yes",0.05,0) +IF(K68="Yes",0.15,0) +IF(L68="Yes",0.3,0) -> 1 | E68: Yes | F68: Yes | G68: Yes | H68: Yes | I68: Yes | J68: Yes | K68: Yes | L68: Yes
... A71: https://4ammedia.zendesk.com/agent/tickets/273268 | B71: 46242 | C71: =IF(B71="", "", TEXT(B71, "ddd")) -> Sat | D71: =IF(E71="Yes",0.05,0) +IF(F71="Yes",0.1,0) +IF(G71="Yes",0.15,0) +IF(H71="Yes",0.15,0) +IF(I71="Yes",0.05,0) +IF(J71="Yes",0.05,0) +IF(K71="Yes",0.15,0) +IF(L71="Yes",0.3,0) -> 1 | E71: Yes | F71: Yes | G71: Yes | H71: Yes | I71: Yes | J71: Yes | K71: Yes | L71: Yes
C72: Final QA Score | D72: =AVERAGE(D57:D71) -> 1 | L72: Final QA Score | M72: =SUM(M57:M71)/75*0.1 -> 0
A73: Week (Aug 10, - Aug 16,2026)
A74: Ticket Link | B74: Date | C74: Day | D74: SCORE | E74: Notes and Tagging(internal Note and Sticky Note) 5% | F74: COURTESY & EMPATHY 15% | G74: TONE OF VOICE & ELOQUENCE 20% | H74: CALL CONTROL 15% | I74: VERIFICATION 5% | J74: PROBING 5% | K74: MASTERY OF INFORMATION 15% | L74: RESOLUTION 20% | M74: Average | N74: NOTES
A75: https://4ammedia.zendesk.com/agent/tickets/275986 | B75: 46244 | C75: =IF(B75="", "", TEXT(B75, "ddd")) -> Mon | D75: =IF(E75="Yes",0.05,0) +IF(F75="Yes",0.1,0) +IF(G75="Yes",0.15,0) +IF(H75="Yes",0.15,0) +IF(I75="Yes",0.05,0) +IF(J75="Yes",0.05,0) +IF(K75="Yes",0.15,0) +IF(L75="Yes",0.3,0) -> 1 | E75: Yes | F75: Yes | G75: Yes | H75: Yes | I75: Yes | J75: Yes | K75: Yes | L75: Yes
A76: https://4ammedia.zendesk.com/agent/tickets/276332 | B76: 46244 | C76: =IF(B76="", "", TEXT(B76, "ddd")) -> Mon | D76: =IF(E76="Yes",0.05,0) +IF(F76="Yes",0.1,0) +IF(G76="Yes",0.15,0) +IF(H76="Yes",0.15,0) +IF(I76="Yes",0.05,0) +IF(J76="Yes",0.05,0) +IF(K76="Yes",0.15,0) +IF(L76="Yes",0.3,0) -> 1 | E76: Yes | F76: Yes | G76: Yes | H76: Yes | I76: Yes | J76: Yes | K76: Yes | L76: Yes
A77: https://4ammedia.zendesk.com/agent/tickets/276747 | B77: 46244 | C77: =IF(B77="", "", TEXT(B77, "ddd")) -> Mon | D77: =IF(E77="Yes",0.05,0) +IF(F77="Yes",0.1,0) +IF(G77="Yes",0.15,0) +IF(H77="Yes",0.15,0) +IF(I77="Yes",0.05,0) +IF(J77="Yes",0.05,0) +IF(K77="Yes",0.15,0) +IF(L77="Yes",0.3,0) -> 1 | E77: Yes | F77: Yes | G77: Yes | H77: Yes | I77: Yes | J77: Yes | K77: Yes | L77: Yes
A78: https://4ammedia.zendesk.com/agent/tickets/278402 | B78: 46245 | C78: =IF(B78="", "", TEXT(B78, "ddd")) -> Tue | D78: =IF(E78="Yes",0.05,0) +IF(F78="Yes",0.1,0) +IF(G78="Yes",0.15,0) +IF(H78="Yes",0.15,0) +IF(I78="Yes",0.05,0) +IF(J78="Yes",0.05,0) +IF(K78="Yes",0.15,0) +IF(L78="Yes",0.3,0) -> 1 | E78: Yes | F78: Yes | G78: Yes | H78: Yes | I78: Yes | J78: Yes | K78: Yes | L78: Yes
A79: https://4ammedia.zendesk.com/agent/tickets/278597 | B79: 46245 | C79: =IF(B79="", "", TEXT(B79, "ddd")) -> Tue | D79: =IF(E79="Yes",0.05,0) +IF(F79="Yes",0.1,0) +IF(G79="Yes",0.15,0) +IF(H79="Yes",0.15,0) +IF(I79="Yes",0.05,0) +IF(J79="Yes",0.05,0) +IF(K79="Yes",0.15,0) +IF(L79="Yes",0.3,0) -> 1 | E79: Yes | F79: Yes | G79: Yes | H79: Yes | I79: Yes | J79: Yes | K79: Yes | L79: Yes
A80: https://4ammedia.zendesk.com/agent/tickets/278961 | B80: 46245 | C80: =IF(B80="", "", TEXT(B80, "ddd")) -> Tue | D80: =IF(E80="Yes",0.05,0) +IF(F80="Yes",0.1,0) +IF(G80="Yes",0.15,0) +IF(H80="Yes",0.15,0) +IF(I80="Yes",0.05,0) +IF(J80="Yes",0.05,0) +IF(K80="Yes",0.15,0) +IF(L80="Yes",0.3,0) -> 1 | E80: Yes | F80: Yes | G80: Yes | H80: Yes | I80: Yes | J80: Yes | K80: Yes | L80: Yes
A81: https://4ammedia.zendesk.com/agent/tickets/281910 | B81: 46247 | C81: =IF(B81="", "", TEXT(B81, "ddd")) -> Thu | D81: =IF(E81="Yes",0.05,0) +IF(F81="Yes",0.1,0) +IF(G81="Yes",0.15,0) +IF(H81="Yes",0.15,0) +IF(I81="Yes",0.05,0) +IF(J81="Yes",0.05,0) +IF(K81="Yes",0.15,0) +IF(L81="Yes",0.3,0) -> 1 | E81: Yes | F81: Yes | G81: Yes | H81: Yes | I81: Yes | J81: Yes | K81: Yes | L81: Yes
A82: https://4ammedia.zendesk.com/agent/tickets/282437 | B82: 46247 | C82: =IF(B82="", "", TEXT(B82, "ddd")) -> Thu | D82: =IF(E82="Yes",0.05,0) +IF(F82="Yes",0.1,0) +IF(G82="Yes",0.15,0) +IF(H82="Yes",0.15,0) +IF(I82="Yes",0.05,0) +IF(J82="Yes",0.05,0) +IF(K82="Yes",0.15,0) +IF(L82="Yes",0.3,0) -> 1 | E82: Yes | F82: Yes | G82: Yes | H82: Yes | I82: Yes | J82: Yes | K82: Yes | L82: Yes
A83: https://4ammedia.zendesk.com/agent/tickets/282520 | B83: 46247 | C83: =IF(B83="", "", TEXT(B83, "ddd")) -> Thu | D83: =IF(E83="Yes",0.05,0) +IF(F83="Yes",0.1,0) +IF(G83="Yes",0.15,0) +IF(H83="Yes",0.15,0) +IF(I83="Yes",0.05,0) +IF(J83="Yes",0.05,0) +IF(K83="Yes",0.15,0) +IF(L83="Yes",0.3,0) -> 1 | E83: Yes | F83: Yes | G83: Yes | H83: Yes | I83: Yes | J83: Yes | K83: Yes | L83: Yes
A84: https://4ammedia.zendesk.com/agent/tickets/284451 | B84: 46248 | C84: =IF(B84="", "", TEXT(B84, "ddd")) -> Fri | D84: =IF(E84="Yes",0.05,0) +IF(F84="Yes",0.1,0) +IF(G84="Yes",0.15,0) +IF(H84="Yes",0.15,0) +IF(I84="Yes",0.05,0) +IF(J84="Yes",0.05,0) +IF(K84="Yes",0.15,0) +IF(L84="Yes",0.3,0) -> 1 | E84: Yes | F84: Yes | G84: Yes | H84: Yes | I84: Yes | J84: Yes | K84: Yes | L84: Yes
A85: https://4ammedia.zendesk.com/agent/tickets/284724 | B85: 46248 | C85: =IF(B85="", "", TEXT(B85, "ddd")) -> Fri | D85: =IF(E85="Yes",0.05,0) +IF(F85="Yes",0.1,0) +IF(G85="Yes",0.15,0) +IF(H85="Yes",0.15,0) +IF(I85="Yes",0.05,0) +IF(J85="Yes",0.05,0) +IF(K85="Yes",0.15,0) +IF(L85="Yes",0.3,0) -> 1 | E85: Yes | F85: Yes | G85: Yes | H85: Yes | I85: Yes | J85: Yes | K85: Yes | L85: Yes
A86: https://4ammedia.zendesk.com/agent/tickets/284785 | B86: 46248 | C86: =IF(B86="", "", TEXT(B86, "ddd")) -> Fri | D86: =IF(E86="Yes",0.05,0) +IF(F86="Yes",0.1,0) +IF(G86="Yes",0.15,0) +IF(H86="Yes",0.15,0) +IF(I86="Yes",0.05,0) +IF(J86="Yes",0.05,0) +IF(K86="Yes",0.15,0) +IF(L86="Yes",0.3,0) -> 1 | E86: Yes | F86: Yes | G86: Yes | H86: Yes | I86: Yes | J86: Yes | K86: Yes | L86: Yes
... A89: https://4ammedia.zendesk.com/agent/tickets/286316 | B89: 46249 | C89: =IF(B89="", "", TEXT(B89, "ddd")) -> Sat | D89: =IF(E89="Yes",0.05,0) +IF(F89="Yes",0.1,0) +IF(G89="Yes",0.15,0) +IF(H89="Yes",0.15,0) +IF(I89="Yes",0.05,0) +IF(J89="Yes",0.05,0) +IF(K89="Yes",0.15,0) +IF(L89="Yes",0.3,0) -> 1 | E89: Yes | F89: Yes | G89: Yes | H89: Yes | I89: Yes | J89: Yes | K89: Yes | L89: Yes
C90: Final QA Score | D90: =AVERAGE(D75:D89) -> 1 | L90: Final QA Score | M90: =SUM(M75:M89)/75*0.1 -> 0
A91: Week (Aug 17, - Aug 23,2026)
A92: Ticket Link | B92: Date | C92: Day | D92: SCORE | E92: Notes and Tagging(internal Note and Sticky Note) 5% | F92: COURTESY & EMPATHY 15% | G92: TONE OF VOICE & ELOQUENCE 20% | H92: CALL CONTROL 15% | I92: VERIFICATION 5% | J92: PROBING 5% | K92: MASTERY OF INFORMATION 15% | L92: RESOLUTION 20% | M92: Average | N92: NOTES
A93: https://4ammedia.zendesk.com/agent/tickets/288606 | B93: 46251 | C93: =IF(B93="", "", TEXT(B93, "ddd")) -> Mon | D93: =IF(E93="Yes",0.05,0) +IF(F93="Yes",0.1,0) +IF(G93="Yes",0.15,0) +IF(H93="Yes",0.15,0) +IF(I93="Yes",0.05,0) +IF(J93="Yes",0.05,0) +IF(K93="Yes",0.15,0) +IF(L93="Yes",0.3,0) -> 1 | E93: Yes | F93: Yes | G93: Yes | H93: Yes | I93: Yes | J93: Yes | K93: Yes | L93: Yes
A94: https://4ammedia.zendesk.com/agent/tickets/288757 | B94: 46251 | C94: =IF(B94="", "", TEXT(B94, "ddd")) -> Mon | D94: =IF(E94="Yes",0.05,0) +IF(F94="Yes",0.1,0) +IF(G94="Yes",0.15,0) +IF(H94="Yes",0.15,0) +IF(I94="Yes",0.05,0) +IF(J94="Yes",0.05,0) +IF(K94="Yes",0.15,0) +IF(L94="Yes",0.3,0) -> 1 | E94: Yes | F94: Yes | G94: Yes | H94: Yes | I94: Yes | J94: Yes | K94: Yes | L94: Yes
A95: https://4ammedia.zendesk.com/agent/tickets/288807 | B95: 46251 | C95: =IF(B95="", "", TEXT(B95, "ddd")) -> Mon | D95: =IF(E95="Yes",0.05,0) +IF(F95="Yes",0.1,0) +IF(G95="Yes",0.15,0) +IF(H95="Yes",0.15,0) +IF(I95="Yes",0.05,0) +IF(J95="Yes",0.05,0) +IF(K95="Yes",0.15,0) +IF(L95="Yes",0.3,0) -> 1 | E95: Yes | F95: Yes | G95: Yes | H95: Yes | I95: Yes | J95: Yes | K95: Yes | L95: Yes
A96: https://4ammedia.zendesk.com/agent/tickets/291489 | B96: 46252 | C96: =IF(B96="", "", TEXT(B96, "ddd")) -> Tue | D96: =IF(E96="Yes",0.05,0) +IF(F96="Yes",0.1,0) +IF(G96="Yes",0.15,0) +IF(H96="Yes",0.15,0) +IF(I96="Yes",0.05,0) +IF(J96="Yes",0.05,0) +IF(K96="Yes",0.15,0) +IF(L96="Yes",0.3,0) -> 1 | E96: Yes | F96: Yes | G96: Yes | H96: Yes | I96: Yes | J96: Yes | K96: Yes | L96: Yes
A97: https://4ammedia.zendesk.com/agent/tickets/291719 | B97: 46252 | C97: =IF(B97="", "", TEXT(B97, "ddd")) -> Tue | D97: =IF(E97="Yes",0.05,0) +IF(F97="Yes",0.1,0) +IF(G97="Yes",0.15,0) +IF(H97="Yes",0.15,0) +IF(I97="Yes",0.05,0) +IF(J97="Yes",0.05,0) +IF(K97="Yes",0.15,0) +IF(L97="Yes",0.3,0) -> 1 | E97: Yes | F97: Yes | G97: Yes | H97: Yes | I97: Yes | J97: Yes | K97: Yes | L97: Yes
A98: https://4ammedia.zendesk.com/agent/tickets/291814 | B98: 46252 | C98: =IF(B98="", "", TEXT(B98, "ddd")) -> Tue | D98: =IF(E98="Yes",0.05,0) +IF(F98="Yes",0.1,0) +IF(G98="Yes",0.15,0) +IF(H98="Yes",0.15,0) +IF(I98="Yes",0.05,0) +IF(J98="Yes",0.05,0) +IF(K98="Yes",0.15,0) +IF(L98="Yes",0.3,0) -> 1 | E98: Yes | F98: Yes | G98: Yes | H98: Yes | I98: Yes | J98: Yes | K98: Yes | L98: Yes
A99: https://4ammedia.zendesk.com/agent/tickets/295275 | B99: 46254 | C99: =IF(B99="", "", TEXT(B99, "ddd")) -> Thu | D99: =IF(E99="Yes",0.05,0) +IF(F99="Yes",0.1,0) +IF(G99="Yes",0.15,0) +IF(H99="Yes",0.15,0) +IF(I99="Yes",0.05,0) +IF(J99="Yes",0.05,0) +IF(K99="Yes",0.15,0) +IF(L99="Yes",0.3,0) -> 1 | E99: Yes | F99: Yes | G99: Yes | H99: Yes | I99: Yes | J99: Yes | K99: Yes | L99: Yes
A100: https://4ammedia.zendesk.com/agent/tickets/295543 | B100: 46254 | C100: =IF(B100="", "", TEXT(B100, "ddd")) -> Thu | D100: =IF(E100="Yes",0.05,0) +IF(F100="Yes",0.1,0) +IF(G100="Yes",0.15,0) +IF(H100="Yes",0.15,0) +IF(I100="Yes",0.05,0) +IF(J100="Yes",0.05,0) +IF(K100="Yes",0.15,0) +IF(L100="Yes",0.3,0) -> 1 | E100: Yes | F100: Yes | G100: Yes | H100: Yes | I100: Yes | J100: Yes | K100: Yes | L100: Yes
A101: https://4ammedia.zendesk.com/agent/tickets/295746 | B101: 46254 | C101: =IF(B101="", "", TEXT(B101, "ddd")) -> Thu | D101: =IF(E101="Yes",0.05,0) +IF(F101="Yes",0.1,0) +IF(G101="Yes",0.15,0) +IF(H101="Yes",0.15,0) +IF(I101="Yes",0.05,0) +IF(J101="Yes",0.05,0) +IF(K101="Yes",0.15,0) +IF(L101="Yes",0.3,0) -> 1 | E101: Yes | F101: Yes | G101: Yes | H101: Yes | I101: Yes | J101: Yes | K101: Yes | L101: Yes
A102: https://4ammedia.zendesk.com/agent/tickets/297139 | B102: 46255 | C102: =IF(B102="", "", TEXT(B102, "ddd")) -> Fri | D102: =IF(E102="Yes",0.05,0) +IF(F102="Yes",0.1,0) +IF(G102="Yes",0.15,0) +IF(H102="Yes",0.15,0) +IF(I102="Yes",0.05,0) +IF(J102="Yes",0.05,0) +IF(K102="Yes",0.15,0) +IF(L102="Yes",0.3,0) -> 1 | E102: Yes | F102: Yes | G102: Yes | H102: Yes | I102: Yes | J102: Yes | K102: Yes | L102: Yes
A103: https://4ammedia.zendesk.com/agent/tickets/297362 | B103: 46255 | C103: =IF(B103="", "", TEXT(B103, "ddd")) -> Fri | D103: =IF(E103="Yes",0.05,0) +IF(F103="Yes",0.1,0) +IF(G103="Yes",0.15,0) +IF(H103="Yes",0.15,0) +IF(I103="Yes",0.05,0) +IF(J103="Yes",0.05,0) +IF(K103="Yes",0.15,0) +IF(L103="Yes",0.3,0) -> 1 | E103: Yes | F103: Yes | G103: Yes | H103: Yes | I103: Yes | J103: Yes | K103: Yes | L103: Yes
A104: https://4ammedia.zendesk.com/agent/tickets/297739 | B104: 46255 | C104: =IF(B104="", "", TEXT(B104, "ddd")) -> Fri | D104: =IF(E104="Yes",0.05,0) +IF(F104="Yes",0.1,0) +IF(G104="Yes",0.15,0) +IF(H104="Yes",0.15,0) +IF(I104="Yes",0.05,0) +IF(J104="Yes",0.05,0) +IF(K104="Yes",0.15,0) +IF(L104="Yes",0.3,0) -> 1 | E104: Yes | F104: Yes | G104: Yes | H104: Yes | I104: Yes | J104: Yes | K104: Yes | L104: Yes
... A107: https://4ammedia.zendesk.com/agent/tickets/299131 | B107: 46256 | C107: =IF(B107="", "", TEXT(B107, "ddd")) -> Sat | D107: =IF(E107="Yes",0.05,0) +IF(F107="Yes",0.1,0) +IF(G107="Yes",0.15,0) +IF(H107="Yes",0.15,0) +IF(I107="Yes",0.05,0) +IF(J107="Yes",0.05,0) +IF(K107="Yes",0.15,0) +IF(L107="Yes",0.3,0) -> 1 | E107: Yes | F107: Yes | G107: Yes | H107: Yes | I107: Yes | J107: Yes | K107: Yes | L107: Yes
C108: Final QA Score | D108: =AVERAGE(D93:D107) -> 1 | L108: Final QA Score | M108: =SUM(M93:M107)/75*0.1 -> 0
...

Sheet Claudette
A1: Week (July 20, - July 26,2026)
A2: Ticket Link | B2: Date | C2: Day | D2: SCORE | E2: Notes and Tagging(internal Note and Sticky Note) 5% | F2: COURTESY & EMPATHY 15% | G2: TONE OF VOICE & ELOQUENCE 20% | H2: CALL CONTROL 15% | I2: VERIFICATION 5% | J2: PROBING 5% | K2: MASTERY OF INFORMATION 15% | L2: RESOLUTION 20% | M2: Average | N2: NOTES
A3: https://4ammedia.zendesk.com/agent/tickets/236913 | B3: 46223 | C3: =IF(B3="", "", TEXT(B3, "ddd")) -> Mon | D3: =IF(E3="Yes",0.05,0) +IF(F3="Yes",0.1,0) +IF(G3="Yes",0.15,0) +IF(H3="Yes",0.15,0) +IF(I3="Yes",0.05,0) +IF(J3="Yes",0.05,0) +IF(K3="Yes",0.15,0) +IF(L3="Yes",0.3,0) -> 1 | E3: Yes | F3: Yes | G3: Yes | H3: Yes | I3: Yes | J3: Yes | K3: Yes | L3: Yes
A4: https://4ammedia.zendesk.com/agent/tickets/236968 | B4: 46223 | C4: =IF(B4="", "", TEXT(B4, "ddd")) -> Mon | D4: =IF(E4="Yes",0.05,0) +IF(F4="Yes",0.1,0) +IF(G4="Yes",0.15,0) +IF(H4="Yes",0.15,0) +IF(I4="Yes",0.05,0) +IF(J4="Yes",0.05,0) +IF(K4="Yes",0.15,0) +IF(L4="Yes",0.3,0) -> 1 | E4: Yes | F4: Yes | G4: Yes | H4: Yes | I4: Yes | J4: Yes | K4: Yes | L4: Yes
A5: https://4ammedia.zendesk.com/agent/tickets/237096 | B5: 46223 | C5: =IF(B5="", "", TEXT(B5, "ddd")) -> Mon | D5: =IF(E5="Yes",0.05,0) +IF(F5="Yes",0.1,0) +IF(G5="Yes",0.15,0) +IF(H5="Yes",0.15,0) +IF(I5="Yes",0.05,0) +IF(J5="Yes",0.05,0) +IF(K5="Yes",0.15,0) +IF(L5="Yes",0.3,0) -> 1 | E5: Yes | F5: Yes | G5: Yes | H5: Yes | I5: Yes | J5: Yes | K5: Yes | L5: Yes
A6: https://4ammedia.zendesk.com/agent/tickets/238882 | B6: 46224 | C6: =IF(B6="", "", TEXT(B6, "ddd")) -> Tue | D6: =IF(E6="Yes",0.05,0) +IF(F6="Yes",0.1,0) +IF(G6="Yes",0.15,0) +IF(H6="Yes",0.15,0) +IF(I6="Yes",0.05,0) +IF(J6="Yes",0.05,0) +IF(K6="Yes",0.15,0) +IF(L6="Yes",0.3,0) -> 1 | E6: Yes | F6: Yes | G6: Yes | H6: Yes | I6: Yes | J6: Yes | K6: Yes | L6: Yes
A7: https://4ammedia.zendesk.com/agent/tickets/239043 | B7: 46224 | C7: =IF(B7="", "", TEXT(B7, "ddd")) -> Tue | D7: =IF(E7="Yes",0.05,0) +IF(F7="Yes",0.1,0) +IF(G7="Yes",0.15,0) +IF(H7="Yes",0.15,0) +IF(I7="Yes",0.05,0) +IF(J7="Yes",0.05,0) +IF(K7="Yes",0.15,0) +IF(L7="Yes",0.3,0) -> 1 | E7: Yes | F7: Yes | G7: Yes | H7: Yes | I7: Yes | J7: Yes | K7: Yes | L7: Yes
A8: https://4ammedia.zendesk.com/agent/tickets/239140 | B8: 46224 | C8: =IF(B8="", "", TEXT(B8, "ddd")) -> Tue | D8: =IF(E8="Yes",0.05,0) +IF(F8="Yes",0.1,0) +IF(G8="Yes",0.15,0) +IF(H8="Yes",0.15,0) +IF(I8="Yes",0.05,0) +IF(J8="Yes",0.05,0) +IF(K8="Yes",0.15,0) +IF(L8="Yes",0.3,0) -> 1 | E8: Yes | F8: Yes | G8: Yes | H8: Yes | I8: Yes | J8: Yes | K8: Yes | L8: Yes
A9: https://4ammedia.zendesk.com/agent/tickets/241082 | B9: 46225 | C9: =IF(B9="", "", TEXT(B9, "ddd")) -> Wed | D9: =IF(E9="Yes",0.05,0) +IF(F9="Yes",0.1,0) +IF(G9="Yes",0.15,0) +IF(H9="Yes",0.15,0) +IF(I9="Yes",0.05,0) +IF(J9="Yes",0.05,0) +IF(K9="Yes",0.15,0) +IF(L9="Yes",0.3,0) -> 1 | E9: Yes | F9: Yes | G9: Yes | H9: Yes | I9: Yes | J9: Yes | K9: Yes | L9: Yes
A10: https://4ammedia.zendesk.com/agent/tickets/241283 | B10: 46225 | C10: =IF(B10="", "", TEXT(B10, "ddd")) -> Wed | D10: =IF(E10="Yes",0.05,0) +IF(F10="Yes",0.1,0) +IF(G10="Yes",0.15,0) +IF(H10="Yes",0.15,0) +IF(I10="Yes",0.05,0) +IF(J10="Yes",0.05,0) +IF(K10="Yes",0.15,0) +IF(L10="Yes",0.3,0) -> 1 | E10: Yes | F10: Yes | G10: Yes | H10: Yes | I10: Yes | J10: Yes | K10: Yes | L10: Yes
A11: https://4ammedia.zendesk.com/agent/tickets/241441 | B11: 46225 | C11: =IF(B11="", "", TEXT(B11, "ddd")) -> Wed | D11: =IF(E11="Yes",0.05,0) +IF(F11="Yes",0.1,0) +IF(G11="Yes",0.15,0) +IF(H11="Yes",0.15,0) +IF(I11="Yes",0.05,0) +IF(J11="Yes",0.05,0) +IF(K11="Yes",0.15,0) +IF(L11="Yes",0.3,0) -> 1 | E11: Yes | F11: Yes | G11: Yes | H11: Yes | I11: Yes | J11: Yes | K11: Yes | L11: Yes
A12: https://4ammedia.zendesk.com/agent/tickets/243296 | B12: 46226 | C12: =IF(B12="", "", TEXT(B12, "ddd")) -> Thu | D12: =IF(E12="Yes",0.05,0) +IF(F12="Yes",0.1,0) +IF(G12="Yes",0.15,0) +IF(H12="Yes",0.15,0) +IF(I12="Yes",0.05,0) +IF(J12="Yes",0.05,0) +IF(K12="Yes",0.15,0) +IF(L12="Yes",0.3,0) -> 1 | E12: Yes | F12: Yes | G12: Yes | H12: Yes | I12: Yes | J12: Yes | K12: Yes | L12: Yes
A13: https://4ammedia.zendesk.com/agent/tickets/243386 | B13: 46226 | C13: =IF(B13="", "", TEXT(B13, "ddd")) -> Thu | D13: =IF(E13="Yes",0.05,0) +IF(F13="Yes",0.1,0) +IF(G13="Yes",0.15,0) +IF(H13="Yes",0.15,0) +IF(I13="Yes",0.05,0) +IF(J13="Yes",0.05,0) +IF(K13="Yes",0.15,0) +IF(L13="Yes",0.3,0) -> 1 | E13: Yes | F13: Yes | G13: Yes | H13: Yes | I13: Yes | J13: Yes | K13: Yes | L13: Yes
A14: https://4ammedia.zendesk.com/agent/tickets/243544 | B14: 46226 | C14: =IF(B14="", "", TEXT(B14, "ddd")) -> Thu | D14: =IF(E14="Yes",0.05,0) +IF(F14="Yes",0.1,0) +IF(G14="Yes",0.15,0) +IF(H14="Yes",0.15,0) +IF(I14="Yes",0.05,0) +IF(J14="Yes",0.05,0) +IF(K14="Yes",0.15,0) +IF(L14="Yes",0.3,0) -> 1 | E14: Yes | F14: Yes | G14: Yes | H14: Yes | I14: Yes | J14: Yes | K14: Yes | L14: Yes
... A17: https://4ammedia.zendesk.com/agent/tickets/248481 | B17: 46229 | C17: =IF(B17="", "", TEXT(B17, "ddd")) -> Sun | D17: =IF(E17="Yes",0.05,0) +IF(F17="Yes",0.1,0) +IF(G17="Yes",0.15,0) +IF(H17="Yes",0.15,0) +IF(I17="Yes",0.05,0) +IF(J17="Yes",0.05,0) +IF(K17="Yes",0.15,0) +IF(L17="Yes",0.3,0) -> 1 | E17: Yes | F17: Yes | G17: Yes | H17: Yes | I17: Yes | J17: Yes | K17: Yes | L17: Yes
C18: Final QA Score | D18: =AVERAGE(D3:D17) -> 1 | L18: Final QA Score | M18: =SUM(M3:M17)/75*0.1 -> 0
A19: Week (July 27, - Aug 2,2026)
A20: Ticket Link | B20: Date | C20: Day | D20: SCORE | E20: Notes and Tagging(internal Note and Sticky Note) 5% | F20: COURTESY & EMPATHY 15% | G20: TONE OF VOICE & ELOQUENCE 20% | H20: CALL CONTROL 15% | I20: VERIFICATION 5% | J20: PROBING 5% | K20: MASTERY OF INFORMATION 15% | L20: RESOLUTION 20% | M20: Average | N20: NOTES
A21: https://4ammedia.zendesk.com/agent/tickets/250325 | B21: 46230 | C21: =IF(B21="", "", TEXT(B21, "ddd")) -> Mon | D21: =IF(E21="Yes",0.05,0) +IF(F21="Yes",0.1,0) +IF(G21="Yes",0.15,0) +IF(H21="Yes",0.15,0) +IF(I21="Yes",0.05,0) +IF(J21="Yes",0.05,0) +IF(K21="Yes",0.15,0) +IF(L21="Yes",0.3,0) -> 1 | E21: Yes | F21: Yes | G21: Yes | H21: Yes | I21: Yes | J21: Yes | K21: Yes | L21: Yes
A22: https://4ammedia.zendesk.com/agent/tickets/250378 | B22: 46230 | C22: =IF(B22="", "", TEXT(B22, "ddd")) -> Mon | D22: =IF(E22="Yes",0.05,0) +IF(F22="Yes",0.1,0) +IF(G22="Yes",0.15,0) +IF(H22="Yes",0.15,0) +IF(I22="Yes",0.05,0) +IF(J22="Yes",0.05,0) +IF(K22="Yes",0.15,0) +IF(L22="Yes",0.3,0) -> 1 | E22: Yes | F22: Yes | G22: Yes | H22: Yes | I22: Yes | J22: Yes | K22: Yes | L22: Yes
A23: https://4ammedia.zendesk.com/agent/tickets/250680 | B23: 46230 | C23: =IF(B23="", "", TEXT(B23, "ddd")) -> Mon | D23: =IF(E23="Yes",0.05,0) +IF(F23="Yes",0.1,0) +IF(G23="Yes",0.15,0) +IF(H23="Yes",0.15,0) +IF(I23="Yes",0.05,0) +IF(J23="Yes",0.05,0) +IF(K23="Yes",0.15,0) +IF(L23="Yes",0.3,0) -> 1 | E23: Yes | F23: Yes | G23: Yes | H23: Yes | I23: Yes | J23: Yes | K23: Yes | L23: Yes
A24: https://4ammedia.zendesk.com/agent/tickets/251780 | B24: 46231 | C24: =IF(B24="", "", TEXT(B24, "ddd")) -> Tue | D24: =IF(E24="Yes",0.05,0) +IF(F24="Yes",0.1,0) +IF(G24="Yes",0.15,0) +IF(H24="Yes",0.15,0) +IF(I24="Yes",0.05,0) +IF(J24="Yes",0.05,0) +IF(K24="Yes",0.15,0) +IF(L24="Yes",0.3,0) -> 1 | E24: Yes | F24: Yes | G24: Yes | H24: Yes | I24: Yes | J24: Yes | K24: Yes | L24: Yes
A25: https://4ammedia.zendesk.com/agent/tickets/252276 | B25: 46231 | C25: =IF(B25="", "", TEXT(B25, "ddd")) -> Tue | D25: =IF(E25="Yes",0.05,0) +IF(F25="Yes",0.1,0) +IF(G25="Yes",0.15,0) +IF(H25="Yes",0.15,0) +IF(I25="Yes",0.05,0) +IF(J25="Yes",0.05,0) +IF(K25="Yes",0.15,0) +IF(L25="Yes",0.3,0) -> 0.45 | E25: Yes | F25: Yes | G25: Yes | H25: Yes | I25: No | J25: No | K25: No | L25: No | N25: CSR offered replacement even though the order is already passed the return window
A26: https://4ammedia.zendesk.com/agent/tickets/251918 | B26: 46231 | C26: =IF(B26="", "", TEXT(B26, "ddd")) -> Tue | D26: =IF(E26="Yes",0.05,0) +IF(F26="Yes",0.1,0) +IF(G26="Yes",0.15,0) +IF(H26="Yes",0.15,0) +IF(I26="Yes",0.05,0) +IF(J26="Yes",0.05,0) +IF(K26="Yes",0.15,0) +IF(L26="Yes",0.3,0) -> 1 | E26: Yes | F26: Yes | G26: Yes | H26: Yes | I26: Yes | J26: Yes | K26: Yes | L26: Yes
A27: https://4ammedia.zendesk.com/agent/tickets/254686 | B27: 46232 | C27: =IF(B27="", "", TEXT(B27, "ddd")) -> Wed | D27: =IF(E27="Yes",0.05,0) +IF(F27="Yes",0.1,0) +IF(G27="Yes",0.15,0) +IF(H27="Yes",0.15,0) +IF(I27="Yes",0.05,0) +IF(J27="Yes",0.05,0) +IF(K27="Yes",0.15,0) +IF(L27="Yes",0.3,0) -> 1 | E27: Yes | F27: Yes | G27: Yes | H27: Yes | I27: Yes | J27: Yes | K27: Yes | L27: Yes
A28: https://4ammedia.zendesk.com/agent/tickets/254960 | B28: 46232 | C28: =IF(B28="", "", TEXT(B28, "ddd")) -> Wed | D28: =IF(E28="Yes",0.05,0) +IF(F28="Yes",0.1,0) +IF(G28="Yes",0.15,0) +IF(H28="Yes",0.15,0) +IF(I28="Yes",0.05,0) +IF(J28="Yes",0.05,0) +IF(K28="Yes",0.15,0) +IF(L28="Yes",0.3,0) -> 1 | E28: Yes | F28: Yes | G28: Yes | H28: Yes | I28: Yes | J28: Yes | K28: Yes | L28: Yes
A29: https://4ammedia.zendesk.com/agent/tickets/255022 | B29: 46232 | C29: =IF(B29="", "", TEXT(B29, "ddd")) -> Wed | D29: =IF(E29="Yes",0.05,0) +IF(F29="Yes",0.1,0) +IF(G29="Yes",0.15,0) +IF(H29="Yes",0.15,0) +IF(I29="Yes",0.05,0) +IF(J29="Yes",0.05,0) +IF(K29="Yes",0.15,0) +IF(L29="Yes",0.3,0) -> 1 | E29: Yes | F29: Yes | G29: Yes | H29: Yes | I29: Yes | J29: Yes | K29: Yes | L29: Yes
A30: https://4ammedia.zendesk.com/agent/tickets/260104 | B30: 46235 | C30: =IF(B30="", "", TEXT(B30, "ddd")) -> Sat | D30: =IF(E30="Yes",0.05,0) +IF(F30="Yes",0.1,0) +IF(G30="Yes",0.15,0) +IF(H30="Yes",0.15,0) +IF(I30="Yes",0.05,0) +IF(J30="Yes",0.05,0) +IF(K30="Yes",0.15,0) +IF(L30="Yes",0.3,0) -> 1 | E30: Yes | F30: Yes | G30: Yes | H30: Yes | I30: Yes | J30: Yes | K30: Yes | L30: Yes
A31: https://4ammedia.zendesk.com/agent/tickets/260160 | B31: 46235 | C31: =IF(B31="", "", TEXT(B31, "ddd")) -> Sat | D31: =IF(E31="Yes",0.05,0) +IF(F31="Yes",0.1,0) +IF(G31="Yes",0.15,0) +IF(H31="Yes",0.15,0) +IF(I31="Yes",0.05,0) +IF(J31="Yes",0.05,0) +IF(K31="Yes",0.15,0) +IF(L31="Yes",0.3,0) -> 1 | E31: Yes | F31: Yes | G31: Yes | H31: Yes | I31: Yes | J31: Yes | K31: Yes | L31: Yes
A32: https://4ammedia.zendesk.com/agent/tickets/260193 | B32: 46235 | C32: =IF(B32="", "", TEXT(B32, "ddd")) -> Sat | D32: =IF(E32="Yes",0.05,0) +IF(F32="Yes",0.1,0) +IF(G32="Yes",0.15,0) +IF(H32="Yes",0.15,0) +IF(I32="Yes",0.05,0) +IF(J32="Yes",0.05,0) +IF(K32="Yes",0.15,0) +IF(L32="Yes",0.3,0) -> 1 | E32: Yes | F32: Yes | G32: Yes | H32: Yes | I32: Yes | J32: Yes | K32: Yes | L32: Yes
A33: https://4ammedia.zendesk.com/agent/tickets/261437 | C33: =IF(B33="", "", TEXT(B33, "ddd")) | D33: =IF(E33="Yes",0.05,0) +IF(F33="Yes",0.1,0) +IF(G33="Yes",0.15,0) +IF(H33="Yes",0.15,0) +IF(I33="Yes",0.05,0) +IF(J33="Yes",0.05,0) +IF(K33="Yes",0.15,0) +IF(L33="Yes",0.3,0) -> 1 | E33: Yes | F33: Yes | G33: Yes | H33: Yes | I33: Yes | J33: Yes | K33: Yes | L33: Yes
A34: https://4ammedia.zendesk.com/agent/tickets/261529 | C34: =IF(B34="", "", TEXT(B34, "ddd")) | D34: =IF(E34="Yes",0.05,0) +IF(F34="Yes",0.1,0) +IF(G34="Yes",0.15,0) +IF(H34="Yes",0.15,0) +IF(I34="Yes",0.05,0) +IF(J34="Yes",0.05,0) +IF(K34="Yes",0.15,0) +IF(L34="Yes",0.3,0) -> 1 | E34: Yes | F34: Yes | G34: Yes | H34: Yes | I34: Yes | J34: Yes | K34: Yes | L34: Yes
A35: https://4ammedia.zendesk.com/agent/tickets/261660 | C35: =IF(B35="", "", TEXT(B35, "ddd")) | D35: =IF(E35="Yes",0.05,0) +IF(F35="Yes",0.1,0) +IF(G35="Yes",0.15,0) +IF(H35="Yes",0.15,0) +IF(I35="Yes",0.05,0) +IF(J35="Yes",0.05,0) +IF(K35="Yes",0.15,0) +IF(L35="Yes",0.3,0) -> 1 | E35: Yes | F35: Yes | G35: Yes | H35: Yes | I35: Yes | J35: Yes | K35: Yes | L35: Yes
C36: Final QA Score | D36: =AVERAGE(D21:D35) -> 0.96333333 | L36: Final QA Score | M36: =SUM(M21:M35)/75*0.1 -> 0
A37: Week (Aug 3, - Aug 9,2026)
A38: Ticket Link | B38: Date | C38: Day | D38: SCORE | E38: Notes and Tagging(internal Note and Sticky Note) 5% | F38: COURTESY & EMPATHY 15% | G38: TONE OF VOICE & ELOQUENCE 20% | H38: CALL CONTROL 15% | I38: VERIFICATION 5% | J38: PROBING 5% | K38: MASTERY OF INFORMATION 15% | L38: RESOLUTION 20% | M38: Average | N38: NOTES
A39: https://4ammedia.zendesk.com/agent/tickets/262991 | B39: 46237 | C39: =IF(B39="", "", TEXT(B39, "ddd")) -> Mon | D39: =IF(E39="Yes",0.05,0) +IF(F39="Yes",0.1,0) +IF(G39="Yes",0.15,0) +IF(H39="Yes",0.15,0) +IF(I39="Yes",0.05,0) +IF(J39="Yes",0.05,0) +IF(K39="Yes",0.15,0) +IF(L39="Yes",0.3,0) -> 1 | E39: Yes | F39: Yes | G39: Yes | H39: Yes | I39: Yes | J39: Yes | K39: Yes | L39: Yes
A40: https://4ammedia.zendesk.com/agent/tickets/263282 | B40: 46237 | C40: =IF(B40="", "", TEXT(B40, "ddd")) -> Mon | D40: =IF(E40="Yes",0.05,0) +IF(F40="Yes",0.1,0) +IF(G40="Yes",0.15,0) +IF(H40="Yes",0.15,0) +IF(I40="Yes",0.05,0) +IF(J40="Yes",0.05,0) +IF(K40="Yes",0.15,0) +IF(L40="Yes",0.3,0) -> 1 | E40: Yes | F40: Yes | G40: Yes | H40: Yes | I40: Yes | J40: Yes | K40: Yes | L40: Yes
A41: https://4ammedia.zendesk.com/agent/tickets/263653 | B41: 46237 | C41: =IF(B41="", "", TEXT(B41, "ddd")) -> Mon | D41: =IF(E41="Yes",0.05,0) +IF(F41="Yes",0.1,0) +IF(G41="Yes",0.15,0) +IF(H41="Yes",0.15,0) +IF(I41="Yes",0.05,0) +IF(J41="Yes",0.05,0) +IF(K41="Yes",0.15,0) +IF(L41="Yes",0.3,0) -> 1 | E41: Yes | F41: Yes | G41: Yes | H41: Yes | I41: Yes | J41: Yes | K41: Yes | L41: Yes
A42: https://4ammedia.zendesk.com/agent/tickets/265337 | B42: 46238 | C42: =IF(B42="", "", TEXT(B42, "ddd")) -> Tue | D42: =IF(E42="Yes",0.05,0) +IF(F42="Yes",0.1,0) +IF(G42="Yes",0.15,0) +IF(H42="Yes",0.15,0) +IF(I42="Yes",0.05,0) +IF(J42="Yes",0.05,0) +IF(K42="Yes",0.15,0) +IF(L42="Yes",0.3,0) -> 1 | E42: Yes | F42: Yes | G42: Yes | H42: Yes | I42: Yes | J42: Yes | K42: Yes | L42: Yes
A43: https://4ammedia.zendesk.com/agent/tickets/265403 | B43: 46238 | C43: =IF(B43="", "", TEXT(B43, "ddd")) -> Tue | D43: =IF(E43="Yes",0.05,0) +IF(F43="Yes",0.1,0) +IF(G43="Yes",0.15,0) +IF(H43="Yes",0.15,0) +IF(I43="Yes",0.05,0) +IF(J43="Yes",0.05,0) +IF(K43="Yes",0.15,0) +IF(L43="Yes",0.3,0) -> 1 | E43: Yes | F43: Yes | G43: Yes | H43: Yes | I43: Yes | J43: Yes | K43: Yes | L43: Yes
A44: https://4ammedia.zendesk.com/agent/tickets/265441 | B44: 46238 | C44: =IF(B44="", "", TEXT(B44, "ddd")) -> Tue | D44: =IF(E44="Yes",0.05,0) +IF(F44="Yes",0.1,0) +IF(G44="Yes",0.15,0) +IF(H44="Yes",0.15,0) +IF(I44="Yes",0.05,0) +IF(J44="Yes",0.05,0) +IF(K44="Yes",0.15,0) +IF(L44="Yes",0.3,0) -> 1 | E44: Yes | F44: Yes | G44: Yes | H44: Yes | I44: Yes | J44: Yes | K44: Yes | L44: Yes
A45: https://4ammedia.zendesk.com/agent/tickets/267801 | B45: 46239 | C45: =IF(B45="", "", TEXT(B45, "ddd")) -> Wed | D45: =IF(E45="Yes",0.05,0) +IF(F45="Yes",0.1,0) +IF(G45="Yes",0.15,0) +IF(H45="Yes",0.15,0) +IF(I45="Yes",0.05,0) +IF(J45="Yes",0.05,0) +IF(K45="Yes",0.15,0) +IF(L45="Yes",0.3,0) -> 1 | E45: Yes | F45: Yes | G45: Yes | H45: Yes | I45: Yes | J45: Yes | K45: Yes | L45: Yes
A46: https://4ammedia.zendesk.com/agent/tickets/267944 | B46: 46239 | C46: =IF(B46="", "", TEXT(B46, "ddd")) -> Wed | D46: =IF(E46="Yes",0.05,0) +IF(F46="Yes",0.1,0) +IF(G46="Yes",0.15,0) +IF(H46="Yes",0.15,0) +IF(I46="Yes",0.05,0) +IF(J46="Yes",0.05,0) +IF(K46="Yes",0.15,0) +IF(L46="Yes",0.3,0) -> 1 | E46: Yes | F46: Yes | G46: Yes | H46: Yes | I46: Yes | J46: Yes | K46: Yes | L46: Yes
A47: https://4ammedia.zendesk.com/agent/tickets/268102 | B47: 46239 | C47: =IF(B47="", "", TEXT(B47, "ddd")) -> Wed | D47: =IF(E47="Yes",0.05,0) +IF(F47="Yes",0.1,0) +IF(G47="Yes",0.15,0) +IF(H47="Yes",0.15,0) +IF(I47="Yes",0.05,0) +IF(J47="Yes",0.05,0) +IF(K47="Yes",0.15,0) +IF(L47="Yes",0.3,0) -> 1 | E47: Yes | F47: Yes | G47: Yes | H47: Yes | I47: Yes | J47: Yes | K47: Yes | L47: Yes
A48: https://4ammedia.zendesk.com/agent/tickets/269513 | B48: 46240 | C48: =IF(B48="", "", TEXT(B48, "ddd")) -> Thu | D48: =IF(E48="Yes",0.05,0) +IF(F48="Yes",0.1,0) +IF(G48="Yes",0.15,0) +IF(H48="Yes",0.15,0) +IF(I48="Yes",0.05,0) +IF(J48="Yes",0.05,0) +IF(K48="Yes",0.15,0) +IF(L48="Yes",0.3,0) -> 1 | E48: Yes | F48: Yes | G48: Yes | H48: Yes | I48: Yes | J48: Yes | K48: Yes | L48: Yes
A49: https://4ammedia.zendesk.com/agent/tickets/269672 | B49: 46240 | C49: =IF(B49="", "", TEXT(B49, "ddd")) -> Thu | D49: =IF(E49="Yes",0.05,0) +IF(F49="Yes",0.1,0) +IF(G49="Yes",0.15,0) +IF(H49="Yes",0.15,0) +IF(I49="Yes",0.05,0) +IF(J49="Yes",0.05,0) +IF(K49="Yes",0.15,0) +IF(L49="Yes",0.3,0) -> 1 | E49: Yes | F49: Yes | G49: Yes | H49: Yes | I49: Yes | J49: Yes | K49: Yes | L49: Yes
A50: https://4ammedia.zendesk.com/agent/tickets/269697 | B50: 46240 | C50: =IF(B50="", "", TEXT(B50, "ddd")) -> Thu | D50: =IF(E50="Yes",0.05,0) +IF(F50="Yes",0.1,0) +IF(G50="Yes",0.15,0) +IF(H50="Yes",0.15,0) +IF(I50="Yes",0.05,0) +IF(J50="Yes",0.05,0) +IF(K50="Yes",0.15,0) +IF(L50="Yes",0.3,0) -> 1 | E50: Yes | F50: Yes | G50: Yes | H50: Yes | I50: Yes | J50: Yes | K50: Yes | L50: Yes
... A53: https://4ammedia.zendesk.com/agent/tickets/273459 | B53: 46242 | C53: =IF(B53="", "", TEXT(B53, "ddd")) -> Sat | D53: =IF(E53="Yes",0.05,0) +IF(F53="Yes",0.1,0) +IF(G53="Yes",0.15,0) +IF(H53="Yes",0.15,0) +IF(I53="Yes",0.05,0) +IF(J53="Yes",0.05,0) +IF(K53="Yes",0.15,0) +IF(L53="Yes",0.3,0) -> 1 | E53: Yes | F53: Yes | G53: Yes | H53: Yes | I53: Yes | J53: Yes | K53: Yes | L53: Yes
C54: Final QA Score | D54: =AVERAGE(D39:D53) -> 1 | L54: Final QA Score | M54: =SUM(M39:M53)/75*0.1 -> 0
A55: Week (Aug 10, - Aug 16,2026)
A56: Ticket Link | B56: Date | C56: Day | D56: SCORE | E56: Notes and Tagging(internal Note and Sticky Note) 5% | F56: COURTESY & EMPATHY 15% | G56: TONE OF VOICE & ELOQUENCE 20% | H56: CALL CONTROL 15% | I56: VERIFICATION 5% | J56: PROBING 5% | K56: MASTERY OF INFORMATION 15% | L56: RESOLUTION 20% | M56: Average | N56: NOTES
A57: https://4ammedia.zendesk.com/agent/tickets/276368 | B57: 46244 | C57: =IF(B57="", "", TEXT(B57, "ddd")) -> Mon | D57: =IF(E57="Yes",0.05,0) +IF(F57="Yes",0.1,0) +IF(G57="Yes",0.15,0) +IF(H57="Yes",0.15,0) +IF(I57="Yes",0.05,0) +IF(J57="Yes",0.05,0) +IF(K57="Yes",0.15,0) +IF(L57="Yes",0.3,0) -> 1 | E57: Yes | F57: Yes | G57: Yes | H57: Yes | I57: Yes | J57: Yes | K57: Yes | L57: Yes
A58: https://4ammedia.zendesk.com/agent/tickets/276462 | B58: 46244 | C58: =IF(B58="", "", TEXT(B58, "ddd")) -> Mon | D58: =IF(E58="Yes",0.05,0) +IF(F58="Yes",0.1,0) +IF(G58="Yes",0.15,0) +IF(H58="Yes",0.15,0) +IF(I58="Yes",0.05,0) +IF(J58="Yes",0.05,0) +IF(K58="Yes",0.15,0) +IF(L58="Yes",0.3,0) -> 1 | E58: Yes | F58: Yes | G58: Yes | H58: Yes | I58: Yes | J58: Yes | K58: Yes | L58: Yes
A59: https://4ammedia.zendesk.com/agent/tickets/276656 | B59: 46244 | C59: =IF(B59="", "", TEXT(B59, "ddd")) -> Mon | D59: =IF(E59="Yes",0.05,0) +IF(F59="Yes",0.1,0) +IF(G59="Yes",0.15,0) +IF(H59="Yes",0.15,0) +IF(I59="Yes",0.05,0) +IF(J59="Yes",0.05,0) +IF(K59="Yes",0.15,0) +IF(L59="Yes",0.3,0) -> 1 | E59: Yes | F59: Yes | G59: Yes | H59: Yes | I59: Yes | J59: Yes | K59: Yes | L59: Yes
A60: https://4ammedia.zendesk.com/agent/tickets/278079 | B60: 46245 | C60: =IF(B60="", "", TEXT(B60, "ddd")) -> Tue | D60: =IF(E60="Yes",0.05,0) +IF(F60="Yes",0.1,0) +IF(G60="Yes",0.15,0) +IF(H60="Yes",0.15,0) +IF(I60="Yes",0.05,0) +IF(J60="Yes",0.05,0) +IF(K60="Yes",0.15,0) +IF(L60="Yes",0.3,0) -> 1 | E60: Yes | F60: Yes | G60: Yes | H60: Yes | I60: Yes | J60: Yes | K60: Yes | L60: Yes
A61: https://4ammedia.zendesk.com/agent/tickets/278137 | B61: 46245 | C61: =IF(B61="", "", TEXT(B61, "ddd")) -> Tue | D61: =IF(E61="Yes",0.05,0) +IF(F61="Yes",0.1,0) +IF(G61="Yes",0.15,0) +IF(H61="Yes",0.15,0) +IF(I61="Yes",0.05,0) +IF(J61="Yes",0.05,0) +IF(K61="Yes",0.15,0) +IF(L61="Yes",0.3,0) -> 1 | E61: Yes | F61: Yes | G61: Yes | H61: Yes | I61: Yes | J61: Yes | K61: Yes | L61: Yes
A62: https://4ammedia.zendesk.com/agent/tickets/278210 | B62: 46245 | C62: =IF(B62="", "", TEXT(B62, "ddd")) -> Tue | D62: =IF(E62="Yes",0.05,0) +IF(F62="Yes",0.1,0) +IF(G62="Yes",0.15,0) +IF(H62="Yes",0.15,0) +IF(I62="Yes",0.05,0) +IF(J62="Yes",0.05,0) +IF(K62="Yes",0.15,0) +IF(L62="Yes",0.3,0) -> 1 | E62: Yes | F62: Yes | G62: Yes | H62: Yes | I62: Yes | J62: Yes | K62: Yes | L62: Yes
A63: https://4ammedia.zendesk.com/agent/tickets/280718 | B63: 46246 | C63: =IF(B63="", "", TEXT(B63, "ddd")) -> Wed | D63: =IF(E63="Yes",0.05,0) +IF(F63="Yes",0.1,0) +IF(G63="Yes",0.15,0) +IF(H63="Yes",0.15,0) +IF(I63="Yes",0.05,0) +IF(J63="Yes",0.05,0) +IF(K63="Yes",0.15,0) +IF(L63="Yes",0.3,0) -> 1 | E63: Yes | F63: Yes | G63: Yes | H63: Yes | I63: Yes | J63: Yes | K63: Yes | L63: Yes
A64: https://4ammedia.zendesk.com/agent/tickets/280829 | B64: 46246 | C64: =IF(B64="", "", TEXT(B64, "ddd")) -> Wed | D64: =IF(E64="Yes",0.05,0) +IF(F64="Yes",0.1,0) +IF(G64="Yes",0.15,0) +IF(H64="Yes",0.15,0) +IF(I64="Yes",0.05,0) +IF(J64="Yes",0.05,0) +IF(K64="Yes",0.15,0) +IF(L64="Yes",0.3,0) -> 1 | E64: Yes | F64: Yes | G64: Yes | H64: Yes | I64: Yes | J64: Yes | K64: Yes | L64: Yes
A65: https://4ammedia.zendesk.com/agent/tickets/280931 | B65: 46246 | C65: =IF(B65="", "", TEXT(B65, "ddd")) -> Wed | D65: =IF(E65="Yes",0.05,0) +IF(F65="Yes",0.1,0) +IF(G65="Yes",0.15,0) +IF(H65="Yes",0.15,0) +IF(I65="Yes",0.05,0) +IF(J65="Yes",0.05,0) +IF(K65="Yes",0.15,0) +IF(L65="Yes",0.3,0) -> 1 | E65: Yes | F65: Yes | G65: Yes | H65: Yes | I65: Yes | J65: Yes | K65: Yes | L65: Yes
A66: https://4ammedia.zendesk.com/agent/tickets/282179 | B66: 46247 | C66: =IF(B66="", "", TEXT(B66, "ddd")) -> Thu | D66: =IF(E66="Yes",0.05,0) +IF(F66="Yes",0.1,0) +IF(G66="Yes",0.15,0) +IF(H66="Yes",0.15,0) +IF(I66="Yes",0.05,0) +IF(J66="Yes",0.05,0) +IF(K66="Yes",0.15,0) +IF(L66="Yes",0.3,0) -> 1 | E66: Yes | F66: Yes | G66: Yes | H66: Yes | I66: Yes | J66: Yes | K66: Yes | L66: Yes
A67: https://4ammedia.zendesk.com/agent/tickets/282320 | B67: 46247 | C67: =IF(B67="", "", TEXT(B67, "ddd")) -> Thu | D67: =IF(E67="Yes",0.05,0) +IF(F67="Yes",0.1,0) +IF(G67="Yes",0.15,0) +IF(H67="Yes",0.15,0) +IF(I67="Yes",0.05,0) +IF(J67="Yes",0.05,0) +IF(K67="Yes",0.15,0) +IF(L67="Yes",0.3,0) -> 1 | E67: Yes | F67: Yes | G67: Yes | H67: Yes | I67: Yes | J67: Yes | K67: Yes | L67: Yes
A68: https://4ammedia.zendesk.com/agent/tickets/282458 | B68: 46247 | C68: =IF(B68="", "", TEXT(B68, "ddd")) -> Thu | D68: =IF(E68="Yes",0.05,0) +IF(F68="Yes",0.1,0) +IF(G68="Yes",0.15,0) +IF(H68="Yes",0.15,0) +IF(I68="Yes",0.05,0) +IF(J68="Yes",0.05,0) +IF(K68="Yes",0.15,0) +IF(L68="Yes",0.3,0) -> 1 | E68: Yes | F68: Yes | G68: Yes | H68: Yes | I68: Yes | J68: Yes | K68: Yes | L68: Yes
... A71: https://4ammedia.zendesk.com/agent/tickets/286245 | B71: 46249 | C71: =IF(B71="", "", TEXT(B71, "ddd")) -> Sat | D71: =IF(E71="Yes",0.05,0) +IF(F71="Yes",0.1,0) +IF(G71="Yes",0.15,0) +IF(H71="Yes",0.15,0) +IF(I71="Yes",0.05,0) +IF(J71="Yes",0.05,0) +IF(K71="Yes",0.15,0) +IF(L71="Yes",0.3,0) -> 1 | E71: Yes | F71: Yes | G71: Yes | H71: Yes | I71: Yes | J71: Yes | K71: Yes | L71: Yes
C72: Final QA Score | D72: =AVERAGE(D57:D71) -> 1 | L72: Final QA Score | M72: =SUM(M57:M71)/75*0.1 -> 0
A73: Week (Aug 17, - Aug 23,2026)
A74: Ticket Link | B74: Date | C74: Day | D74: SCORE | E74: Notes and Tagging(internal Note and Sticky Note) 5% | F74: COURTESY & EMPATHY 15% | G74: TONE OF VOICE & ELOQUENCE 20% | H74: CALL CONTROL 15% | I74: VERIFICATION 5% | J74: PROBING 5% | K74: MASTERY OF INFORMATION 15% | L74: RESOLUTION 20% | M74: Average | N74: NOTES
A75: https://4ammedia.zendesk.com/agent/tickets/288971 | B75: 46251 | C75: =IF(B75="", "", TEXT(B75, "ddd")) -> Mon | D75: =IF(E75="Yes",0.05,0) +IF(F75="Yes",0.1,0) +IF(G75="Yes",0.15,0) +IF(H75="Yes",0.15,0) +IF(I75="Yes",0.05,0) +IF(J75="Yes",0.05,0) +IF(K75="Yes",0.15,0) +IF(L75="Yes",0.3,0) -> 1 | E75: Yes | F75: Yes | G75: Yes | H75: Yes | I75: Yes | J75: Yes | K75: Yes | L75: Yes
A76: https://4ammedia.zendesk.com/agent/tickets/289180 | B76: 46251 | C76: =IF(B76="", "", TEXT(B76, "ddd")) -> Mon | D76: =IF(E76="Yes",0.05,0) +IF(F76="Yes",0.1,0) +IF(G76="Yes",0.15,0) +IF(H76="Yes",0.15,0) +IF(I76="Yes",0.05,0) +IF(J76="Yes",0.05,0) +IF(K76="Yes",0.15,0) +IF(L76="Yes",0.3,0) -> 1 | E76: Yes | F76: Yes | G76: Yes | H76: Yes | I76: Yes | J76: Yes | K76: Yes | L76: Yes
A77: https://4ammedia.zendesk.com/agent/tickets/289271 | B77: 46251 | C77: =IF(B77="", "", TEXT(B77, "ddd")) -> Mon | D77: =IF(E77="Yes",0.05,0) +IF(F77="Yes",0.1,0) +IF(G77="Yes",0.15,0) +IF(H77="Yes",0.15,0) +IF(I77="Yes",0.05,0) +IF(J77="Yes",0.05,0) +IF(K77="Yes",0.15,0) +IF(L77="Yes",0.3,0) -> 1 | E77: Yes | F77: Yes | G77: Yes | H77: Yes | I77: Yes | J77: Yes | K77: Yes | L77: Yes
A78: https://4ammedia.zendesk.com/agent/tickets/291419 | B78: 46252 | C78: =IF(B78="", "", TEXT(B78, "ddd")) -> Tue | D78: =IF(E78="Yes",0.05,0) +IF(F78="Yes",0.1,0) +IF(G78="Yes",0.15,0) +IF(H78="Yes",0.15,0) +IF(I78="Yes",0.05,0) +IF(J78="Yes",0.05,0) +IF(K78="Yes",0.15,0) +IF(L78="Yes",0.3,0) -> 1 | E78: Yes | F78: Yes | G78: Yes | H78: Yes | I78: Yes | J78: Yes | K78: Yes | L78: Yes
A79: https://4ammedia.zendesk.com/agent/tickets/291571 | B79: 46252 | C79: =IF(B79="", "", TEXT(B79, "ddd")) -> Tue | D79: =IF(E79="Yes",0.05,0) +IF(F79="Yes",0.1,0) +IF(G79="Yes",0.15,0) +IF(H79="Yes",0.15,0) +IF(I79="Yes",0.05,0) +IF(J79="Yes",0.05,0) +IF(K79="Yes",0.15,0) +IF(L79="Yes",0.3,0) -> 1 | E79: Yes | F79: Yes | G79: Yes | H79: Yes | I79: Yes | J79: Yes | K79: Yes | L79: Yes
A80: https://4ammedia.zendesk.com/agent/tickets/291663 | B80: 46252 | C80: =IF(B80="", "", TEXT(B80, "ddd")) -> Tue | D80: =IF(E80="Yes",0.05,0) +IF(F80="Yes",0.1,0) +IF(G80="Yes",0.15,0) +IF(H80="Yes",0.15,0) +IF(I80="Yes",0.05,0) +IF(J80="Yes",0.05,0) +IF(K80="Yes",0.15,0) +IF(L80="Yes",0.3,0) -> 1 | E80: Yes | F80: Yes | G80: Yes | H80: Yes | I80: Yes | J80: Yes | K80: Yes | L80: Yes
A81: https://4ammedia.zendesk.com/agent/tickets/293706 | B81: 46253 | C81: =IF(B81="", "", TEXT(B81, "ddd")) -> Wed | D81: =IF(E81="Yes",0.05,0) +IF(F81="Yes",0.1,0) +IF(G81="Yes",0.15,0) +IF(H81="Yes",0.15,0) +IF(I81="Yes",0.05,0) +IF(J81="Yes",0.05,0) +IF(K81="Yes",0.15,0) +IF(L81="Yes",0.3,0) -> 1 | E81: Yes | F81: Yes | G81: Yes | H81: Yes | I81: Yes | J81: Yes | K81: Yes | L81: Yes
A82: https://4ammedia.zendesk.com/agent/tickets/293757 | B82: 46253 | C82: =IF(B82="", "", TEXT(B82, "ddd")) -> Wed | D82: =IF(E82="Yes",0.05,0) +IF(F82="Yes",0.1,0) +IF(G82="Yes",0.15,0) +IF(H82="Yes",0.15,0) +IF(I82="Yes",0.05,0) +IF(J82="Yes",0.05,0) +IF(K82="Yes",0.15,0) +IF(L82="Yes",0.3,0) -> 1 | E82: Yes | F82: Yes | G82: Yes | H82: Yes | I82: Yes | J82: Yes | K82: Yes | L82: Yes
A83: https://4ammedia.zendesk.com/agent/tickets/293839 | B83: 46253 | C83: =IF(B83="", "", TEXT(B83, "ddd")) -> Wed | D83: =IF(E83="Yes",0.05,0) +IF(F83="Yes",0.1,0) +IF(G83="Yes",0.15,0) +IF(H83="Yes",0.15,0) +IF(I83="Yes",0.05,0) +IF(J83="Yes",0.05,0) +IF(K83="Yes",0.15,0) +IF(L83="Yes",0.3,0) -> 1 | E83: Yes | F83: Yes | G83: Yes | H83: Yes | I83: Yes | J83: Yes | K83: Yes | L83: Yes
A84: https://4ammedia.zendesk.com/agent/tickets/295266 | B84: 46254 | C84: =IF(B84="", "", TEXT(B84, "ddd")) -> Thu | D84: =IF(E84="Yes",0.05,0) +IF(F84="Yes",0.1,0) +IF(G84="Yes",0.15,0) +IF(H84="Yes",0.15,0) +IF(I84="Yes",0.05,0) +IF(J84="Yes",0.05,0) +IF(K84="Yes",0.15,0) +IF(L84="Yes",0.3,0) -> 1 | E84: Yes | F84: Yes | G84: Yes | H84: Yes | I84: Yes | J84: Yes | K84: Yes | L84: Yes
A85: https://4ammedia.zendesk.com/agent/tickets/295418 | B85: 46254 | C85: =IF(B85="", "", TEXT(B85, "ddd")) -> Thu | D85: =IF(E85="Yes",0.05,0) +IF(F85="Yes",0.1,0) +IF(G85="Yes",0.15,0) +IF(H85="Yes",0.15,0) +IF(I85="Yes",0.05,0) +IF(J85="Yes",0.05,0) +IF(K85="Yes",0.15,0) +IF(L85="Yes",0.3,0) -> 1 | E85: Yes | F85: Yes | G85: Yes | H85: Yes | I85: Yes | J85: Yes | K85: Yes | L85: Yes
A86: https://4ammedia.zendesk.com/agent/tickets/295445 | B86: 46254 | C86: =IF(B86="", "", TEXT(B86, "ddd")) -> Thu | D86: =IF(E86="Yes",0.05,0) +IF(F86="Yes",0.1,0) +IF(G86="Yes",0.15,0) +IF(H86="Yes",0.15,0) +IF(I86="Yes",0.05,0) +IF(J86="Yes",0.05,0) +IF(K86="Yes",0.15,0) +IF(L86="Yes",0.3,0) -> 1 | E86: Yes | F86: Yes | G86: Yes | H86: Yes | I86: Yes | J86: Yes | K86: Yes | L86: Yes
... A89: https://4ammedia.zendesk.com/agent/tickets/300665 | B89: 46257 | C89: =IF(B89="", "", TEXT(B89, "ddd")) -> Sun | D89: =IF(E89="Yes",0.05,0) +IF(F89="Yes",0.1,0) +IF(G89="Yes",0.15,0) +IF(H89="Yes",0.15,0) +IF(I89="Yes",0.05,0) +IF(J89="Yes",0.05,0) +IF(K89="Yes",0.15,0) +IF(L89="Yes",0.3,0) -> 1 | E89: Yes | F89: Yes | G89: Yes | H89: Yes | I89: Yes | J89: Yes | K89: Yes | L89: Yes
C90: Final QA Score | D90: =AVERAGE(D75:D89) -> 1 | L90: Final QA Score | M90: =SUM(M75:M89)/75*0.1 -> 0
A91: Week (Aug 24, - Aug 30,2026)
A92: Ticket Link | B92: Date | C92: Day | D92: SCORE | E92: Notes and Tagging(internal Note and Sticky Note) 5% | F92: COURTESY & EMPATHY 15% | G92: TONE OF VOICE & ELOQUENCE 20% | H92: CALL CONTROL 15% | I92: VERIFICATION 5% | J92: PROBING 5% | K92: MASTERY OF INFORMATION 15% | L92: RESOLUTION 20% | M92: Average | N92: NOTES
A93: https://4ammedia.zendesk.com/agent/tickets/302040 | B93: 46258 | C93: =IF(B93="", "", TEXT(B93, "ddd")) -> Mon | D93: =IF(E93="Yes",0.05,0) +IF(F93="Yes",0.1,0) +IF(G93="Yes",0.15,0) +IF(H93="Yes",0.15,0) +IF(I93="Yes",0.05,0) +IF(J93="Yes",0.05,0) +IF(K93="Yes",0.15,0) +IF(L93="Yes",0.3,0) -> 1 | E93: Yes | F93: Yes | G93: Yes | H93: Yes | I93: Yes | J93: Yes | K93: Yes | L93: Yes
A94: https://4ammedia.zendesk.com/agent/tickets/302462 | B94: 46258 | C94: =IF(B94="", "", TEXT(B94, "ddd")) -> Mon | D94: =IF(E94="Yes",0.05,0) +IF(F94="Yes",0.1,0) +IF(G94="Yes",0.15,0) +IF(H94="Yes",0.15,0) +IF(I94="Yes",0.05,0) +IF(J94="Yes",0.05,0) +IF(K94="Yes",0.15,0) +IF(L94="Yes",0.3,0) -> 1 | E94: Yes | F94: Yes | G94: Yes | H94: Yes | I94: Yes | J94: Yes | K94: Yes | L94: Yes
A95: https://4ammedia.zendesk.com/agent/tickets/302539 | B95: 46258 | C95: =IF(B95="", "", TEXT(B95, "ddd")) -> Mon | D95: =IF(E95="Yes",0.05,0) +IF(F95="Yes",0.1,0) +IF(G95="Yes",0.15,0) +IF(H95="Yes",0.15,0) +IF(I95="Yes",0.05,0) +IF(J95="Yes",0.05,0) +IF(K95="Yes",0.15,0) +IF(L95="Yes",0.3,0) -> 1 | E95: Yes | F95: Yes | G95: Yes | H95: Yes | I95: Yes | J95: Yes | K95: Yes | L95: Yes
A96: https://4ammedia.zendesk.com/agent/tickets/304478 | B96: 46259 | C96: =IF(B96="", "", TEXT(B96, "ddd")) -> Tue | D96: =IF(E96="Yes",0.05,0) +IF(F96="Yes",0.1,0) +IF(G96="Yes",0.15,0) +IF(H96="Yes",0.15,0) +IF(I96="Yes",0.05,0) +IF(J96="Yes",0.05,0) +IF(K96="Yes",0.15,0) +IF(L96="Yes",0.3,0) -> 1 | E96: Yes | F96: Yes | G96: Yes | H96: Yes | I96: Yes | J96: Yes | K96: Yes | L96: Yes
A97: https://4ammedia.zendesk.com/agent/tickets/304558 | B97: 46259 | C97: =IF(B97="", "", TEXT(B97, "ddd")) -> Tue | D97: =IF(E97="Yes",0.05,0) +IF(F97="Yes",0.1,0) +IF(G97="Yes",0.15,0) +IF(H97="Yes",0.15,0) +IF(I97="Yes",0.05,0) +IF(J97="Yes",0.05,0) +IF(K97="Yes",0.15,0) +IF(L97="Yes",0.3,0) -> 1 | E97: Yes | F97: Yes | G97: Yes | H97: Yes | I97: Yes | J97: Yes | K97: Yes | L97: Yes
A98: https://4ammedia.zendesk.com/agent/tickets/304633 | B98: 46259 | C98: =IF(B98="", "", TEXT(B98, "ddd")) -> Tue | D98: =IF(E98="Yes",0.05,0) +IF(F98="Yes",0.1,0) +IF(G98="Yes",0.15,0) +IF(H98="Yes",0.15,0) +IF(I98="Yes",0.05,0) +IF(J98="Yes",0.05,0) +IF(K98="Yes",0.15,0) +IF(L98="Yes",0.3,0) -> 1 | E98: Yes | F98: Yes | G98: Yes | H98: Yes | I98: Yes | J98: Yes | K98: Yes | L98: Yes
A99: https://4ammedia.zendesk.com/agent/tickets/306715 | B99: 46260 | C99: =IF(B99="", "", TEXT(B99, "ddd")) -> Wed | D99: =IF(E99="Yes",0.05,0) +IF(F99="Yes",0.1,0) +IF(G99="Yes",0.15,0) +IF(H99="Yes",0.15,0) +IF(I99="Yes",0.05,0) +IF(J99="Yes",0.05,0) +IF(K99="Yes",0.15,0) +IF(L99="Yes",0.3,0) -> 1 | E99: Yes | F99: Yes | G99: Yes | H99: Yes | I99: Yes | J99: Yes | K99: Yes | L99: Yes
A100: https://4ammedia.zendesk.com/agent/tickets/306877 | B100: 46260 | C100: =IF(B100="", "", TEXT(B100, "ddd")) -> Wed | D100: =IF(E100="Yes",0.05,0) +IF(F100="Yes",0.1,0) +IF(G100="Yes",0.15,0) +IF(H100="Yes",0.15,0) +IF(I100="Yes",0.05,0) +IF(J100="Yes",0.05,0) +IF(K100="Yes",0.15,0) +IF(L100="Yes",0.3,0) -> 1 | E100: Yes | F100: Yes | G100: Yes | H100: Yes | I100: Yes | J100: Yes | K100: Yes | L100: Yes
A101: https://4ammedia.zendesk.com/agent/tickets/306921 | B101: 46260 | C101: =IF(B101="", "", TEXT(B101, "ddd")) -> Wed | D101: =IF(E101="Yes",0.05,0) +IF(F101="Yes",0.1,0) +IF(G101="Yes",0.15,0) +IF(H101="Yes",0.15,0) +IF(I101="Yes",0.05,0) +IF(J101="Yes",0.05,0) +IF(K101="Yes",0.15,0) +IF(L101="Yes",0.3,0) -> 1 | E101: Yes | F101: Yes | G101: Yes | H101: Yes | I101: Yes | J101: Yes | K101: Yes | L101: Yes
A102: https://4ammedia.zendesk.com/agent/tickets/308578 | B102: 46261 | C102: =IF(B102="", "", TEXT(B102, "ddd")) -> Thu | D102: =IF(E102="Yes",0.05,0) +IF(F102="Yes",0.1,0) +IF(G102="Yes",0.15,0) +IF(H102="Yes",0.15,0) +IF(I102="Yes",0.05,0) +IF(J102="Yes",0.05,0) +IF(K102="Yes",0.15,0) +IF(L102="Yes",0.3,0) -> 1 | E102: Yes | F102: Yes | G102: Yes | H102: Yes | I102: Yes | J102: Yes | K102: Yes | L102: Yes
A103: https://4ammedia.zendesk.com/agent/tickets/308822 | B103: 46261 | C103: =IF(B103="", "", TEXT(B103, "ddd")) -> Thu | D103: =IF(E103="Yes",0.05,0) +IF(F103="Yes",0.1,0) +IF(G103="Yes",0.15,0) +IF(H103="Yes",0.15,0) +IF(I103="Yes",0.05,0) +IF(J103="Yes",0.05,0) +IF(K103="Yes",0.15,0) +IF(L103="Yes",0.3,0) -> 1 | E103: Yes | F103: Yes | G103: Yes | H103: Yes | I103: Yes | J103: Yes | K103: Yes | L103: Yes
A104: https://4ammedia.zendesk.com/agent/tickets/308896 | B104: 46261 | C104: =IF(B104="", "", TEXT(B104, "ddd")) -> Thu | D104: =IF(E104="Yes",0.05,0) +IF(F104="Yes",0.1,0) +IF(G104="Yes",0.15,0) +IF(H104="Yes",0.15,0) +IF(I104="Yes",0.05,0) +IF(J104="Yes",0.05,0) +IF(K104="Yes",0.15,0) +IF(L104="Yes",0.3,0) -> 1 | E104: Yes | F104: Yes | G104: Yes | H104: Yes | I104: Yes | J104: Yes | K104: Yes | L104: Yes
... A107: https://4ammedia.zendesk.com/agent/tickets/314018 | B107: 46262 | C107: =IF(B107="", "", TEXT(B107, "ddd")) -> Fri | D107: =IF(E107="Yes",0.05,0) +IF(F107="Yes",0.1,0) +IF(G107="Yes",0.15,0) +IF(H107="Yes",0.15,0) +IF(I107="Yes",0.05,0) +IF(J107="Yes",0.05,0) +IF(K107="Yes",0.15,0) +IF(L107="Yes",0.3,0) -> 1 | E107: Yes | F107: Yes | G107: Yes | H107: Yes | I107: Yes | J107: Yes | K107: Yes | L107: Yes
C108: Final QA Score | D108: =AVERAGE(D93:D107) -> 1 | L108: Final QA Score | M108: =SUM(M93:M107)/75*0.1 -> 0
A109: Week (Aug 31, - Sep 6,2026)
